Workbook

Sheet CA 1996
C2: CONTROL TRÁMITE DE CONCESIÓN DE AGUAS | BP2: Código | BQ2: RE-AA-20
BP3: Versión | BQ3: 8
BP4: Fecha | BQ4: 45617
A6: DATOS DE LA SOLICITUD | L6: REQUERIMIENTO | Q6: PAGO SERVICIOS DE EVALUACION | V6: AUTO | Y6: CONCEPTO TECNICO | AF6: REQUERIMIENTO | AK6: ACTO ADMINISTRATIVO | AR6: RECURSO DE REPOSICION | AT6: ACTO ADMINISTRATIVO RECURSO DE REPOSICION | AY6: MEMORIAS DE CALCULO | BH6: RECIBO A SATISFACCION DE OBRAS | BQ6: OBSERVACIONES
A7: No. Radicado | B7: Fecha Radicado | C7: No. Expediente | D7: Solicitante/Interesado | E7: Cédula de ciudadanía - NIT | F7: Municipio | G7: Vereda | H7: Tipo de Fuente | I7: Fuente | J7: Nombre de la Fuente | K7: Uso | L7: No. Oficio/ Auto de Requerimiento | M7: Fecha Oficio/ Auto de Requerimiento | N7: Nombre de quién proyectó | O7: Radicado Oficio de entrada | P7: Fecha oficio de entrada | Q7: No. de la Factura | R7: Valor tabla única (Factura) | S7: Valor Facturado | T7: Valor Cancelado | U7: Fecha del pago servicio de evaluación | V7: No. Auto admite y fija | W7: Fecha Auto admite y fija | X7: Nombre de quién proyectó | Y7: Fecha Visita técnica | Z7: Nombre del técnico | AA7: Fecha Concepto técnico | AB7: Caudal Fuente | AC7: Caudal Disponible | AD7: Caudal Otorgado | AE7: Número de Usuarios | AF7: No. Auto de Requerimiento | AG7: Fecha Auto de Requerimiento | AH7: Nombre de quién proyectó | AI7: Radicado Oficio de entrada | AJ7: Fecha oficio de entrada | AK7: No. Acto Administrativo | AL7: Fecha Acto Administrativo | AM7: Nombre de quién proyectó | AN7: Otorgada | AO7: Negada | AP7: Fecha Notificación | AQ7: Fecha ejecutoria | AR7: No. Radicado | AS7: Fecha Radicado | AT7: No. Acto Administrativo | AU7: Fecha Acto Administrativo | AV7: Nombre de quién proyectó | AW7: Modifica/ Aclara / Confirma/ Adiciona /Niega | AX7: Fecha Notificación | AY7: No. Radicado | AZ7: Fecha Radicado | BA7: Auto Requer. | BB7: Fecha Requer. | BC7: Nombre de quién proyecto | BD7: No. Acto Administrativo | BE7: Fecha Act Administrativo | BF7: Nombre de quien proyectó | BG7: Cumple o NO | BH7: No. Radicado del usuario | BI7: Fecha Radicado | BJ7: Fecha de visita técnica | BK7: Fecha Informe técnico | BL7: Nombre del técnico | BM7: No. Acto Administrativo | BN7: Fecha Acto Administrativo | BO7: Nombre de quién proyectó | BP7: Cumple o NO
A8: 2726 | B8: 32780 | C8: CA 160-96 | D8: ACUEDUCTO CHORRO BLANCO | E8: 4276408 | F8: TIBANA | G8: QUICHATOQUE | H8: SUPERFICIAL | I8: QUEBRADA | J8: CHORRO BLANCO | K8: DOMESTICO Y ABREVADERO | L8: N/A | M8: N/A | N8: N/A | O8: N/A | P8: N/A | Q8: N/A | R8: N/A | S8: N/A | T8: N/A | U8: N/A | V8: N/A | W8: N/A | X8: N/A | Y8: N/A | Z8: N/A | AA8: N/A | AB8: N/A | AC8: N/A | AD8: N/A | AE8: N/A | AF8: N/A | AG8: N/A | AH8: N/A | AI8: N/A | AJ8: N/A | AK8: RES 254 RES629 RES921 RES651 | AL8: 28/09/1990 02/09/1996 29/12/2000 23/08/2007 | AM8: N/A | AN8: X | AP8: 39349 | AQ8: 39356 | AR8: N/A | AS8: N/A | AT8: N/A | AU8: N/A | AV8: N/A | AW8: N/A | AX8: N/A | AY8: 2013ER5281 | AZ8: 41620 | BA8: N/A | BB8: N/A | BC8: N/A | BD8: 41739 | BE8: 41739 | BF8: HERCYV | BG8: SI | BH8: N/A | BI8: N/A | BJ8: N/A | BK8: N/A | BL8: N/A | BM8: 165 | BN8: 42822 | BO8: JULIAN SUAREZ | BP8: NO | BQ8: PARA PERDIDA DE FUERZA
A9: 1209 2007ER608 | B9: 15/11/1995 07/02/2007 | C9: CA 136-96 | D9: RODRIGO JOSE QUINTANA MUÑOZ Y OTROS | E9: 7167299 | F9: TURMEQUE | G9: ROSALES | H9: SUPERFICIAL | I9: NACIMIENTO | J9: EL MANANTIAL | K9: DOMESTICO PECUARIO AGRICOLA | V9: 3/06/1996 1443 | W9: 3/06/1996 02/11/2021 | X9: N/A | Y9: 35230 | AA9: 35115 | AB9: N/A | AC9: N/A | AD9: N/A | AE9: N/A | AF9: N/A | AG9: N/A | AH9: N/A | AI9: N/A | AJ9: N/A | AK9: RES 180 RES 238 RES 1195 | AL9: 27/02/1997 03/06/2011 08/11/2022 | AM9: NOHORA P PERILLA JEFER AVILA | AN9: X | AP9: 35508 | AQ9: 35521 | AR9: N/A | AS9: N/A | AT9: N/A | AU9: N/A | AV9: N/A | AW9: N/A | AX9: N/A | AY9: 808 2848 | AZ9: 24/02/2004 04/10/2023 | BA9: N/A | BB9: N/A | BC9: N/A | BD9: 461 750 162 | BE9: 10/06/2004 13/08/2025 23/02/2026 | BF9: YAMILE MILENA G | BG9: SI SI | BH9: 2004ER4579 | BI9: 38259 | BJ9: 38275 | BK9: 38309 | BL9: HENRY LESMES | BM9: 38315 | BN9: 38315 | BO9: YAMILE C | BP9: SI | BQ9: VIGENTE HASTA EL 2032
A10: 334 | B10: 35116 | C10: CA 267-96 | D10: ROBERTO RATIVA BERNAL | E10: 1008756 | F10: BOYACA | G10: VANEGAS | H10: SUPERFICIAL | I10: NACIMIENTO | J10: BUENOS AIRES | K10: DOMESTICO | L10: N/A | M10: N/A | N10: N/A | O10: N/A | P10: N/A | Q10: N/A | R10: N/A | S10: N/A | T10: N/A | U10: N/A | V10: N/A | W10: N/A | X10: N/A | Y10: N/A | Z10: N/A | AA10: N/A | AB10: N/A | AC10: N/A | AD10: N/A | AE10: N/A | AF10: N/A | AG10: N/A | AH10: N/A | AI10: N/A | AJ10: N/A | AK10: 1102 | AL10: 45650 | AM10: N/A | AO10: DESISTIDA | AP10: N/A | AQ10: N/A | AR10: N/A | AS10: N/A | AT10: N/A | AU10: N/A | AV10: N/A | AW10: N/A | AX10: N/A | AY10: N/A | AZ10: N/A | BA10: N/A | BB10: N/A | BC10: N/A | BD10: N/A | BE10: N/A | BF10: N/A | BG10: N/A | BH10: N/A | BI10: N/A | BJ10: N/A | BK10: N/A | BL10: N/A | BM10: N/A | BN10: N/A | BO10: N/A | BP10: N/A | BQ10: DESISTIDA PENDENTE NOTIFICACION Y ARCHIVO
A11: 2130 2018ER7751 | B11: 1/08/1996 23/10/2018 | C11: CA 356-96 | D11: MARTA PATRICIA PARRA | E11: 40015708 | F11: TIBANA | G11: PIEDRA DE CANDELA | H11: SUPERFICIAL | I11: NACIMIENTO | J11: TOPAGA Y PANTANOS | L11: N/A | M11: N/A | N11: N/A | O11: N/A | P11: N/A | Q11: N/A 623 | R11: N/A 146857 | S11: N/A 146857 | T11: N/A 3,000 146857 | U11: N/A 20/01/2007 23/10/2018 | V11: 29/08/1996 09/02/2007 318 | W11: 29/08/1996 09/02/2007 08/05/2019 | X11: NJR JEFER AVILA | Y11: 17/09/1996 27/02/2007 28/05/2019 20/02/2020 n/a | Z11: JOSE MIGUEL LARA JORGE MONROY JHHON RODRIGUEZ DIEGO MORENO | AA11: 17/09/1996 12/03/2007 30/05/2019 20/02/2020 01/11/2022 | AB11: 12LTS/SEG | AC11: N/A | AD11: N/A | AE11: N/A | AF11: N/A 6191 661 221 1718 0106 0483 | AG11: N/A 21/07/2005 09/09/2019 01/09/2022 12/03/2025 27/03/2026 | AH11: N/A NAYDA ROMERO y cuesta IVONE GUTIERREZ JUAN CRUZ LEO GOMEZ DANIEL RODRIGUEZ | AI11: N/A 2005ER5558 2019ER7559 3702 2022ER9868 | AJ11: N/A 21/09/2005 27/09/2019 19/06/2020 03/10/2022 | AK11: 1113 0467 MODIFICA 370 129 886 | AL11: 27/12/1996 11/07/1997 28/05/2007 04/02/2009 26/11/2019 | AM11: NOHORA MAURICIO ROJAS | AN11: X | AP11: 10/01/1996 08/10/1997 28/05/2007 24/03/2009 | AQ11: 35089 | AR11: N/A | AS11: N/A | AT11: N/A | AU11: N/A | AV11: N/A | AW11: N/A | AX11: N/A | AY11: 1766 5223 2020ER785 | AZ11: 22/04/2002 21/07/2009 07/02/2020 | BA11: N/A | BB11: N/A | BC11: N/A | BD11: 527 1418 | BE11: 2/08/2002 19/12/2022 | BF11: MERCEDES YEIMI GARCIA | BG11: SI | BH11: 6070 | BI11: 37483 | BJ11: 37601 | BK11: 37602 | BL11: heNRY LESMES | BQ11: EXPEDIENTE SE ENCUENTRA REQUERIDO DESDE EL 07/04/2026
A12: 3227 | B12: 35309 | C12: CA 115-96 | D12: ACUEDUCTO EL CEDRO | F12: NUEVO COLON | G12: CARBONERA SUR Y CENRO RURAL | H12: SUPERFICIAL | I12: NACIMIENTO | J12: EL CEDRO | K12: DOMESTICO Y ABREVADERO | L12: N/A | M12: N/A | N12: N/A | O12: N/A | P12: N/A | Q12: N/A | R12: N/A | S12: N/A | T12: 3000 | U12: N/A | V12: N/A 16/02/2006 281 | W12: N/A 16/02/2006 27/04/2017 | X12: N/A JAVIER FREDY PIÑEROS | Y12: N/A 06/02/2006 06/04/2016 11/08/2020 09/07/2021 | Z12: JOSE MIGUEL LARA ALFREDO RONALD RAMIREZ EDGAR MORENO angela RAMOS | AA12: 11/09/1995 29/03/2006 23/05/2016 28/08/2020 16/06/2021 | AB12: N/A 5,09 | AC12: N/A 0,83 | AD12: N/A 0,83 | AE12: 480 240 | AF12: 21/07/2005 28/09/2020 881 1841 | AG12: 21/07/2005 28/09/2020 21/12/2021 | AK12: 112 844 204 AMPLIA 329 ACUMULA Y PRORROGA 311 | AL12: 14/02/2026 01/08/2006 07/05/2015 30/06/2016 07/07/2017 | AM12: JAVIER C JULIAN S JEFER A MAIRA CARRILLO | AN12: X | AP12: 22/03/1996 29/08/2006 | AQ12: N/A | AR12: N/A | AS12: N/A | AT12: N/A | AU12: N/A | AV12: N/A | AW12: N/A | AX12: N/A | AY12: 2006ER5504 | AZ12: 39014 | BA12: 2009EE2553 | BB12: 2009EE2553 | BC12: DIANA JUANITA | BD12: 764 | BE12: 42725 | BF12: XIMENA B. | BG12: N/A | BH12: N/A | BI12: N/A | BJ12: N/A | BK12: N/A | BL12: N/A | BM12: N/A | BN12: N/A | BO12: N/A | BP12: N/A | BQ12: expediente fue requerido en 2021
A13: 3548 | B13: 35125 | C13: CA 292/96 | D13: RAFAEL MUÑOZ MORENO | E13: 1186479 | F13: VENTAQUEMADA | G13: CAPELLANIA | H13: SUPERFICIAL | I13: qUEBRADA | J13: RIO CACHUCHITA | K13: RIEGO | L13: N/A | M13: N/A | N13: N/A | O13: N/A | P13: N/A | Q13: N/A 0517 | R13: N/A | S13: N/A 6000 | T13: N/A 6000 | U13: N/A 08/08/1996 | V13: 3/06/1996 13/02/2006 | W13: 3/06/1996 13/02/2006 | X13: NJR JAVIER C | Y13: 19/06/1996 28/02/2006 | Z13: JOSE MIGUEL LARA alfredo | AA13: 19/06/2006 21/03/2006 | AB13: 513LTXS | AC13: 1,50LTS/S | AD13: 1,50LTS/S | AE13: 12 | AF13: N/A | AG13: N/A | AH13: N/A | AI13: N/A | AJ13: N/A | AK13: 570 01089 542 357 perdida fuerza ejec 1426 | AL13: 31/07/1996 29/11/2002 25/05/2006 19/05/2021 24/12/2024 | AM13: NOHORA MERCEDES javier c PAULA MORENO | AN13: X | AP13: 8/08/1996 12/06/2006 | AQ13: N/A | AR13: N/A | AS13: N/A | AT13: N/A | AU13: N/A | AV13: N/A | AW13: N/A | AX13: N/A | AY13: 4838 | AZ13: 37175 | BA13: 4821 | BB13: 37404 | BC13: ana elvia | BD13: 163 | BE13: 37708 | BF13: MERCEDES | BG13: SI | BH13: N/A | BI13: N/A | BJ13: N/A | BK13: N/A | BL13: N/A | BM13: 37886 | BN13: 37886 | BO13: MERCEDES | BP13: SI | BQ13: EXPEDIENTE SE ENCUENTRA REQUERIDO DESDE EL 24/12/2024 CON CITACION DE NOTIFICACION PERSONAL DE 27/12/2024
A14: 4014 | B14: 34436 | C14: CA4014/96 | D14: JOSE ARGEMIRO VELANDIA | E14: 19397583 | F14: NUEVO COLON | G14: FIOTA | H14: SUPERFICIAL | I14: NACIMIENTO | J14: LA RINCONADA | K14: DOMESTICO | L14: N/A | M14: N/A | N14: N/A | O14: N/A | P14: N/A | Q14: N/A 0388 | R14: N/A | S14: N/A 3000 | T14: N/A 3000 | U14: N/A 09/05/1996 | V14: N/A | W14: N/A 05/09/2016 | X14: N/A | Y14: 13/09/1995 27/11/2003 08/09/2004 06/04/2006 26/11/2011 10/12/2014 24/04/2018 28/07/2023 | Z14: RODRIGO CORREAL ALFREDO HENRY LESMES alexander CASTRO ANDRES CORTEZ JEISON SANCHEZ JAIDER ARIAS maria paula sanchez | AA14: 13/09/1995 22/01/2004 25/11/2004 01/11/2011 30/12/2014 10/07/2017 29/12/2023 | AB14: N/A | AC14: N/A | AD14: N/A | AE14: N/A | AF14: N/A 1057 4705 753 796 | AG14: N/A 02/02/2012 15/07/2016 24/08/2014 14/08/2024 | AH14: N/A JULIAN MORENO LORENA BARON leonardo gomez | AI14: N/A 2014ER4712 2016ER4699 | AJ14: N/A 08/10/2014 05/08/2014 | AK14: 108 619 300 235prorroga 713 corrige yerro | AL14: 13/02/1996 09/06/2006 26/03/2018 13/05/2019 01/10/2019 | AM14: JVED FRANCY MAURICIO ROJAS JAVIER ORTIZ | AN14: X | AP14: 35145 | AQ14: N/A | AR14: N/A | AS14: N/A | AT14: N/A | AU14: N/A | AV14: N/A | AW14: N/A | AX14: N/A | AY14: 4688 2019ER6305 | AZ14: 26/09/2000 12/08/2019 | BA14: N/A | BB14: N/A | BC14: N/A | BD14: N/A 0119 922 | BE14: N/A 28/03/2001 01/09/2022 | BF14: N/A juan ´pablo cruz | BG14: SI | BH14: 85 | BI14: 38043 | BJ14: 38078 | BK14: 38091 | BL14: HENRY LESMES | BM14: N/A | BN14: N/A | BO14: N/A | BP14: N/A | BQ14: Expediente se encuentra requerido de fecha 09/07/2026

Sheet CA 1997
C1: CONTROL TRAMITE DE CONCESION DE AGUAS 1997 | CF1: Código | CG1: RE-AA-20
CF2: Versión | CG2: 7
CF3: Fecha | CG3: 44411
A4: DATOS DE LA SOLICITUD | Q4: REQUERIMIENTO | X4: PAGO SERVICIOS DE EVALUACION | AC4: AUTO | AF4: CONTROL- DIAS TRANSCURRIDOS HASTA FECHA DE VISITA | AG4: CONCEPTO TECNICO | AT4: CONTROL- DIAS TRANSCURRIDOS DE LA RADICACION AL CONCEPTO CON Vo.Bo. | AV4: REQUERIMIENTO | BA4: ACTO ADMINISTRATIVO | BH4: RECURSO DE REPOSICION | BJ4: ACTO ADMINISTRATIVO RECURSO DE REPOSICION | BO4: MEMORIAS DE CALCULO | BX4: RECIBO A SATISFACCION DE OBRAS | CG4: OBSERVACIONES
A5: No. Radicado | B5: Fecha Radicado | C5: No. Expediente | D5: RADICADO EN VITAL | E5: Solicitante/Interesado | F5: Cédula de ciudadanía - NIT | G5: Dirección de correspondencia | H5: Municipio - CONCESION DE AGUAS | I5: Teléfono | J5: Correo Electrónico | K5: Lugar de la captación (Vereda) | L5: Tipo de Fuente | M5: Fuente | N5: Nombre de la Fuente | O5: Uso | P5: APERTURÓ | Q5: No. Oficio/ Auto de Requerimiento | R5: Fecha Oficio/ Auto de Requerimiento | S5: Nombre de quién proyectó | T5: DIAS DEL RADICADO AL REQUERIMIENTO | U5: Radicado Oficio de entrada | V5: Fecha oficio de entrada | W5: DESCRIPCION DEL REQUERIMIENTO | X5: No. de la Factura | Y5: Valor tabla única (Factura) | Z5: Valor Facturado | AA5: Valor Cancelado | AB5: Fecha del pago servicio de evaluación | AC5: No. Auto admite y fija | AD5: Fecha Auto admite y fija | AE5: Nombre de quién proyectó | AG5: Fecha Visita técnica | AH5: Nombre del técnico | AI5: FECHA LIMITE ENTREGA DE CONCEPTO | AJ5: DIAS CALENDARIO TRANSCURRIDOS SEGÚN FECHA LIMITE DE ENTRE DE CONCEPTO Y FECHA DE VISITA TECNICA | AK5: ALERTAS | AL5: Fecha entrega a Revisión Informe - Lider | AM5: Entrega de Informe al técnico para corrección | AN5: Entrega de concepto corregido | AO5: Fecha Concepto técnico | AP5: Caudal Fuente | AQ5: Caudal Disponible | AR5: Caudal Otorgado | AS5: Número de Usuarios | AU5: FECHA DE ASIGNACION CONCEPTO AL AREA JURIDICO | AV5: No. Auto de Requerimiento | AW5: Fecha Auto de Requerimiento | AX5: Nombre de quién proyectó | AY5: Radicado Oficio de entrada | AZ5: Fecha oficio de entrada | BA5: No. Acto Administrativo | BB5: Fecha Acto Administrativo | BC5: Nombre de quién proyectó | BD5: Otorgada | BE5: Negada | BF5: Fecha Notificación | BG5: Fecha ejecutoria | BH5: No. Radicado | BI5: Fecha Radicado | BJ5: No. Acto Administrativo | BK5: Fecha Acto Administrativo | BL5: Nombre de quién proyectó | BM5: Modifica/ Aclara / Confirma/ Adiciona /Niega | BN5: Fecha Notificación | BO5: No. Radicado | BP5: Fecha Radicado | BQ5: Auto Requer. | BR5: Fecha Requer. | BS5: Nombre de quién proyecto | BT5: No. Acto Administrativo | BU5: Fecha Act Administrativo | BV5: Nombre de quien proyectó | BW5: Cumple o NO | BX5: No. Radicado del usuario | BY5: Fecha Radicado | BZ5: Fecha de visita técnica | CA5: Fecha Informe técnico | CB5: Nombre del técnico | CC5: No. Acto Administrativo | CD5: Fecha Acto Administrativo | CE5: Nombre de quién proyectó | CF5: Cumple o NO | CH5: ULTIMA ACTULIZACION | CI5: FECHA ACTUALIZAICON
C6: CA 007-97 | Q6: 2025EE6209 | R6: 07/072025 | S6: KAREN BARRETO | U6: 2025ER6592 | V6: 45828 | CB6: NA | CC6: NA | CD6: NA | CE6: NA | CF6: NA | CG6: SE ACTUALIZO INFORMACION TOMO DOS | CH6: KAREN BARRETO | CI6: 45849
C7: C.A. 051/97 | E7: WILLIAM MANCIPE MANCIPE | F7: 3206495 | G7: Predio Buenos Aites Vereda San Josi Tibaná– Boyacá | H7: TIBANA | I7: 320 267 3336 - 311 462 1454 | J7: williammancipe79@gmail.com - hernanmanrtinez608@hotmail.com | K7: El Carmen San Jose | L7: SUPERFICIAL | M7: NACIMIENTO | N7: SAN PEDRO | O7: DOMESTICO AGRICOLA PECUARIO | P7: NA | Q7: NA | R7: NA | S7: NA | T7: NA | U7: NA | V7: NA | W7: NA | X7: NA | Y7: NA | Z7: NA | AA7: NA | AB7: NA | AC7: NA | AD7: NA | AE7: NA | AF7: NA | AG7: NA | AH7: NA | AI7: NA | AJ7: NA | AK7: NA | AL7: NA | AM7: NA | AN7: NA | AO7: NA | AP7: NA | AQ7: NA | AR7: NA | AS7: NA | AT7: NA | AU7: NA | AV7: NA | AW7: NA | AX7: NA | AY7: NA | AZ7: NA | BA7: NA | BB7: NA | BC7: NA | BD7: 549 537 344 | BE7: 29/08/2999 25/05/2006 30/06/2016 | BF7: 42578 | BG7: 42592 | BH7: NA | BI7: NA | BJ7: NA | BK7: NA | BL7: NA | BM7: NA | BN7: NA | BO7: NA | BP7: NA | BQ7: NA | BR7: NA | BS7: NA | BT7: NA | BU7: NA | BV7: NA | BW7: NA | BX7: NA | BY7: NA | BZ7: NA | CA7: NA | CB7: NA | CC7: NA | CD7: NA | CE7: NA | CF7: NA | CG7: Requerido mediante oficio No. 2026EE6396 -Prorroga y Modificación | CH7: MILENA GALINDO | CI7: 46183
C8: C.A 061-97 | E8: ACUEDUCTO URBANO DE TURMEQUE | F8: 820003743-2 | G8: carrera 1 con calle 1 | H8: TURMEQUE | I8: 3133415820 | J8: acueductoturmeque@hotmail.com | L8: SUPERFICIAL | M8: nacimiento | N8: El Gacal El Pedregral El Arrayan | O8: DOMESTICO | P8: NA | Q8: NA | R8: NA | S8: NA | T8: NA | U8: NA | V8: NA | W8: NA | X8: NA | Y8: NA | Z8: NA | AA8: NA | AB8: NA | AC8: NA | AD8: NA | AE8: NA | AF8: NA | AG8: NA | AH8: NA | AI8: NA | AJ8: NA | AK8: NA | AL8: NA | AM8: NA | AN8: NA | AO8: NA | AP8: NA | AQ8: NA | AR8: NA | AS8: NA | AT8: NA | AU8: NA | AV8: NA | AW8: NA | AX8: NA | AY8: NA | AZ8: NA | BA8: 51 930-Prorroga 360-Prorroga | BB8: 13/03/1998 27-10-08 19-06-2019 | BC8: Luis Alfondo Plinio Forero | BD8: x | BF8: 43675 | BG8: 43691 | BH8: NA | BI8: NA | BJ8: NA | BK8: NA | BL8: NA | BM8: NA | BN8: NA | BO8: 2021ER7374 | BP8: 40788 | BQ8: NA | BR8: NA | BS8: NA | BT8: RES1458 | BU8: 44483 | BV8: Jefer Avila | BW8: SI | BX8: 2022ER5691 | BY8: 44718 | BZ8: 44743 | CA8: 44750 | CB8: DIEGO MORENO | CC8: 778 | CD8: 44776 | CE8: JEVER AVILA | CF8: SI | CG8: Por medio del Auto No. 109 de fecha 30-02-2026 no se aprueba PUEAA y se realizo requerimiento con el fin de ajustar el PUEAA (30 dias) | CH8: karen Barreto | CI8: 46073
A9: 1997ER3787 | B9: 35695 | C9: CA 095-97 | E9: RIGOBERTO PULIDO MUÑOZ Y OTROS | F9: 4286627 | G9: Vereda Chirata | H9: Turmeque | I9: 3123815808 | J9: N/A | L9: SUPERFICIAL | M9: Nacimiento | N9: La Leontina | O9: Domestico Pecuario | P9: N/A | Q9: N/A | R9: N/A | S9: N/A | T9: N/A | U9: N/A | V9: N/A | W9: N/A | X9: N/A | Y9: N/A | Z9: N/A | AA9: N/A | AB9: N/A | AC9: N/A | AD9: N/A | AE9: N/A | AF9: N/A | AG9: N/A | AH9: N/A | AI9: N/A | AJ9: N/A | AK9: N/A | AL9: N/A | AM9: N/A | AN9: N/A | AO9: N/A | AP9: N/A | AQ9: N/A | AR9: N/A | AS9: N/A | AT9: N/A | AU9: N/A | AV9: N/A | AW9: N/A | AX9: N/A | AY9: N/A | AZ9: N/A | BA9: 723 450 596 | BB9: 30/12/1997 20/06/2007 30/09/2020 | BC9: ANA ELVIA ANA CELIA | BD9: X | BF9: 44109 | BG9: 44125 | BH9: N/A | BI9: N/A | BJ9: N/A | BK9: N/A | BL9: N/A | BM9: N/A | BN9: N/A | BO9: N/A | BP9: N/A | BQ9: N/A | BR9: N/A | BS9: N/A | BT9: N/A | BU9: 38714 | BV9: JUAN PABLO | BW9: SI | BX9: N/A | BY9: N/A | BZ9: N/A | CA9: N/A | CB9: N/A | CC9: N/A | CD9: N/A | CE9: N/A | CF9: N/A | CG9: Requerido mediante Auto No. 212 de 2025 | CH9: MILENA GALINDO | CI9: 45413
A10: 1997EE4749 | B10: 35754 | C10: CA 122-97 | E10: ASOCIACION DE SUSCRIPTORES DEL ACUEDUCTO JABONERA SUR DEL MUNICIPIO DE NUEVO COLON DEPARTAMENTO DE BOYACA | F10: 4182613 | G10: Jabonera Sur | H10: Nuevo Colon
C13: CONTROL TRÁMITE DE CONCESIÓN DE AGUAS | BP13: Código | BQ13: RE-AA-20
BP14: Versión | BQ14: 8
BP15: Fecha | BQ15: 45617
A17: DATOS DE LA SOLICITUD | L17: REQUERIMIENTO | Q17: PAGO SERVICIOS DE EVALUACION | V17: AUTO | Y17: CONCEPTO TECNICO | AF17: REQUERIMIENTO | AK17: ACTO ADMINISTRATIVO | AR17: RECURSO DE REPOSICION | AT17: ACTO ADMINISTRATIVO RECURSO DE REPOSICION | AY17: MEMORIAS DE CALCULO | BH17: RECIBO A SATISFACCION DE OBRAS | BQ17: OBSERVACIONES
A18: No. Radicado | B18: Fecha Radicado | C18: No. Expediente | D18: Solicitante/Interesado | E18: Cédula de ciudadanía - NIT | F18: Municipio | G18: Vereda | H18: Tipo de Fuente | I18: Fuente | J18: Nombre de la Fuente | K18: Uso | L18: No. Oficio/ Auto de Requerimiento | M18: Fecha Oficio/ Auto de Requerimiento | N18: Nombre de quién proyectó | O18: Radicado Oficio de entrada | P18: Fecha oficio de entrada | Q18: No. de la Factura | R18: Valor tabla única (Factura) | S18: Valor Facturado | T18: Valor Cancelado | U18: Fecha del pago servicio de evaluación | V18: No. Auto admite y fija | W18: Fecha Auto admite y fija | X18: Nombre de quién proyectó | Y18: Fecha Visita técnica | Z18: Nombre del técnico | AA18: Fecha Concepto técnico | AB18: Caudal Fuente | AC18: Caudal Disponible | AD18: Caudal Otorgado | AE18: Número de Usuarios | AF18: No. Auto de Requerimiento | AG18: Fecha Auto de Requerimiento | AH18: Nombre de quién proyectó | AI18: Radicado Oficio de entrada | AJ18: Fecha oficio de entrada | AK18: No. Acto Administrativo | AL18: Fecha Acto Administrativo | AM18: Nombre de quién proyectó | AN18: Otorgada | AO18: Negada | AP18: Fecha Notificación | AQ18: Fecha ejecutoria | AR18: No. Radicado | AS18: Fecha Radicado | AT18: No. Acto Administrativo | AU18: Fecha Acto Administrativo | AV18: Nombre de quién proyectó | AW18: Modifica/ Aclara / Confirma/ Adiciona /Niega | AX18: Fecha Notificación | AY18: No. Radicado | AZ18: Fecha Radicado | BA18: Auto Requer. | BB18: Fecha Requer. | BC18: Nombre de quién proyecto | BD18: No. Acto Administrativo | BE18: Fecha Act Administrativo | BF18: Nombre de quien proyectó | BG18: Cumple o NO | BH18: No. Radicado del usuario | BI18: Fecha Radicado | BJ18: Fecha de visita técnica | BK18: Fecha Informe técnico | BL18: Nombre del técnico | BM18: No. Acto Administrativo | BN18: Fecha Acto Administrativo | BO18: Nombre de quién proyectó | BP18: Cumple o NO
A19: 3879 | B19: 35407 | C19: CA 13/97 | D19: SANTIAGO ALFONSO VARGAS | E19: 4182699 | F19: NUEVO COLON | G19: JABONERA | H19: SUPERFICIAL | I19: NACIMIENTO | J19: EL PEDREGAL | K19: DOMESTICO | L19: N/A | M19: N/A | N19: N/A | O19: N/A | P19: N/A | Q19: N/A | R19: N/A | S19: N/A | T19: N/A | U19: N/A | V19: 13/01/1997 AUTO RENOV 05/02/2007 | W19: 13/01/1997 05/02/2007 | X19: NOHORA MERY | Y19: 28/02/1997 02/09/2004 19/02/2007 | Z19: JOSE MIGUEL LARA HENRY LESMES RAFAEL EDUARDO MORENO | AA19: 21/03/1997 02/09/2004 19/02/2007 | AB19: N/A 0,38 | AC19: N/A | AD19: 0,01 0,01 | AE19: 1 FAMILIA | AF19: N/A 1286 2352 | AG19: N/A 10/02/2005 21/03/2006 | AH19: N/A ALV | AI19: N/A 2006ER6762 | AJ19: N/A 27/12/2006 | AK19: 403 434 Prorroga 883 PERDIDA EJEC | AL19: 6/06/1997 15/06/2007 08/11/2024 | AM19: NOHORA riaño ALEJANDRA GUERRERO | AN19: X | AP19: 25/07/1997 21/11/2024 | AQ19: N/A | AR19: N/A | AS19: N/A | AT19: N/A | AU19: N/A | AV19: N/A | AW19: N/A | AX19: N/A | AY19: N/A | AZ19: N/A | BA19: N/A | BB19: N/A | BC19: N/A | BD19: N/A | BE19: N/A | BF19: N/A | BG19: N/A | BH19: N/A | BI19: N/A | BJ19: N/A | BK19: N/A | BL19: N/A | BM19: N/A | BN19: N/A | BO19: N/A | BP19: N/A | BQ19: Fecha actualizacion 23/09/2026 Yennyf ultima actuacion perdida de fuerza ejecutoria
A20: 3718 2018ER8654 | B20: 5/12/1996 27/11/2018 | C20: CA 04/97 | D20: LUIS ALFONSO ESPINOSA | E20: 4079569 | F20: CIENEGA | G20: TAPIAS | H20: SUPERFICIAL | I20: QUEBRADA TAPIAS | J20: POZO NEGRO | K20: RIEGO Y PECUARIA | L20: N/A | M20: N/A | N20: N/A | O20: N/A | P20: N/A | Q20: N/A 714 | R20: N/A 104756 | S20: N/A 104756 | T20: N/A 104756 | U20: N/A 08/02/2019 | V20: 13/01/1997 14/04/2008 RENOVA | W20: 13/01/1997 14/04/2008 | X20: NOHORA D SIERRA | Y20: 24/02/1997 22/06/2006 22/04/2008 04/11/2011 15/04/2019 17/06/2022 | Z20: JOSE MIGUEL LARA JUAN DAVID ASTRID CORTEZ LIZETH LOPEZ LINA SANTAMARIA | AA20: 3/04/1997 22/06/2006 13/05/2008 17/11/2012 23/04/2019 01/07/2022 | AB20: 1.33 | AC20: 1.33 | AD20: 1.61 | AE20: 3 FAMILIAS | AF20: N/A 1749 10554 5023 2019EE57 1603 2547 1993 | AG20: N/A 28/02/2006 27/11/2006 25/06/2007 03/01/2019 31/08/2022 09/11/2022 14/07/2023 | AH20: N/A FRANCY ALCIRA CRISTIAN MARTA SANCHEZ GERMAN RODRIGUEZ | AI20: N/A 2006ER1879 02871 2019ER1591 2022ER12379 | AJ20: N/A 17/04/2006 04/06/2007 06/03/2019 14/12/2022 | AK20: 398 778 179 ADM PRORRO 545 | AL20: 6/07/1997 08/09/2008 21/03/2019 12/08/2019 | AM20: NOHORA DSIERRA FREDY PIÑEROS JEFER AVILA | AN20: X | AP20: 2/02/1997 02/04/2019 | AQ20: N/A | AR20: N/A | AS20: N/A | AT20: N/A | AU20: N/A | AV20: N/A | AW20: N/A | AX20: N/A | AY20: 6613 | AZ20: 39792 | BA20: N/A | BB20: N/A | BC20: N/A | BD20: 39846 | BE20: 39847 | BF20: BFERERO | BG20: SI | BH20: N/A | BI20: N/A | BJ20: N/A | BK20: N/A | BL20: N/A | BM20: N/A | BN20: N/A | BO20: N/A | BP20: N/A | BQ20: Fecha actualizacion 23/09/2026 Yennyf ultima actuacion REQUERIDA
A21: 948 | B21: 35509 | C21: CA 37-97 | D21: JOSE LEVI SANCHEZ GONZALEZ | E21: 1159048 | F21: SOMONDOCO | G21: CUCUAVACA | I21: QUEBRADA LA HORCA | J21: SIN NOMBRE | K21: INDUSTRIAL | L21: N/A | M21: N/A | N21: N/A | O21: N/A | P21: N/A | Q21: N/A | R21: N/A | S21: N/A | T21: N/A | U21: N/A | V21: 17/04/1997 | W21: 35537 | X21: NOHORA | Y21: 3/06/1997 09/07/2006 18/01/2007 23/12/2010 25/04/2011 19/07/2011 16/10/2014 22/07/2015 | Z21: JOSE MIGUEL LARA JORGE MONROY WILSON LOZANO BLANCA CARO MARCO DURAN | AA21: 3/06/1997 29/06/2006 31/10/2006 07/01/2011 23/05/2011 19/08/2011 23/01/2012 04/12/2014 28/08/2015 | AB21: 4 | AC21: 4 | AD21: 3 | AE21: 1 FAMILIA | AF21: N/A 2942 5420 2006ee7005 5205 9529 2591 | AG21: N/A 05/04/2006 27/06/2006 30/08/2006 21/07/2009 20/10/2011 22/03/2012 | AH21: N/A FRANCY PRFD CAROLINA ROA | AI21: N/A 04317 2006ER2233 2006ER5258 2014ER3931 2015ER629 2015ER3317 | AJ21: N/A 20/10/1997 08/05/2006 10/10/2006 25/08/2014 12/02/2015 09/07/2015 | AK21: 507 701 APRUBAN PMA PARA INDUSTRIA 09/01/2007 admite renovac 272 PRORROGA 1105 | AL21: 12/08/1997 23/12/1997 07/05/2007 24/12/2024 | AM21: NOHORA PAULA MORENO | AN21: X | AP21: 20/08/1997 08/01/1998 | AQ21: N/A | AR21: N/A | AS21: N/A | AT21: N/A | AU21: N/A | AV21: N/A | AW21: N/A | AX21: N/A | AY21: N/A | AZ21: N/A | BA21: N/A | BB21: N/A | BC21: N/A | BD21: 39066 | BE21: 39066 | BF21: JAVIERC | BG21: SI | BH21: N/A | BI21: N/A | BJ21: N/A | BK21: N/A | BL21: N/A | BM21: 589 | BN21: 42286 | BO21: LORENA BARON | BP21: Cumple | BQ21: Fecha actualizacion 23/09/2026 Yennyf ultima actuacion perdida de fuerza ejecutoria EL SR FALLECIO
A22: 3565 | B22: 35681 | C22: 89/97 | D22: PARMENIO MENDOZA SUAREZ | E22: 133901 | F22: TIBANA | G22: JUANA RUIZ | J22: LAS CIRCAS | L22: N/A | M22: N/A | N22: N/A | O22: N/A | P22: N/A | Q22: N/A | R22: N/A | S22: N/A | T22: N/A | U22: N/A | V22: 35684 | W22: 35684 | X22: NOHORA | Y22: 28/11/1997 08/01/2003 17/06/2003 12/08/2003 18/05/2006 26/03/2008 21/10/2010 28/06/2011 14/12/2016 24/02/2017 | Z22: JOSE LARA HENRY LESMES ANDRES REYES ARMANDO MONROY WILSON LOZANO CARLOS ORTIZ DIEGO FARFAN LIZETH LOPEZ | AA22: 18/12/1997 26/01/2003 01/07/2003 12/08/2003 31/03/2008 011/2010 19/07/2011 27/12/2016 03/04/2017 | AB22: 0.43 | AC22: 0.43 | AD22: 0.06 | AE22: 35 FAMILIAS | AF22: N/A 2002 4958 2006EE6784 4011 369 7985 11850 AUTO REQUE 1029 3859 | AG22: N/A 12/05/2003 13/06/2006 10/05/2007 14/01/2011 24/08/2011 28/12/2011 30/10/2017 13/04/2023 | AH22: N/A JA MONROY SIERRA BRIYIT SACRISTAN LGRAMIREZ VANESA ROA KAREN BUITRAGO | AI22: N/A 01602 01777 4092 2007ER1564 2017ER3398 | AJ22: N/A 08/05/2003 21/05/2003 14/08/2006 21/03/2007 02/06/2017 | AK22: 83 auto 12/05/2003 AUTO 02/09/2003 AUTORENOVA 28/02/2008 783 915 273 NULIDAD 140 MODIFICA 1112 | AL22: 24/03/1998 28/02/2008 08/09/2008 27/10/2008 17/03/2009 05/04/2018 27/12/2024 | AM22: NOHORA SIERRA A MONSALVA JULIAN SUAREZ KAREN BARRETO | AN22: X | AP22: 29/04/1998 24/10/2008 19/06/2009 16/04/2018 | AQ22: N/A | AR22: N/A | AS22: N/A | AT22: N/A | AU22: N/A | AV22: N/A | AW22: N/A | AX22: N/A | AY22: N/A | AZ22: N/A | BA22: N/A | BB22: N/A | BC22: N/A | BD22: N/A | BE22: N/A | BF22: N/A | BG22: N/A | BH22: N/A | BI22: N/A | BJ22: N/A | BK22: N/A | BL22: N/A | BM22: N/A | BN22: N/A | BO22: N/A | BP22: N/A | BQ22: Fecha actualizacion 23/09/2026 Yennyf ultima actuacion perdida de fuerza ejecutoria NOTIFICACION POR CORREO

Sheet CA 1998
C1: CONTROL TRAMITE DE CONCESION DE AGUAS 1997 | CF1: Código | CG1: RE-AA-20
CF2: Versión | CG2: 7
CF3: Fecha | CG3: 44411
A4: DATOS DE LA SOLICITUD | Q4: REQUERIMIENTO | X4: PAGO SERVICIOS DE EVALUACION | AC4: AUTO | AF4: CONTROL- DIAS TRANSCURRIDOS HASTA FECHA DE VISITA | AG4: CONCEPTO TECNICO | AT4: CONTROL- DIAS TRANSCURRIDOS DE LA RADICACION AL CONCEPTO CON Vo.Bo. | AV4: REQUERIMIENTO | BA4: ACTO ADMINISTRATIVO | BH4: RECURSO DE REPOSICION | BJ4: ACTO ADMINISTRATIVO RECURSO DE REPOSICION | BO4: MEMORIAS DE CALCULO | BX4: RECIBO A SATISFACCION DE OBRAS | CG4: OBSERVACIONES
A5: No. Radicado | B5: Fecha Radicado | C5: No. Expediente | D5: RADICADO EN VITAL | E5: Solicitante/Interesado | F5: Cédula de ciudadanía - NIT | G5: Dirección de correspondencia | H5: Municipio - CONCESION DE AGUAS | I5: Teléfono | J5: Correo Electrónico | K5: Lugar de la captación (Vereda) | L5: Tipo de Fuente | M5: Fuente | N5: Nombre de la Fuente | O5: Uso | P5: APERTURÓ | Q5: No. Oficio/ Auto de Requerimiento | R5: Fecha Oficio/ Auto de Requerimiento | S5: Nombre de quién proyectó | T5: DIAS DEL RADICADO AL REQUERIMIENTO | U5: Radicado Oficio de entrada | V5: Fecha oficio de entrada | W5: DESCRIPCION DEL REQUERIMIENTO | X5: No. de la Factura | Y5: Valor tabla única (Factura) | Z5: Valor Facturado | AA5: Valor Cancelado | AB5: Fecha del pago servicio de evaluación | AC5: No. Auto admite y fija | AD5: Fecha Auto admite y fija | AE5: Nombre de quién proyectó | AG5: Fecha Visita técnica | AH5: Nombre del técnico | AI5: FECHA LIMITE ENTREGA DE CONCEPTO | AJ5: DIAS CALENDARIO TRANSCURRIDOS SEGÚN FECHA LIMITE DE ENTRE DE CONCEPTO Y FECHA DE VISITA TECNICA | AK5: ALERTAS | AL5: Fecha entrega a Revisión Informe - Lider | AM5: Entrega de Informe al técnico para corrección | AN5: Entrega de concepto corregido | AO5: Fecha Concepto técnico | AP5: Caudal Fuente | AQ5: Caudal Disponible | AR5: Caudal Otorgado | AS5: Número de Usuarios | AU5: FECHA DE ASIGNACION CONCEPTO AL AREA JURIDICO | AV5: No. Auto de Requerimiento | AW5: Fecha Auto de Requerimiento | AX5: Nombre de quién proyectó | AY5: Radicado Oficio de entrada | AZ5: Fecha oficio de entrada | BA5: No. Acto Administrativo | BB5: Fecha Acto Administrativo | BC5: Nombre de quién proyectó | BD5: Otorgada | BE5: Negada | BF5: Fecha Notificación | BG5: Fecha ejecutoria | BH5: No. Radicado | BI5: Fecha Radicado | BJ5: No. Acto Administrativo | BK5: Fecha Acto Administrativo | BL5: Nombre de quién proyectó | BM5: Modifica/ Aclara / Confirma/ Adiciona /Niega | BN5: Fecha Notificación | BO5: No. Radicado | BP5: Fecha Radicado | BQ5: Auto Requer. | BR5: Fecha Requer. | BS5: Nombre de quién proyecto | BT5: No. Acto Administrativo | BU5: Fecha Act Administrativo | BV5: Nombre de quien proyectó | BW5: Cumple o NO | BX5: No. Radicado del usuario | BY5: Fecha Radicado | BZ5: Fecha de visita técnica | CA5: Fecha Informe técnico | CB5: Nombre del técnico | CC5: No. Acto Administrativo | CD5: Fecha Acto Administrativo | CE5: Nombre de quién proyectó | CF5: Cumple o NO | CH5: ULTIMA ACTULIZACION | CI5: FECHA ACTUALIZAICON
C6: CA 039-98 | E6: ASOCIAICON DE SUSCRIPTORES ADUECUDTO EL TEJAR TEJAR ARRIBA TEJAR ABAJO Y CENTRO RURAL | F6: 900087289 | G6: NA | H6: NUEVO COLON | I6: 3123815808 | J6: acueductosncacutejar@gmail.com NCACUTEJAR@GMAIL.COM | K6: QUEBRADA EL ESPEJO | L6: Superficial | M6: Nacimiento | N6: QUEBRADA EL ESPEJO | O6: domestico | P6: N/A | Q6: 2025EE5138 2025EE10213 | R6: 10/06/2025 09/09/2025 | S6: KAREN BARRETO KAREN BARRETO | T6: N/A | U6: 2025ER5822 2025ER9561 | V6: 30/05/2025 25/08/2025 | W6: N/A | X6: N/A | Y6: N/A | Z6: N/A | AA6: N/A | AB6: N/A | AC6: N/A | AD6: N/A | AE6: N/A | AF6: N/A | AG6: N/A | AH6: N/A | AI6: N/A | AJ6: N/A | AK6: N/A | AL6: N/A | AM6: N/A | AN6: N/A | AO6: N/A | AP6: N/A | AQ6: N/A | AR6: N/A | AS6: N/A | AT6: N/A | AU6: N/A | AV6: N/A | AW6: N/A | AX6: N/A | AY6: N/A | AZ6: N/A | BA6: 484 | BB6: 36070 | BD6: X | BH6: N/A | BI6: N/A | BJ6: N/A | BK6: N/A | BL6: N/A | BM6: N/A | BN6: N/A | BO6: N/A | BP6: N/A | BQ6: N/A | BR6: N/A | BS6: N/A | BT6: N/A | BU6: 38714 | BV6: JUAN PABLO | BW6: SI | BX6: N/A | BY6: N/A | BZ6: N/A | CA6: N/A | CB6: N/A | CC6: N/A | CD6: N/A | CE6: N/A | CF6: N/A | CG6: DESISTIMIENTO TACITO 2025ER13626 DEL 18/12/20024 Y RADICADO 2025ER5822 DEL 30 DE MAYO | CH6: KAREN BARRETO | CI6: 45915
C9: CONTROL TRÁMITE DE CONCESIÓN DE AGUAS | BP9: Código | BQ9: RE-AA-20
BP10: Versión | BQ10: 8
BP11: Fecha | BQ11: 45617
A13: DATOS DE LA SOLICITUD | L13: REQUERIMIENTO | Q13: PAGO SERVICIOS DE EVALUACION | V13: AUTO | Y13: CONCEPTO TECNICO | AF13: REQUERIMIENTO | AK13: ACTO ADMINISTRATIVO | AR13: RECURSO DE REPOSICION | AT13: ACTO ADMINISTRATIVO RECURSO DE REPOSICION | AY13: MEMORIAS DE CALCULO | BH13: RECIBO A SATISFACCION DE OBRAS | BQ13: OBSERVACIONES
A14: No. Radicado | B14: Fecha Radicado | C14: No. Expediente | D14: Solicitante/Interesado | E14: Cédula de ciudadanía - NIT | F14: Municipio | G14: Vereda | H14: Tipo de Fuente | I14: Fuente | J14: Nombre de la Fuente | K14: Uso | L14: No. Oficio/ Auto de Requerimiento | M14: Fecha Oficio/ Auto de Requerimiento | N14: Nombre de quién proyectó | O14: Radicado Oficio de entrada | P14: Fecha oficio de entrada | Q14: No. de la Factura | R14: Valor tabla única (Factura) | S14: Valor Facturado | T14: Valor Cancelado | U14: Fecha del pago servicio de evaluación | V14: No. Auto admite y fija | W14: Fecha Auto admite y fija | X14: Nombre de quién proyectó | Y14: Fecha Visita técnica | Z14: Nombre del técnico | AA14: Fecha Concepto técnico | AB14: Caudal Fuente | AC14: Caudal Disponible | AD14: Caudal Otorgado | AE14: Número de Usuarios | AF14: No. Auto de Requerimiento | AG14: Fecha Auto de Requerimiento | AH14: Nombre de quién proyectó | AI14: Radicado Oficio de entrada | AJ14: Fecha oficio de entrada | AK14: No. Acto Administrativo | AL14: Fecha Acto Administrativo | AM14: Nombre de quién proyectó | AN14: Otorgada | AO14: Negada | AP14: Fecha Notificación | AQ14: Fecha ejecutoria | AR14: No. Radicado | AS14: Fecha Radicado | AT14: No. Acto Administrativo | AU14: Fecha Acto Administrativo | AV14: Nombre de quién proyectó | AW14: Modifica/ Aclara / Confirma/ Adiciona /Niega | AX14: Fecha Notificación | AY14: No. Radicado | AZ14: Fecha Radicado | BA14: Auto Requer. | BB14: Fecha Requer. | BC14: Nombre de quién proyecto | BD14: No. Acto Administrativo | BE14: Fecha Act Administrativo | BF14: Nombre de quien proyectó | BG14: Cumple o NO | BH14: No. Radicado del usuario | BI14: Fecha Radicado | BJ14: Fecha de visita técnica | BK14: Fecha Informe técnico | BL14: Nombre del técnico | BM14: No. Acto Administrativo | BN14: Fecha Acto Administrativo | BO14: Nombre de quién proyectó | BP14: Cumple o NO
A15: N/A 465 | B15: N/A 05/02/2004 | C15: CA 106/98 | D15: JOSE URIEL SANCHEZ TORRES | E15: N/A | F15: GARAGOA | G15: ACUEDUCTO INTERVEREDAL 1 | L15: 3159 05108 | M15: 4/07/2001 04/09/2001 | N15: NOHORA | O15: 3702 | P15: 37111 | Q15: N/A | R15: N/A | S15: N/A | T15: N/A | U15: N/A | V15: N/A | W15: N/A | X15: N/A | Y15: 37138 | Z15: HENRY LESMES | AA15: 37180 | AB15: N/A | AC15: N/A | AD15: N/A | AE15: N/A | AF15: N/A | AG15: N/A | AH15: N/A | AI15: N/A | AJ15: N/A | AK15: N/A | AL15: N/A | AM15: N/A | AN15: N/A | AO15: N/A | AP15: N/A | AQ15: N/A | AR15: N/A | AS15: N/A | AT15: N/A | AU15: N/A | AV15: N/A | AW15: N/A | AX15: N/A | AY15: N/A | AZ15: N/A | BA15: N/A | BB15: N/A | BC15: N/A | BD15: N/A | BE15: N/A | BF15: N/A | BG15: N/A | BH15: N/A | BI15: N/A | BJ15: N/A | BK15: N/A | BL15: N/A | BM15: N/A | BN15: N/A | BO15: N/A | BP15: N/A | BQ15: Fecha actualizacion 23/09/2026 Yennyf ultima actuacion memorando de fecha 23/02/2025

Sheet CA 1999
C1: CONTROL TRÁMITE DE CONCESIÓN DE AGUAS | BP1: Código | BQ1: RE-AA-20
BP2: Versión | BQ2: 8
BP3: Fecha | BQ3: 45617
A5: DATOS DE LA SOLICITUD | L5: REQUERIMIENTO | Q5: PAGO SERVICIOS DE EVALUACION | V5: AUTO | Y5: CONCEPTO TECNICO | AF5: REQUERIMIENTO | AK5: ACTO ADMINISTRATIVO | AR5: RECURSO DE REPOSICION | AT5: ACTO ADMINISTRATIVO RECURSO DE REPOSICION | AY5: MEMORIAS DE CALCULO | BH5: RECIBO A SATISFACCION DE OBRAS | BQ5: OBSERVACIONES
A6: No. Radicado | B6: Fecha Radicado | C6: No. Expediente | D6: Solicitante/Interesado | E6: Cédula de ciudadanía - NIT | F6: Municipio | G6: Vereda | H6: Tipo de Fuente | I6: Fuente | J6: Nombre de la Fuente | K6: Uso | L6: No. Oficio/ Auto de Requerimiento | M6: Fecha Oficio/ Auto de Requerimiento | N6: Nombre de quién proyectó | O6: Radicado Oficio de entrada | P6: Fecha oficio de entrada | Q6: No. de la Factura | R6: Valor tabla única (Factura) | S6: Valor Facturado | T6: Valor Cancelado | U6: Fecha del pago servicio de evaluación | V6: No. Auto admite y fija | W6: Fecha Auto admite y fija | X6: Nombre de quién proyectó | Y6: Fecha Visita técnica | Z6: Nombre del técnico | AA6: Fecha Concepto técnico | AB6: Caudal Fuente | AC6: Caudal Disponible | AD6: Caudal Otorgado | AE6: Número de Usuarios | AF6: No. Auto de Requerimiento | AG6: Fecha Auto de Requerimiento | AH6: Nombre de quién proyectó | AI6: Radicado Oficio de entrada | AJ6: Fecha oficio de entrada | AK6: No. Acto Administrativo | AL6: Fecha Acto Administrativo | AM6: Nombre de quién proyectó | AN6: Otorgada | AO6: Negada | AP6: Fecha Notificación | AQ6: Fecha ejecutoria | AR6: No. Radicado | AS6: Fecha Radicado | AT6: No. Acto Administrativo | AU6: Fecha Acto Administrativo | AV6: Nombre de quién proyectó | AW6: Modifica/ Aclara / Confirma/ Adiciona /Niega | AX6: Fecha Notificación | AY6: No. Radicado | AZ6: Fecha Radicado | BA6: Auto Requer. | BB6: Fecha Requer. | BC6: Nombre de quién proyecto | BD6: No. Acto Administrativo | BE6: Fecha Act Administrativo | BF6: Nombre de quien proyectó | BG6: Cumple o NO | BH6: No. Radicado del usuario | BI6: Fecha Radicado | BJ6: Fecha de visita técnica | BK6: Fecha Informe técnico | BL6: Nombre del técnico | BM6: No. Acto Administrativo | BN6: Fecha Acto Administrativo | BO6: Nombre de quién proyectó | BP6: Cumple o NO
A7: 6201 2015ER5742 | B7: 3/12/1999 26/11/2015 | C7: 067/99 | D7: DORA ELVIA JUNCO DE RODRIGUEZ | E7: 24160613 | F7: TIBANA | G7: APOSENTOS - IMBITA | H7: SUPERDIFICAL | I7: QUEBRADA | J7: QUEBRADA DE SORCA | K7: PECUARIO Y AGRICOLA | L7: N/A | M7: N/A | N7: N/A | O7: N/A | P7: N/A | Q7: N/A | R7: N/A | S7: N/A | T7: N/A | U7: N/A | V7: 9/12/1999 08/01/2010 29/12/2015 | W7: 9/12/1999 08/01/2010 29/12/2015 | X7: NOHORA DMANOSALVA JULIAN S | Y7: 10/04/2000 10/02/2010 30/09/2015 28/03/2016 01/11/2016 16/11/2022 | Z7: EDILBERTO MORENO REYES JORGE MONROY ANDREA OLIVEROS SERGIO DUEÑAS ELIANA CARDENAS JONATAN MUÑOZ | AA7: 10/04/2000 10/02/2010 10/11/2015 03/06/2016 01/11/2016 21/12/2022 | AB7: 8.12 | AC7: 8.12 | AD7: 2.25 | AE7: 10 | AF7: N/A 5269 264 0048 | AG7: N/A 21/07/2009 06/03/2023 15/01/2026 | AH7: N/A ARIOS GERMAN RODRIGUEZ ANGIE CRISTANCHO | AI7: N/A 2009ER6303 | AJ7: N/A 28/12/2009 | AK7: 16/08/1900 0164 PRORROGA 367 MODIFICA | AL7: 25/05/2000 17/02/2010 30/06/2016 | AM7: NOHORA PPERILLA LORENA BARON | AN7: X | AP7: 7/07/2000 18/03/2010 11/08/2016 | AQ7: N/A | AR7: N/A | AS7: N/A | AT7: N/A | AU7: N/A | AV7: N/A | AW7: N/A | AX7: N/A | AY7: N/A 2016ER6813 | AZ7: N/A 09/11/2016 | BA7: N/A | BB7: N/A | BC7: N/A | BD7: N/A 112 | BE7: N/A 03/05/2017 | BF7: N/A XIMENA BARRAGAN | BG7: N/A SI | BH7: N/A | BI7: N/A | BJ7: N/A | BK7: N/A | BL7: N/A | BM7: N/A | BN7: N/A | BO7: N/A | BP7: N/A | BQ7: Actualizada 23/09/2026 Yennyf Expediente se encuentra requerido desde el 15/01/2026
A8: 1531 2011ER460 | B8: 36271 | C8: CA 035/99 | D8: JOSE EUCARIO OSOARIO | E8: 79467076 | F8: TURMEQUE | G8: GUANZAQUE | H8: SUPERDIFICAL | J8: LA HONDURA | K8: ABREVADERO | L8: N/A | M8: N/A | N8: N/A | O8: N/A | P8: N/A | Q8: N/A | R8: N/A | S8: N/A | T8: N/A | U8: N/A | V8: 36278 | W8: 36278 | X8: NOHORA | Y8: 9/08/1999 21/10/2003 31/07/2008 15/02/2010 28/11/2018 | Z8: CARLOS SIERRA RAFAEL MORENO eliana cardenas | AA8: 9/08/1999 04/08/2008 28/04/2010 30/11/2018 | AB8: 1.25 | AC8: 1.25 | AD8: 0.07 | AE8: 19 FAMILIAS | AF8: N/A 5115 6541 2194 994 | AG8: N/A 24/10/2003 26/08/2006 06/04/2018 23/10/2020 | AH8: N/A YAMILE | AI8: N/A 2008ER5299 2009ER3092 | AJ8: N/A 08/10/2008 25/06/2009 | AK8: 378 AUTO ADM RENOVA 09/07/2009 025 PRORROGA | AL8: 8/09/1999 09/07/2009 07/02/2011 | AM8: NOHORA D MONSALVA P PERILLA | AN8: X | AP8: 22/09/1999 17/09/2012 | AQ8: N/A | AR8: N/A | AS8: N/A | AT8: N/A | AU8: N/A | AV8: N/A | AW8: N/A | AX8: N/A | AY8: N/A | AZ8: N/A | BA8: N/A | BB8: N/A | BC8: N/A | BD8: N/A | BE8: N/A | BF8: N/A | BG8: N/A | BH8: N/A | BI8: N/A | BJ8: N/A | BK8: N/A | BL8: N/A | BM8: N/A | BN8: N/A | BO8: N/A | BP8: N/A | BQ8: Actualizada 23/09/2026 Yennyf Expediente se encuentra para perdida de fuerza ejecutoria

Sheet CA 2000
A1: DATOS DE LA SOLICITUD | O1: APERTURÓ | P1: REQUERIMIENTO | W1: PAGO SERVICIOS DE EVALUACION | AB1: No. Oficio/ Auto de Requerimiento | AE1: CONTROL- DIAS TRANSCURRIDOS HASTA FECHA DE VISITA | AF1: CONCEPTO TECNICO | AV1: CONTROL- DIAS TRANSCURRIDOS DE LA RADICACION AL CONCEPTO CON Vo.Bo. | AW1: FECHA DE ASIGNACION CONCEPTO AL AREA JURIDICO | AX1: REQUERIMIENTO | BC1: ACTO ADMINISTRATIVO | BL1: RECURSO DE REPOSICION | BS1: MEMORIAS DE CALCULO | CB1: RECIBO A SATISFACCION DE OBRAS | CK1: ACTO ADMINISTRATIVO | EU1: SEGUIMIENTO | FD1: Observaciones de lo evidenciado en la visita técnica | FE1: Ultima Actualización
A2: No. Radicado | B2: Fecha Radicado | C2: No. Expediente | D2: RADICADO EN VITAL | E2: Solicitante/Interesado | F2: Cédula de ciudadanía - NIT | G2: Dirección de correspondencia | H2: Telefono | I2: Correo Electrónico | J2: Municipio permiso | K2: Lugar de la captación (Vereda) | L2: Tipo de Fuente | M2: Fuente | N2: Nombre de la Fuente | P2: No. Oficio/ Auto de Requerimiento | Q2: Fecha Oficio/ Auto de Requerimiento | R2: Nombre de quién proyectó | S2: Dias del radicado al requerimiento | T2: Descripcion del requerimiento | U2: Radicado Oficio de entrada | V2: Fecha oficio de entrada | W2: No. de la Factura | X2: Valor tabla única (Factura) | Y2: Valor Facturado | Z2: Valor Cancelado | AA2: Fecha del pago servicio de evaluación | AB2: No. Oficio/ Auto de Requerimiento | AC2: Fecha Oficio/ Auto de Requerimiento | AD2: Nombre de quién proyectó | AF2: Fecha Visita técnica | AG2: Nombre del técnico | AH2: FECHA LIMITE ENTREGA DE CONCEPTO | AI2: DIAS CALENDARIO TRANSCURRIDOS SEGÚN FECHA LIMITE DE ENTRE DE CONCEPTO Y FECHA DE VISITA TECNICA | AJ2: ALERTAS | AK2: Fecha entrega a Revisión Informe - Lider | AL2: Entrega de Informe al técnico para corrección | AM2: Entrega de concepto corregido | AN2: Fecha Concepto técnico | AO2: Predio a beneficiar | AP2: Georreferenciación del punto de captación | AQ2: Vereda de la localización del punto de captación | AR2: Usos | AS2: Caudal Otordo, dicriminado por cada uso | AT2: Total del caudal otorgado | AU2: Número de Suscriptores | AX2: No. Auto de Requerimiento | AY2: Fecha Auto de Requerimiento | AZ2: Nombre de quién proyectó | BA2: Radicado Oficio de entrada | BB2: Fecha oficio de entrada | BC2: No. Acto Administrativo | BD2: Fecha Acto Administrativo | BE2: Nombre de quién proyectó | BF2: Otorgada | BG2: Negada | BH2: Desistida | BI2: Fecha Notificación | BJ2: Fecha ejecutoria | BK2: Fecha de vencimiento | BL2: No. Radicado | BM2: Fecha Radicado | BN2: No. Acto Administrativo | BO2: Fecha Acto Administrativo | BP2: Nombre de quién proyectó | BQ2: Modifica/ Aclara / Confirma/ Adiciona /Niega | BR2: Fecha Notificación | BS2: No. Radicado | BT2: Fecha Radicado | BU2: Auto Requer. | BV2: Fecha Requer. | BW2: Nombre de quién proyecto | BX2: No. Acto Administrativo | BY2: Fecha Act Administrativo | BZ2: Nombre de quien proyectó | CA2: Cumple o NO | CB2: No. Radicado del usuario | CC2: Fecha Radicado | CD2: Fecha de visita técnica | CE2: Fecha Informe técnico | CF2: Nombre del técnico | CG2: No. Acto Administrativo | CH2: Fecha Acto Administrativo | CI2: Nombre de quién proyectó | CJ2: Cumple o NO | CK2: No. Radicado | CL2: Fecha Radicado | CM2: Fecha de visita técnica | CN2: Fecha Informe técnico | CO2: Nombre del técnico | CP2: No. Acto Administrativo | CQ2: Fecha de notificación | CR2: Fecha de ejecutoria | CS2: Observación | CT2: No. Radicado | CU2: Fecha Radicado | CV2: Fecha de visita técnica | CW2: Fecha Informe técnico | CX2: Nombre del técnico | CY2: No. Acto Administrativo | CZ2: Fecha de notificación | DA2: Fecha de ejecutoria | DB2: Observación | DC2: No. Radicado | DD2: Fecha Radicado | DE2: Fecha de visita técnica | DF2: Fecha Informe técnico | DG2: Nombre del técnico | DH2: No. Acto Administrativo | DI2: Fecha de notificación | DJ2: Fecha de ejecutoria | DK2: Observación | DL2: No. Radicado | DM2: Fecha Radicado | DN2: Fecha de visita técnica | DO2: Fecha Informe técnico | DP2: Nombre del técnico | DQ2: No. Acto Administrativo | DR2: Fecha de notificación | DS2: Fecha de ejecutoria | DT2: Observación | DU2: No. Radicado | DV2: Fecha Radicado | DW2: Fecha de visita técnica | DX2: Fecha Informe técnico | DY2: Nombre del técnico | DZ2: No. Acto Administrativo | EA2: Fecha de notificación | EB2: Fecha de ejecutoria | EC2: Observación | ED2: No. Radicado | EE2: Fecha Radicado | EF2: Fecha de visita técnica | EG2: Fecha Informe técnico | EH2: Nombre del técnico | EI2: No. Acto Administrativo | EJ2: Fecha de notificación | EK2: Fecha de ejecutoria | EL2: Observación | EM2: Fecha Radicado | EN2: Fecha de visita técnica | EO2: Fecha Informe técnico | EP2: Nombre del técnico | EQ2: RECLAMACION TUA | ER2: Fecha de notificación | ES2: Fecha de ejecutoria | ET2: Observación | EU2: Fecha ultimo seguimiento | EV2: Fecha de concepto | EW2: Cadual Aforado (Captado o vertido) | EX2: Volumen metros cubicos aprovechado ( AF) aprovechamiento forestal | EY2: Entrega informes Anuales (L.A) Solo aplica para licencias ambientales | FB2: Acto administrativo
AV3: Solicitamos se agregue la formula | CP3: Modificacion | CY3: Traspaso | DH3: Prorroga | DQ3: Cancelación | DZ3: Perdida de fuerza ejecutoria | EI3: Suspensión | EY3: Llantas Usadas | EZ3: ICA | FA3: Autoliquidación de la vigencia | FB3: N° | FC3: Fecha
EY5: SI /NO
A6: 2025ER13098 | B6: 45960 | E6: Acuducto caldera-ASUPAL | F6: 901406724-6 | G6: vereda caldera abajo | H6: 3167529752 | I6: marthacpineda@hotmail.com | J6: Garagoa | K6: Caldera arriba, caldera abajo quigua abajo, y las escuelas de las veredas caldera arriba y abajo | N6: chorro caldera | P6: 2025EE13610 | Q6: 45975 | R6: Karen Barreto | BC6: 370 332 119 | BD6: 11/07/2000 09-07-2013 08-03-2024 | BF6: otorgo prorroga prorroga | BL6: NA | BM6: NA | BN6: NA | BO6: NA | BP6: NA | BQ6: NA | BR6: NA | BS6: 2024ER4994 | BT6: 45806 | BX6: Res 567 | BY6: 45503 | BZ6: Milena Galindo | CA6: si | CB6: 2024ER9659 | CC6: 45558 | CD6: 45612 | CE6: 45645 | CF6: Andres T | CG6: Res 1139 | CH6: 45653 | CI6: Karen Barreto | CJ6: si | CK6: NA | CL6: NA | CM6: NA | CN6: NA | CO6: NA | CP6: NA | CQ6: NA | CR6: NA | CS6: NA | CT6: NA | CU6: NA | CV6: AN | CW6: NA | CX6: NA | CY6: NA | CZ6: NA | DA6: NA | DB6: NA | DC6: NA | DD6: NA | DE6: NA | DF6: NA | DG6: NA | DH6: NA | DI6: NA | DJ6: NA | DK6: NA | DL6: NA | DM6: NA | DN6: NA | DO6: NA | DP6: NA | DQ6: NA | DR6: NA | DS6: NA | DT6: NA | EU6: NA | EV6: NA | EW6: NA | EX6: NA | EY6: NA | EZ6: NA | FA6: NA | FB6: NA | FC6: NA | FD6: en tramite de actualizacion de representante legal 2025EE13610 | FE6: 45994 | FF6: KAREN BARRETO
C7: CA 069-00 | E7: ASOCIACION DE SUSCRIPTORES DE LA VEREDA DE CHAGUATA BOYACA ASAC SANTA ROSA | F7: 900432356 | G7: vereda chaguatoque | H7: 310 334 1156 | I7: carleon07@gmail.com | J7: tenza | P7: 2024EE8425 2025EE828 2025EE1427 2025EE3252 2025EE3253 | Q7: 3/09/2024 21/02/2025 14/03/2025 05/05/2025 05/05/2025 | R7: KAREN BARRETO ANGIE ALVAREZ KAREN BARRETO KAREN BARRETO KAREN BARRETO | U7: 2024ER8082 2025ER873 2025ER963 2025ER2690 | V7: 22/08/2024 04/02/2025 06/02/2025 25/03/2025 | W7: EV -23 | X7: 156585 | Y7: 156585 | Z7: 156585 | AA7: 45741 | AB7: 239 | AC7: 45779 | AD7: KAREN BARRETO | BC7: 285 418 | BD7: 29/06/201 07/07/2014 | BF7: OTORGO PRORROGA | BG7: NA | BH7: NA | DE7: 45797 | DF7: 45854 | DG7: adrian | DH7: requerido Auto No. 1285 | DI7: 45882 | FD7: requerido para allegar autorizacion sanitaria favorable | FE7: 45912 | FF7: MILENA GALINDO
A8: 200ER6107 | B8: 36887 | C8: CA 103-00 | D8: PENDIENTE | E8: JOSE RAMON SUAREZ SANTUARIO | F8: 1181410 | G8: VEREDA ROSALES | H8: 3108854907 | I8: NA | J8: TURMEQUE | K8: NA | L8: NA | M8: NA | N8: NA | O8: NA | P8: NA | Q8: NA | R8: NA | S8: NA | T8: NA | U8: NA | V8: NA | W8: NA | X8: NA | Y8: NA | Z8: NA | AA8: NA | AB8: NA | AC8: NA | AD8: NA | AE8: NA | AF8: NA | AG8: NA | AH8: NA | AI8: NA | AJ8: NA | AK8: NA | AL8: NA | AM8: NA | AN8: NA | AO8: NA | AP8: NA | AQ8: NA | AR8: NA | AS8: NA | AT8: NA | AU8: NA | AV8: NA | AW8: NA | AX8: NA | AY8: NA | AZ8: NA | BA8: NA | BB8: NA | BC8: NA | BD8: NA | BE8: NA | BF8: NA | BG8: NA | BH8: NA | BI8: NA | BJ8: NA | BK8: NA | BL8: NA | BM8: NA | BN8: NA | BO8: NA | BP8: NA | BQ8: NA | BR8: NA | BS8: NA | BT8: NA | BU8: NA | BV8: NA | BW8: NA | BX8: NA | BY8: NA | BZ8: NA | CA8: NA | CB8: NA | CC8: NA | CD8: NA | CE8: NA | CF8: NA | CG8: NA | CH8: NA | CI8: NA | CJ8: NA | CK8: NA | CL8: NA | CM8: NA | CN8: NA | CO8: NA | CP8: NA | CQ8: NA | CR8: NA | CS8: NA | CT8: NA | CU8: NA | CV8: NA | CW8: NA | CX8: NA | CY8: NA | CZ8: NA | DA8: NA | DB8: NA | DC8: NA | DD8: NA | DE8: NA | DF8: NA | DG8: NA | DH8: NA | DI8: NA | DJ8: NA | DK8: NA | DL8: NA | DM8: NA | DN8: NA | DO8: NA | DP8: NA | DQ8: NA | DR8: NA | DS8: NA | DT8: NA | DU8: NA | DV8: NA | DW8: NA | DX8: NA | DY8: NA | DZ8: NA | EA8: NA | EB8: NA | EC8: NA | ED8: NA | EE8: NA | EF8: NA | EG8: NA | EH8: NA | EI8: NA | EJ8: NA | EK8: NA | EL8: NA | EM8: NA | EN8: NA | EO8: NA | EP8: NA | EQ8: NA | ER8: NA | ES8: NA | ET8: NA | EU8: NA | EV8: NA | EW8: NA | EX8: NA | EY8: NA | EZ8: NA | FA8: NA | FB8: NA | FC8: NA | FD8: MEDIANTE RESOLUCION 778 DEL 20/08/2025 SE ARCHIVA EL EXPEDIENTE Actuacion notificada por aviso el día 16-12-2025 | FE8: 46013 | FF8: KAREN BARRETO

Sheet CA 2001
C1: CONTROL TRAMITE DE CONCESION DE AGUAS 2001 | CF1: Código | CG1: RE-AA-20
CF2: Versión | CG2: 7
CF3: Fecha | CG3: 44411
A4: DATOS DE LA SOLICITUD | Q4: REQUERIMIENTO | X4: PAGO SERVICIOS DE EVALUACION | AC4: AUTO | AF4: CONTROL- DIAS TRANSCURRIDOS HASTA FECHA DE VISITA | AG4: CONCEPTO TECNICO | AT4: CONTROL- DIAS TRANSCURRIDOS DE LA RADICACION AL CONCEPTO CON Vo.Bo. | AV4: REQUERIMIENTO | BA4: ACTO ADMINISTRATIVO | BH4: RECURSO DE REPOSICION | BJ4: ACTO ADMINISTRATIVO RECURSO DE REPOSICION | BO4: MEMORIAS DE CALCULO | BX4: RECIBO A SATISFACCION DE OBRAS | CG4: OBSERVACIONES
A5: No. Radicado | B5: Fecha Radicado | C5: No. Expediente | D5: RADICADO EN VITAL | E5: Solicitante/Interesado | F5: Cédula de ciudadanía - NIT | G5: Dirección de correspondencia | H5: Municipio - CONCESION DE AGUAS | I5: Teléfono | J5: Correo Electrónico | K5: Lugar de la captación (Vereda) | L5: Tipo de Fuente | M5: Fuente | N5: Nombre de la Fuente | O5: Uso | P5: APERTURÓ | Q5: No. Oficio/ Auto de Requerimiento | R5: Fecha Oficio/ Auto de Requerimiento | S5: Nombre de quién proyectó | T5: DIAS DEL RADICADO AL REQUERIMIENTO | U5: Radicado Oficio de entrada | V5: Fecha oficio de entrada | W5: DESCRIPCION DEL REQUERIMIENTO | X5: No. de la Factura | Y5: Valor tabla única (Factura) | Z5: Valor Facturado | AA5: Valor Cancelado | AB5: Fecha del pago servicio de evaluación | AC5: No. Auto admite y fija | AD5: Fecha Auto admite y fija | AE5: Nombre de quién proyectó | AG5: Fecha Visita técnica | AH5: Nombre del técnico | AI5: FECHA LIMITE ENTREGA DE CONCEPTO | AJ5: DIAS CALENDARIO TRANSCURRIDOS SEGÚN FECHA LIMITE DE ENTRE DE CONCEPTO Y FECHA DE VISITA TECNICA | AK5: ALERTAS | AL5: Fecha entrega a Revisión Informe - Lider | AM5: Entrega de Informe al técnico para corrección | AN5: Entrega de concepto corregido | AO5: Fecha Concepto técnico | AP5: Caudal Fuente | AQ5: Caudal Disponible | AR5: Caudal Otorgado | AS5: Número de Usuarios | AU5: FECHA DE ASIGNACION CONCEPTO AL AREA JURIDICO | AV5: No. Auto de Requerimiento | AW5: Fecha Auto de Requerimiento | AX5: Nombre de quién proyectó | AY5: Radicado Oficio de entrada | AZ5: Fecha oficio de entrada | BA5: No. Acto Administrativo | BB5: Fecha Acto Administrativo | BC5: Nombre de quién proyectó | BD5: Otorgada | BE5: Negada | BF5: Fecha Notificación | BG5: Fecha ejecutoria | BH5: No. Radicado | BI5: Fecha Radicado | BJ5: No. Acto Administrativo | BK5: Fecha Acto Administrativo | BL5: Nombre de quién proyectó | BM5: Modifica/ Aclara / Confirma/ Adiciona /Niega | BN5: Fecha Notificación | BO5: No. Radicado | BP5: Fecha Radicado | BQ5: Auto Requer. | BR5: Fecha Requer. | BS5: Nombre de quién proyecto | BT5: No. Acto Administrativo | BU5: Fecha Act Administrativo | BV5: Nombre de quien proyectó | BW5: Cumple o NO | BX5: No. Radicado del usuario | BY5: Fecha Radicado | BZ5: Fecha de visita técnica | CA5: Fecha Informe técnico | CB5: Nombre del técnico | CC5: No. Acto Administrativo | CD5: Fecha Acto Administrativo | CE5: Nombre de quién proyectó | CF5: Cumple o NO | CH5: ULTIMA ACTULIZACION | CI5: FECHA ACTUALIZAICON
A6: 2001EE5425 | B6: 37211 | C6: CA 055-01 | E6: LUIS ALFREDO GAMBA JUNCO | F6: 1098568 | G6: Calle 3 No. 4-23 | H6: Nuevo Colon | I6: 3105578793 | J6: frutasyverduraselcarpo@gmail.com | K6: Centro Rural | L6: Superficial | M6: Quebrada | N6: Grande | O6: Agricola | P6: N/A | Q6: N/A | R6: N/A | S6: N/A | T6: N/A | U6: N/A | V6: N/A | W6: N/A | X6: N/A | Y6: N/A | Z6: N/A | AA6: N/A | AB6: N/A | AC6: N/A | AD6: N/A | AE6: N/A | AF6: N/A | AG6: N/A | AH6: N/A | AI6: N/A | AJ6: N/A | AK6: N/A | AL6: N/A | AM6: N/A | AN6: N/A | AO6: N/A | AP6: N/A | AQ6: N/A | AR6: N/A | AS6: N/A | AT6: N/A | AU6: N/A | AV6: N/A | AW6: N/A | AX6: N/A | AY6: N/A | AZ6: N/A | BA6: 260 476 | BB6: 16/05/2002 23-09-2013 | BC6: ANA ELVIA ANA CELIA | BD6: X | BF6: 29/05/2002 15-10-2013 | BG6: 41576 | BH6: N/A | BI6: N/A | BJ6: N/A | BK6: N/A | BL6: N/A | BM6: N/A | BN6: N/A | BO6: N/A | BP6: N/A | BQ6: N/A | BR6: N/A | BS6: N/A | BT6: N/A | BU6: 38714 | BV6: JUAN PABLO | BW6: SI | BX6: N/A | BY6: N/A | BZ6: N/A | CA6: N/A | CB6: N/A | CC6: 1343 | CD6: 39081 | CE6: PLINIO RONALDO | CF6: SI | CG6: SE DESISTIO SOLICITUD DE PRORROGA ENVIAR A PERDIDA | CH6: MILENA GALINDO | CI6: 45413

Sheet CA 2002
C1: CONTROL TRAMITE DE CONCESION DE AGUAS 2002 | CF1: Código | CG1: RE-AA-20
CF2: Versión | CG2: 7
CF3: Fecha | CG3: 44411
A4: DATOS DE LA SOLICITUD | Q4: REQUERIMIENTO | X4: PAGO SERVICIOS DE EVALUACION | AC4: AUTO | AF4: CONTROL- DIAS TRANSCURRIDOS HASTA FECHA DE VISITA | AG4: CONCEPTO TECNICO | AT4: CONTROL- DIAS TRANSCURRIDOS DE LA RADICACION AL CONCEPTO CON Vo.Bo. | AV4: REQUERIMIENTO | BA4: ACTO ADMINISTRATIVO | BH4: RECURSO DE REPOSICION | BJ4: ACTO ADMINISTRATIVO RECURSO DE REPOSICION | BO4: MEMORIAS DE CALCULO | BX4: RECIBO A SATISFACCION DE OBRAS | CG4: OBSERVACIONES
A5: No. Radicado | B5: Fecha Radicado | C5: No. Expediente | D5: RADICADO EN VITAL | E5: Solicitante/Interesado | F5: Cédula de ciudadanía - NIT | G5: Dirección de correspondencia | H5: Municipio - CONCESION DE AGUAS | I5: Teléfono | J5: Correo Electrónico | K5: Lugar de la captación (Vereda) | L5: Tipo de Fuente | M5: Fuente | N5: Nombre de la Fuente | O5: Uso | P5: APERTURÓ | Q5: No. Oficio/ Auto de Requerimiento | R5: Fecha Oficio/ Auto de Requerimiento | S5: Nombre de quién proyectó | T5: DIAS DEL RADICADO AL REQUERIMIENTO | U5: Radicado Oficio de entrada | V5: Fecha oficio de entrada | W5: DESCRIPCION DEL REQUERIMIENTO | X5: No. de la Factura | Y5: Valor tabla única (Factura) | Z5: Valor Facturado | AA5: Valor Cancelado | AB5: Fecha del pago servicio de evaluación | AC5: No. Auto admite y fija | AD5: Fecha Auto admite y fija | AE5: Nombre de quién proyectó | AG5: Fecha Visita técnica | AH5: Nombre del técnico | AI5: FECHA LIMITE ENTREGA DE CONCEPTO | AJ5: DIAS CALENDARIO TRANSCURRIDOS SEGÚN FECHA LIMITE DE ENTRE DE CONCEPTO Y FECHA DE VISITA TECNICA | AK5: ALERTAS | AL5: Fecha entrega a Revisión Informe - Lider | AM5: Entrega de Informe al técnico para corrección | AN5: Entrega de concepto corregido | AO5: Fecha Concepto técnico | AP5: Caudal Fuente | AQ5: Caudal Disponible | AR5: Caudal Otorgado | AS5: Número de Usuarios | AU5: FECHA DE ASIGNACION CONCEPTO AL AREA JURIDICO | AV5: No. Auto de Requerimiento | AW5: Fecha Auto de Requerimiento | AX5: Nombre de quién proyectó | AY5: Radicado Oficio de entrada | AZ5: Fecha oficio de entrada | BA5: No. Acto Administrativo | BB5: Fecha Acto Administrativo | BC5: Nombre de quién proyectó | BD5: Otorgada | BE5: Negada | BF5: Fecha Notificación | BG5: Fecha ejecutoria | BH5: No. Radicado | BI5: Fecha Radicado | BJ5: No. Acto Administrativo | BK5: Fecha Acto Administrativo | BL5: Nombre de quién proyectó | BM5: Modifica/ Aclara / Confirma/ Adiciona /Niega | BN5: Fecha Notificación | BO5: No. Radicado | BP5: Fecha Radicado | BQ5: Auto Requer. | BR5: Fecha Requer. | BS5: Nombre de quién proyecto | BT5: No. Acto Administrativo | BU5: Fecha Act Administrativo | BV5: Nombre de quien proyectó | BW5: Cumple o NO | BX5: No. Radicado del usuario | BY5: Fecha Radicado | BZ5: Fecha de visita técnica | CA5: Fecha Informe técnico | CB5: Nombre del técnico | CC5: No. Acto Administrativo | CD5: Fecha Acto Administrativo | CE5: Nombre de quién proyectó | CF5: Cumple o NO | CH5: ULTIMA ACTULIZACION | CI5: FECHA ACTUALIZAICON
C6: C.A. 105/02 | E6: OCTAVIO MONTENEGRO LOPEZ | F6: 40128779 | G6: Predio Algarrobo | H6: Campohermoso | I6: 321 343 6905 – 313 840 2816 | J6: olviamontenegro@hotmail.com | K6: Teguas | L6: Nacimiento | M6: Superficial | N6: Sin Nombre | O6: Domestico Pecuario | P6: N/A | Q6: N/A | R6: N/A | S6: N/A | T6: N/A | U6: N/A | V6: N/A | W6: N/A | X6: N/A | Y6: N/A | Z6: N/A | AA6: N/A | AB6: N/A | AC6: N/A | AD6: N/A | AE6: N/A | AF6: N/A | AG6: N/A | AH6: N/A | AI6: N/A | AJ6: N/A | AK6: N/A | AL6: N/A | AM6: N/A | AN6: N/A | AO6: N/A | AP6: N/A | AQ6: N/A | AR6: N/A | AS6: N/A | AT6: N/A | AU6: N/A | AV6: N/A | AW6: N/A | AX6: N/A | AY6: N/A | AZ6: N/A | BA6: N/A | BB6: N/A | BC6: N/A | BD6: 952 544 1169 | BE6: N/A | BF6: 27/01/2003 23/07/2012 01/11/2022 | BG6: N/A | BH6: N/A | BI6: N/A | BJ6: N/A | BK6: N/A | BL6: N/A | BM6: N/A | BN6: N/A | BO6: N/A | BP6: N/A | BQ6: N/A | BR6: N/A | BS6: N/A | BT6: N/A | BU6: N/A | BV6: N/A | BW6: N/A | BX6: N/A | BY6: N/A | BZ6: N/A | CA6: N/A | CB6: N/A | CC6: N/A | CD6: N/A | CE6: N/A | CF6: N/A | CG6: N/A
C7: CA 145-02 | E7: MUNICIPIO DE JENESANO | F7: 891801376 | H7: Jenesano | J7: unidadserviciospublicos@jenesano-boyaca.gov.co | K7: Pulidos | L7: Superficial | M7: Quebrada | N7: La Unica | O7: Domestico | P7: N/A | Q7: N/A | R7: N/A | S7: N/A | T7: N/A | U7: N/A | V7: N/A | W7: N/A | X7: N/A | Y7: N/A | Z7: N/A | AA7: N/A | AB7: N/A | AC7: N/A | AD7: N/A | AE7: N/A | AF7: N/A | AG7: N/A | AH7: N/A | AI7: N/A | AJ7: N/A | AK7: N/A | AL7: N/A | AM7: N/A | AN7: N/A | AO7: N/A | AP7: N/A | AQ7: N/A | AR7: N/A | AS7: N/A | AT7: N/A | AU7: N/A | AV7: N/A | AW7: N/A | AX7: N/A | AY7: N/A | AZ7: N/A | BA7: 482 315 300 | BB7: 02/08/2002 03/07/2013 30/04/2025 | BC7: MILENA GALINDO | BD7: X | BF7: 45782 | BG7: 45796 | BH7: N/A | BI7: N/A | BJ7: N/A | BK7: N/A | BL7: N/A | BM7: N/A | BN7: N/A | BO7: 2025ER7341 | BP7: 45845 | BQ7: 2115 | BR7: 45992 | BS7: Karen B. | BT7: N/A | BU7: N/A | BV7: N/A | BW7: N/A | BX7: N/A | BY7: N/A | BZ7: N/A | CA7: N/A | CB7: N/A | CC7: N/A | CD7: N/A | CE7: N/A | CF7: N/A | CG7: PRORROGADA -Se requieren ajustes ajustes a las memorias(pazo 04-01-2026) | CH7: KAREN BARRETO | CI7: 46010
C8: CA 116-02 | E8: JOSÉ EVARISTO PORRAS, | F8: 4291640 | G8: Sector Agua Buena Vereda Bojirque Ventaquemada - Boyacá | H8: Ventaquemada | I8: 3219093882 | BA8: 416 469 286 | BB8: 12/07/2002 26/06/2012 25/04/2023 | BD8: x | BF8: 45153 | BG8: 45169 | BO8: 2026ER2745 | BP8: 46085 | BQ8: 575 | BR8: 202EE4169 | BS8: Milena G. | BT8: NA | BU8: NA | BV8: NA | BW8: NA | BX8: NA | BY8: NA | BZ8: NA | CA8: NA | CB8: NA | CC8: NA | CD8: NA | CE8: NA | CF8: NA | CG8: Pendiente Ajuste de Obras | CH8: Milena G | CI8: 31-4-26

Sheet CA 2004
A1: DATOS DE LA SOLICITUD | O1: APERTURÓ | P1: REQUERIMIENTO | W1: PAGO SERVICIOS DE EVALUACION | AB1: No. Oficio/ Auto de Requerimiento | AE1: CONTROL- DIAS TRANSCURRIDOS HASTA FECHA DE VISITA | AF1: CONCEPTO TECNICO | AV1: CONTROL- DIAS TRANSCURRIDOS DE LA RADICACION AL CONCEPTO CON Vo.Bo. | AW1: FECHA DE ASIGNACION CONCEPTO AL AREA JURIDICO | AX1: REQUERIMIENTO | BC1: ACTO ADMINISTRATIVO | BL1: RECURSO DE REPOSICION | BS1: MEMORIAS DE CALCULO | CB1: RECIBO A SATISFACCION DE OBRAS | CK1: ACTO ADMINISTRATIVO | EU1: SEGUIMIENTO | FD1: Observaciones de lo evidenciado en la visita técnica | FE1: Ultima Actualización
A2: No. Radicado | B2: Fecha Radicado | C2: No. Expediente | D2: RADICADO EN VITAL | E2: Solicitante/Interesado | F2: Cédula de ciudadanía - NIT | G2: Dirección de correspondencia | H2: Telefono | I2: Correo Electrónico | J2: Municipio permiso | K2: Lugar de la captación (Vereda) | L2: Tipo de Fuente | M2: Fuente | N2: Nombre de la Fuente | P2: No. Oficio/ Auto de Requerimiento | Q2: Fecha Oficio/ Auto de Requerimiento | R2: Nombre de quién proyectó | S2: Dias del radicado al requerimiento | T2: Descripcion del requerimiento | U2: Radicado Oficio de entrada | V2: Fecha oficio de entrada | W2: No. de la Factura | X2: Valor tabla única (Factura) | Y2: Valor Facturado | Z2: Valor Cancelado | AA2: Fecha del pago servicio de evaluación | AB2: No. Oficio/ Auto de Requerimiento | AC2: Fecha Oficio/ Auto de Requerimiento | AD2: Nombre de quién proyectó | AF2: Fecha Visita técnica | AG2: Nombre del técnico | AH2: FECHA LIMITE ENTREGA DE CONCEPTO | AI2: DIAS CALENDARIO TRANSCURRIDOS SEGÚN FECHA LIMITE DE ENTRE DE CONCEPTO Y FECHA DE VISITA TECNICA | AJ2: ALERTAS | AK2: Fecha entrega a Revisión Informe - Lider | AL2: Entrega de Informe al técnico para corrección | AM2: Entrega de concepto corregido | AN2: Fecha Concepto técnico | AO2: Predio a beneficiar | AP2: Georreferenciación del punto de captación | AQ2: Vereda de la localización del punto de captación | AR2: Usos | AS2: Caudal Otordo, dicriminado por cada uso | AT2: Total del caudal otorgado | AU2: Número de Suscriptores | AX2: No. Auto de Requerimiento | AY2: Fecha Auto de Requerimiento | AZ2: Nombre de quién proyectó | BA2: Radicado Oficio de entrada | BB2: Fecha oficio de entrada | BC2: No. Acto Administrativo | BD2: Fecha Acto Administrativo | BE2: Nombre de quién proyectó | BF2: Otorgada | BG2: Negada | BH2: Desistida | BI2: Fecha Notificación | BJ2: Fecha ejecutoria | BK2: Fecha de vencimiento | BL2: No. Radicado | BM2: Fecha Radicado | BN2: No. Acto Administrativo | BO2: Fecha Acto Administrativo | BP2: Nombre de quién proyectó | BQ2: Modifica/ Aclara / Confirma/ Adiciona /Niega | BR2: Fecha Notificación | BS2: No. Radicado | BT2: Fecha Radicado | BU2: Auto Requer. | BV2: Fecha Requer. | BW2: Nombre de quién proyecto | BX2: No. Acto Administrativo | BY2: Fecha Act Administrativo | BZ2: Nombre de quien proyectó | CA2: Cumple o NO | CB2: No. Radicado del usuario | CC2: Fecha Radicado | CD2: Fecha de visita técnica | CE2: Fecha Informe técnico | CF2: Nombre del técnico | CG2: No. Acto Administrativo | CH2: Fecha Acto Administrativo | CI2: Nombre de quién proyectó | CJ2: Cumple o NO | CK2: No. Radicado | CL2: Fecha Radicado | CM2: Fecha de visita técnica | CN2: Fecha Informe técnico | CO2: Nombre del técnico | CP2: No. Acto Administrativo | CQ2: Fecha de notificación | CR2: Fecha de ejecutoria | CS2: Observación | CT2: No. Radicado | CU2: Fecha Radicado | CV2: Fecha de visita técnica | CW2: Fecha Informe técnico | CX2: Nombre del técnico | CY2: No. Acto Administrativo | CZ2: Fecha de notificación | DA2: Fecha de ejecutoria | DB2: Observación | DC2: No. Radicado | DD2: Fecha Radicado | DE2: Fecha de visita técnica | DF2: Fecha Informe técnico | DG2: Nombre del técnico | DH2: No. Acto Administrativo | DI2: Fecha de notificación | DJ2: Fecha de ejecutoria | DK2: Observación | DL2: No. Radicado | DM2: Fecha Radicado | DN2: Fecha de visita técnica | DO2: Fecha Informe técnico | DP2: Nombre del técnico | DQ2: No. Acto Administrativo | DR2: Fecha de notificación | DS2: Fecha de ejecutoria | DT2: Observación | DU2: No. Radicado | DV2: Fecha Radicado | DW2: Fecha de visita técnica | DX2: Fecha Informe técnico | DY2: Nombre del técnico | DZ2: No. Acto Administrativo | EA2: Fecha de notificación | EB2: Fecha de ejecutoria | EC2: Observación | ED2: No. Radicado | EE2: Fecha Radicado | EF2: Fecha de visita técnica | EG2: Fecha Informe técnico | EH2: Nombre del técnico | EI2: No. Acto Administrativo | EJ2: Fecha de notificación | EK2: Fecha de ejecutoria | EL2: Observación | EM2: Fecha Radicado | EN2: Fecha de visita técnica | EO2: Fecha Informe técnico | EP2: Nombre del técnico | EQ2: RECLAMACION TUA | ER2: Fecha de notificación | ES2: Fecha de ejecutoria | ET2: Observación | EU2: Fecha ultimo seguimiento | EV2: Fecha de concepto | EW2: Cadual Aforado (Captado o vertido) | EX2: Volumen metros cubicos aprovechado ( AF) aprovechamiento forestal | EY2: Entrega informes Anuales (L.A) Solo aplica para licencias ambientales | FB2: Acto administrativo
AV3: Solicitamos se agregue la formula | CP3: Modificacion | CY3: Traspaso | DH3: Prorroga | DQ3: Cancelación | DZ3: Perdida de fuerza ejecutoria | EI3: Suspensión | EY3: Llantas Usadas | EZ3: ICA | FA3: Autoliquidación de la vigencia | FB3: N° | FC3: Fecha
EY4: SI /NO
A5: 2004ER788 | B5: 38040 | C5: CA 063-04 | D5: PENDIENTE | E5: JORGE ALIRIO HEREDIA | F5: 4125723 | G5: VEREDA SIGUIQUE CENTRO KM 12 VIA LAS JUNTAS GUATEQUE | H5: 3219103144 3204578304 | I5: herediavillamilfamilia@gmail.com | J5: SUTATENZA | K5: NACIMIENOT EL CANGREJO | L5: SUPERFICIAL | M5: NACIMIENTO | N5: EL CANGREJO | O5: NA | P5: 2021EE11911 2025EE937 2025EE3098 | Q5: 3/11/2021 27/02/205 30/04/2025 | R5: JUAN C PAULA M KAREN BARERTO | U5: 2021ER8873 2021ER8874 2025ER473 2025ER3109 2025ER3202 | V5: 19/10/2021 19/10/2021 22/01/2025 31/03/2025 01/04/2025 | W5: SIN | X5: 100640 | Y5: 100640 | Z5: 100640 | AA5: 44369 | AX5: 321 3585 | AY5: 19/04/2021 27/11/2023 | AZ5: ANGY CARO ADRIANA M | BC5: 619 | BD5: 38197 | BE5: YAMILE C | BF5: X | BG5: NA | BH5: NA | BI5: 38205 | BJ5: 38223 | BK5: 41875 | BU5: SIN | BV5: 40135 | BW5: PLINIO F | CA5: SI | CP5: 807(24/07/2006) | DC5: 2010ER55 | DD5: 096/01/2010 | DE5: 42458 | DF5: 42514 | DG5: PAULA CALDERON | DH5: 318(30/06/2016) | DI5: 42570 | DJ5: 42586 | FD5: PENDIENTE REQUERIMIENTO OFICIO 3098 | FE5: 45785 | FF5: KAREN BARRETO
C6: CA127/04 | E6: YOLANDA BELTRÁN DE NARANJO ARMANDO NARANJO GOMEZ PISCICOLA ANDINA LTDA | F6: 19124269 | G6: Correo electronico:piscicolaandina@yahoo.es - anaran21@yahoo.es Carrera 71 c No. 101-33 Bogota D.C | I6: piscicolaandina@yahoo.es - anaran21@yahoo.es | J6: BOYACA | K6: HUERTA GRANDE | L6: SUPERFICIAL | M6: QUEBRADA | N6: EL CHULO | O6: NA | P6: NA | Q6: NA | R6: NA | S6: NA | T6: NA | U6: NA | V6: NA | W6: NA | X6: NA | Y6: NA | Z6: NA | AA6: NA | AB6: NA | AC6: NA | AD6: NA | AE6: NA | AF6: NA | AG6: NA | AH6: NA | AI6: NA | AJ6: NA | AK6: NA | AL6: NA | AM6: NA | AN6: NA | AO6: NA | AP6: NA | AQ6: NA | AR6: NA | AS6: NA | AT6: NA | AU6: NA | AV6: NA | AW6: NA | AX6: NA | AY6: NA | AZ6: NA | BA6: NA | BB6: NA | BC6: Resolución 429 Resolución No. 545 | BD6: 31 de mayo de 2005 25 de octubre de 2013 | BE6: NA | BF6: X | BG6: NA | BH6: X | BI6: 41583 | BJ6: 41599 | BK6: 45251 | BL6: NA | BM6: NA | BN6: NA | BO6: NA | BP6: NA | BQ6: NA | BR6: NA | BS6: NA | BT6: NA | BU6: NA | BV6: NA | BW6: NA | BX6: NA | BY6: NA | BZ6: NA | CA6: NA | CB6: NA | CC6: NA | CD6: NA | CE6: NA | CF6: NA | CG6: NA | CH6: NA | CI6: NA | CJ6: NA | CK6: NA | CL6: NA | CM6: NA | CN6: NA | CO6: NA | CP6: Resolución 837 de fecha 16 de octubre de 2007 | CQ6: NA | CR6: NA | CS6: NA | CT6: NA | CU6: NA | CV6: NA | CW6: NA | CX6: NA | CY6: NA | CZ6: NA | DA6: NA | DB6: NA | DC6: 2014ER 5342 | DD6: 41956 | DE6: NA | DF6: NA | DG6: NA | DH6: NA | DI6: NA | DJ6: NA | DK6: EN TRAMITE DE DESISTIMIENTO | DL6: NA | DM6: NA | DN6: NA | DO6: NA | DP6: NA | DQ6: NA | DR6: NA | DS6: NA | DT6: NA | DU6: NA | DV6: NA | DW6: NA | DX6: NA | DY6: NA | DZ6: NA | EA6: NA | EB6: NA | EC6: NA | ED6: NA | EE6: NA | EF6: NA | EG6: NA | EH6: NA | EI6: NA | EJ6: NA | EK6: NA | EL6: NA | EM6: NA | EN6: NA | EO6: NA | EP6: NA | EQ6: NA | ER6: NA | ES6: NA | ET6: NA | EU6: NA | EV6: NA | EW6: NA | EX6: NA | EY6: NA | EZ6: NA | FA6: NA | FB6: NA | FC6: NA | FD6: PENDIENTE DECLARARA PERDIDA | FE6: 46142 | FF6: MILENA G

Sheet CA 2005
A1: DATOS DE LA SOLICITUD | O1: APERTURÓ | P1: REQUERIMIENTO | W1: PAGO SERVICIOS DE EVALUACION | AB1: No. Oficio/ Auto de Requerimiento | AE1: CONTROL- DIAS TRANSCURRIDOS HASTA FECHA DE VISITA | AF1: CONCEPTO TECNICO | AV1: CONTROL- DIAS TRANSCURRIDOS DE LA RADICACION AL CONCEPTO CON Vo.Bo. | AW1: FECHA DE ASIGNACION CONCEPTO AL AREA JURIDICO | AX1: REQUERIMIENTO | BC1: ACTO ADMINISTRATIVO | BL1: RECURSO DE REPOSICION | BS1: MEMORIAS DE CALCULO | CB1: RECIBO A SATISFACCION DE OBRAS | CK1: ACTO ADMINISTRATIVO | EU1: SEGUIMIENTO | FD1: Observaciones de lo evidenciado en la visita técnica | FE1: Ultima Actualización
A2: No. Radicado | B2: Fecha Radicado | C2: No. Expediente | D2: RADICADO EN VITAL | E2: Solicitante/Interesado | F2: Cédula de ciudadanía - NIT | G2: Dirección de correspondencia | H2: Telefono | I2: Correo Electrónico | J2: Municipio permiso | K2: Lugar de la captación (Vereda) | L2: Tipo de Fuente | M2: Fuente | N2: Nombre de la Fuente | P2: No. Oficio/ Auto de Requerimiento | Q2: Fecha Oficio/ Auto de Requerimiento | R2: Nombre de quién proyectó | S2: Dias del radicado al requerimiento | T2: Descripcion del requerimiento | U2: Radicado Oficio de entrada | V2: Fecha oficio de entrada | W2: No. de la Factura | X2: Valor tabla única (Factura) | Y2: Valor Facturado | Z2: Valor Cancelado | AA2: Fecha del pago servicio de evaluación | AB2: No. Oficio/ Auto de Requerimiento | AC2: Fecha Oficio/ Auto de Requerimiento | AD2: Nombre de quién proyectó | AF2: Fecha Visita técnica | AG2: Nombre del técnico | AH2: FECHA LIMITE ENTREGA DE CONCEPTO | AI2: DIAS CALENDARIO TRANSCURRIDOS SEGÚN FECHA LIMITE DE ENTRE DE CONCEPTO Y FECHA DE VISITA TECNICA | AJ2: ALERTAS | AK2: Fecha entrega a Revisión Informe - Lider | AL2: Entrega de Informe al técnico para corrección | AM2: Entrega de concepto corregido | AN2: Fecha Concepto técnico | AO2: Predio a beneficiar | AP2: Georreferenciación del punto de captación | AQ2: Vereda de la localización del punto de captación | AR2: Usos | AS2: Caudal Otordo, dicriminado por cada uso | AT2: Total del caudal otorgado | AU2: Número de Suscriptores | AX2: No. Auto de Requerimiento | AY2: Fecha Auto de Requerimiento | AZ2: Nombre de quién proyectó | BA2: Radicado Oficio de entrada | BB2: Fecha oficio de entrada | BC2: No. Acto Administrativo | BD2: Fecha Acto Administrativo | BE2: Nombre de quién proyectó | BF2: Otorgada | BG2: Negada | BH2: Desistida | BI2: Fecha Notificación | BJ2: Fecha ejecutoria | BK2: Fecha de vencimiento | BL2: No. Radicado | BM2: Fecha Radicado | BN2: No. Acto Administrativo | BO2: Fecha Acto Administrativo | BP2: Nombre de quién proyectó | BQ2: Modifica/ Aclara / Confirma/ Adiciona /Niega | BR2: Fecha Notificación | BS2: No. Radicado | BT2: Fecha Radicado | BU2: Auto Requer. | BV2: Fecha Requer. | BW2: Nombre de quién proyecto | BX2: No. Acto Administrativo | BY2: Fecha Act Administrativo | BZ2: Nombre de quien proyectó | CA2: Cumple o NO | CB2: No. Radicado del usuario | CC2: Fecha Radicado | CD2: Fecha de visita técnica | CE2: Fecha Informe técnico | CF2: Nombre del técnico | CG2: No. Acto Administrativo | CH2: Fecha Acto Administrativo | CI2: Nombre de quién proyectó | CJ2: Cumple o NO | CK2: No. Radicado | CL2: Fecha Radicado | CM2: Fecha de visita técnica | CN2: Fecha Informe técnico | CO2: Nombre del técnico | CP2: No. Acto Administrativo | CQ2: Fecha de notificación | CR2: Fecha de ejecutoria | CS2: Observación | CT2: No. Radicado | CU2: Fecha Radicado | CV2: Fecha de visita técnica | CW2: Fecha Informe técnico | CX2: Nombre del técnico | CY2: No. Acto Administrativo | CZ2: Fecha de notificación | DA2: Fecha de ejecutoria | DB2: Observación | DC2: No. Radicado | DD2: Fecha Radicado | DE2: Fecha de visita técnica | DF2: Fecha Informe técnico | DG2: Nombre del técnico | DH2: No. Acto Administrativo | DI2: Fecha de notificación | DJ2: Fecha de ejecutoria | DK2: Observación | DL2: No. Radicado | DM2: Fecha Radicado | DN2: Fecha de visita técnica | DO2: Fecha Informe técnico | DP2: Nombre del técnico | DQ2: No. Acto Administrativo | DR2: Fecha de notificación | DS2: Fecha de ejecutoria | DT2: Observación | DU2: No. Radicado | DV2: Fecha Radicado | DW2: Fecha de visita técnica | DX2: Fecha Informe técnico | DY2: Nombre del técnico | DZ2: No. Acto Administrativo | EA2: Fecha de notificación | EB2: Fecha de ejecutoria | EC2: Observación | ED2: No. Radicado | EE2: Fecha Radicado | EF2: Fecha de visita técnica | EG2: Fecha Informe técnico | EH2: Nombre del técnico | EI2: No. Acto Administrativo | EJ2: Fecha de notificación | EK2: Fecha de ejecutoria | EL2: Observación | EM2: Fecha Radicado | EN2: Fecha de visita técnica | EO2: Fecha Informe técnico | EP2: Nombre del técnico | EQ2: RECLAMACION TUA | ER2: Fecha de notificación | ES2: Fecha de ejecutoria | ET2: Observación | EU2: Fecha ultimo seguimiento | EV2: Fecha de concepto | EW2: Cadual Aforado (Captado o vertido) | EX2: Volumen metros cubicos aprovechado ( AF) aprovechamiento forestal | EY2: Entrega informes Anuales (L.A) Solo aplica para licencias ambientales | FB2: Acto administrativo
AV3: Solicitamos se agregue la formula | CP3: Modificacion | CY3: Traspaso | DH3: Prorroga | DQ3: Cancelación | DZ3: Perdida de fuerza ejecutoria | EI3: Suspensión | EY3: Llantas Usadas | EZ3: ICA | FA3: Autoliquidación de la vigencia | FB3: N° | FC3: Fecha
EY4: SI /NO
C5: C.A. 016/05 | E5: GUILLERMO CRUZ PULIDO | F5: 4221829 | G5: VEREDA CAICEDOS | I5: guillermocruz@gmail.com | J5: RAMIRIQUI | K5: CAICEDOS | L5: SUPERFICIAL | M5: NACIMIENTO | N5: EL ENCANTO | BC5: 441 408 | BD5: 31/05/2005 30/06/2016 | BF5: X | BK5: 06/30/2026 | BL5: NA | BM5: NA | BN5: NA | BO5: NA | BP5: NA | BQ5: NA | BR5: NA | BS5: NA | BT5: NA | BU5: NA | BV5: NA | BW5: NA | BX5: NA | BY5: NA | BZ5: NA | CA5: NA | CB5: NA | CC5: NA | CD5: NA | CE5: NA | CF5: NA | CG5: NA | CH5: NA | CI5: NA | CJ5: NA | CK5: NA | CL5: NA | CM5: NA | CN5: NA | CO5: NA | CP5: NA | CQ5: NA | CR5: NA | CS5: NA | CT5: NA | CU5: NA | CV5: NA | CW5: NA | CX5: NA | CY5: NA | CZ5: NA | DA5: NA | DB5: NA | DC5: NA | DD5: NA | DE5: NA | DF5: NA | DG5: NA | DH5: NA | DI5: NA | DJ5: NA | DK5: NA | DL5: NA | DM5: NA | DN5: NA | DO5: NA | DP5: NA | DQ5: NA | DR5: NA | DS5: NA | DT5: NA | DU5: NA | DV5: NA | DW5: NA | DX5: NA | DY5: NA | DZ5: NA | EA5: NA | EB5: NA | EC5: NA | ED5: NA | EE5: NA | EF5: NA | EG5: NA | EH5: NA | EI5: NA | EJ5: NA | EK5: NA | EL5: NA | EM5: NA | EN5: NA | EO5: NA | EP5: NA | EQ5: NA | ER5: NA | ES5: NA | ET5: NA | EU5: NA | EV5: NA | EW5: NA | EX5: NA | EY5: NA | EZ5: NA | FA5: NA | FB5: NA | FC5: NA | FD5: Seguimiento (Revisión): Requerido mediante Auto No. 0030 de fecha 13 de enero de 2026. En secretaria estan validando la perdida pues el municipio de Ramiriqui CA 48/17 (2026IE3787) | FE5: MILENA GALINDO
A6: 2005ER3566 | B6: 38525 | C6: CA 129-05 | D6: PENDIENTE | E6: EMILIO ANTONIO BENAVIDEZ MEDINA | F6: 6757421 | G6: VEREDA PUENTE DE BOYACA PREDIO VILLA LUZ | H6: 3112310083 | I6: emilio_antoniobm@hotmail.com | J6: VENTAQUEMADA | K6: VILLA LUZ | L6: SUPERFICIAL | M6: NACIMIENTO | N6: SIN NOMBRE | O6: NA | P6: NA | Q6: NA | R6: NA | S6: NA | T6: NA | U6: NA | V6: NA | W6: NA | X6: NA | Y6: NA | Z6: NA | AA6: NA | AB6: NA | AC6: NA | AD6: NA | AE6: NA | AF6: NA | AG6: NA | AH6: NA | AI6: NA | AJ6: NA | AK6: NA | AL6: NA | AM6: NA | AN6: NA | AO6: NA | AP6: NA | AQ6: NA | AR6: NA | AS6: NA | AT6: NA | AU6: NA | AV6: NA | AW6: NA | AX6: NA | AY6: NA | AZ6: NA | BA6: NA | BB6: NA | BC6: 403 | BD6: 38845 | BE6: JAVIER CORONADO | BF6: X | BG6: NA | BH6: NA | BI6: 38853 | BJ6: 38861 | BK6: 42514 | BL6: NA | BM6: NA | BN6: NA | BO6: NA | BP6: NA | BQ6: NA | BR6: NA | BS6: NA | BT6: NA | BU6: NA | BV6: NA | BW6: NA | BX6: NA | BY6: NA | BZ6: NA | CA6: NA | CB6: NA | CC6: NA | CD6: NA | CE6: NA | CF6: NA | CG6: NA | CH6: NA | CI6: NA | CJ6: NA | CK6: NA | CL6: NA | CM6: NA | CN6: NA | CO6: NA | CP6: 909 15/08/2006 | CQ6: NA | CR6: NA | CS6: NA | CT6: NA | CU6: NA | CV6: NA | CW6: NA | CX6: NA | CY6: NA | CZ6: NA | DA6: NA | DB6: NA | DC6: NA | DD6: NA | DE6: NA | DF6: NA | DG6: NA | DH6: NA | DI6: NA | DJ6: NA | DK6: NA | DL6: NA | DM6: NA | DN6: NA | DO6: NA | DP6: NA | DQ6: NA | DR6: NA | DS6: NA | DT6: NA | DU6: NA | DV6: NA | DW6: NA | DX6: NA | DY6: NA | DZ6: 1157 | EA6: 44902 | EB6: 44918 | EC6: NA | ED6: NA | EE6: NA | EF6: NA | EG6: NA | EH6: NA | EI6: NA | EJ6: NA | EK6: NA | EL6: NA | EM6: NA | EN6: NA | EO6: NA | EP6: NA | EQ6: NA | ER6: NA | ES6: NA | ET6: NA | EU6: NA | EV6: NA | EW6: NA | EX6: NA | EY6: NA | EZ6: NA | FA6: NA | FB6: NA | FC6: NA | FD6: A TRAVES DE LA RESOLUCION 693 DEL 18/09/2024 SE RESUELVE UNA RECLAMACION Y SE ANULAN UNAS FACTURAS POR CONCEPTO DE TASA POR UTILIZACION DEL AGUA | FE6: KAREN BARERTO | FF6: 45554
A7: 2005ER7104 | B7: 38679 | C7: CA 150-05 | D7: PENDIENTE | E7: FRANCISCO GUERRA PEDRAZA | F7: 6749899 | G7: CAROS Y GALINDOS | H7: 31320355507 | I7: josecaroplazas1978@hotmail.com | J7: VIRACACHA | K7: CAROS Y GALINDOS | L7: SUPERFICIAL | M7: NACEDERO | N7: LOMA GORDA | O7: NA | P7: NA | Q7: NA | R7: NA | S7: NA | T7: NA | U7: NA | V7: NA | W7: NA | X7: NA | Y7: NA | Z7: NA | AA7: NA | AB7: NA | AC7: NA | AD7: NA | AE7: NA | AF7: NA | AG7: NA | AH7: NA | AI7: NA | AJ7: NA | AK7: NA | AL7: NA | AM7: NA | AN7: NA | AO7: NA | AP7: NA | AQ7: NA | AR7: NA | AS7: NA | AT7: NA | AU7: NA | AV7: NA | AW7: NA | AX7: NA | AY7: NA | AZ7: NA | BA7: NA | BB7: NA | BC7: 533 | BD7: 38861 | BE7: PLINIOI FORERO | BF7: X | BG7: NA | BH7: NA | BI7: 38880 | BJ7: 38889 | BK7: 42542 | BL7: NA | BM7: NA | BN7: NA | BO7: NA | BP7: NA | BQ7: NA | BR7: NA | BS7: NA | BT7: NA | BU7: AUTO | BV7: 39066 | BW7: NA | BX7: NA | BY7: NA | BZ7: NA | CA7: SI | CB7: NA | CC7: NA | CD7: NA | CE7: NA | CF7: NA | CG7: NA | CH7: NA | CI7: NA | CJ7: NA | CK7: NA | CL7: NA | CM7: NA | CN7: NA | CO7: NA | CP7: NA | CQ7: NA | CR7: NA | CS7: NA | CT7: NA | CU7: NA | CV7: NA | CW7: NA | CX7: NA | CY7: NA | CZ7: NA | DA7: NA | DB7: NA | DC7: NA | DD7: NA | DE7: NA | DF7: NA | DG7: NA | DH7: NA | DI7: NA | DJ7: NA | DK7: NA | DL7: NA | DM7: NA | DN7: NA | DO7: NA | DP7: NA | DQ7: NA | DR7: NA | DS7: NA | DT7: NA | DU7: NA | DV7: NA | DW7: NA | DX7: NA | DY7: NA | DZ7: 717 | EA7: 45154 | EB7: 45170 | EC7: NA | ED7: NA | EE7: NA | EF7: NA | EG7: NA | EH7: NA | EI7: NA | EJ7: NA | EK7: NA | EL7: NA | EM7: NA | EN7: NA | EO7: NA | EP7: NA | EQ7: NA | ER7: NA | ES7: NA | ET7: NA | EU7: NA | EV7: NA | EW7: NA | EX7: NA | EY7: NA | EZ7: NA | FA7: NA | FB7: NA | FC7: NA | FD7: SE RESUELVE RECLAMACIO Y SE ANULAN FACTURAS DTUA 600 RESOLUCION 726 DEL 26/09/2024 | FE7: KAREN BARERTO | FF7: 45567

Sheet CA 2006
A1: DATOS DE LA SOLICITUD | O1: APERTURÓ | P1: REQUERIMIENTO | W1: PAGO SERVICIOS DE EVALUACION | AB1: No. Oficio/ Auto de ADMITE | AE1: CONTROL- DIAS TRANSCURRIDOS HASTA FECHA DE VISITA | AF1: CONCEPTO TECNICO | AV1: CONTROL- DIAS TRANSCURRIDOS DE LA RADICACION AL CONCEPTO CON Vo.Bo. | AW1: FECHA DE ASIGNACION CONCEPTO AL AREA JURIDICO | AX1: REQUERIMIENTO | BC1: ACTO ADMINISTRATIVO | BL1: RECURSO DE REPOSICION | BS1: MEMORIAS DE CALCULO | CB1: RECIBO A SATISFACCION DE OBRAS | CK1: ACTO ADMINISTRATIVO | EU1: SEGUIMIENTO | FD1: Observaciones de lo evidenciado en la visita técnica | FE1: Ultima Actualización | FF1: FECHA ACTUALIZACION
A2: No. Radicado | B2: Fecha Radicado | C2: No. Expediente | D2: RADICADO EN VITAL | E2: Solicitante/Interesado | F2: Cédula de ciudadanía - NIT | G2: Dirección de correspondencia | H2: Telefono | I2: Correo Electrónico | J2: Municipio permiso | K2: Lugar de la captación (Vereda) | L2: Tipo de Fuente | M2: Fuente | N2: Nombre de la Fuente | P2: No. Oficio/ Auto de Requerimiento | Q2: Fecha Oficio/ Auto de Requerimiento | R2: Nombre de quién proyectó | S2: Dias del radicado al requerimiento | T2: Descripcion del requerimiento | U2: Radicado Oficio de entrada | V2: Fecha oficio de entrada | W2: No. de la Factura | X2: Valor tabla única (Factura) | Y2: Valor Facturado | Z2: Valor Cancelado | AA2: Fecha del pago servicio de evaluación | AB2: No. Oficio/ Auto de ADMITE | AC2: Fecha Oficio/ Auto de ADMITE | AD2: Nombre de quién proyectó | AF2: Fecha Visita técnica | AG2: Nombre del técnico | AH2: FECHA LIMITE ENTREGA DE CONCEPTO | AI2: DIAS CALENDARIO TRANSCURRIDOS SEGÚN FECHA LIMITE DE ENTRE DE CONCEPTO Y FECHA DE VISITA TECNICA | AJ2: ALERTAS | AK2: Fecha entrega a Revisión Informe - Lider | AL2: Entrega de Informe al técnico para corrección | AM2: Entrega de concepto corregido | AN2: Fecha Concepto técnico | AO2: Predio a beneficiar | AP2: Georreferenciación del punto de captación | AQ2: Vereda de la localización del punto de captación | AR2: Usos | AS2: Caudal Otordo, dicriminado por cada uso | AT2: Total del caudal otorgado | AU2: Número de Suscriptores | AX2: No. Auto de Requerimiento | AY2: Fecha Auto de Requerimiento | AZ2: Nombre de quién proyectó | BA2: Radicado Oficio de entrada | BB2: Fecha oficio de entrada | BC2: No. Acto Administrativo | BD2: Fecha Acto Administrativo | BE2: Nombre de quién proyectó | BF2: Otorgada | BG2: Negada | BH2: Desistida | BI2: Fecha Notificación | BJ2: Fecha ejecutoria | BK2: Fecha de vencimiento | BL2: No. Radicado | BM2: Fecha Radicado | BN2: No. Acto Administrativo | BO2: Fecha Acto Administrativo | BP2: Nombre de quién proyectó | BQ2: Modifica/ Aclara / Confirma/ Adiciona /Niega | BR2: Fecha Notificación | BS2: No. Radicado | BT2: Fecha Radicado | BU2: Auto Requer. | BV2: Fecha Requer. | BW2: Nombre de quién proyecto | BX2: No. Acto Administrativo | BY2: Fecha Act Administrativo | BZ2: Nombre de quien proyectó | CA2: Cumple o NO | CB2: No. Radicado del usuario | CC2: Fecha Radicado | CD2: Fecha de visita técnica | CE2: Fecha Informe técnico | CF2: Nombre del técnico | CG2: No. Acto Administrativo | CH2: Fecha Acto Administrativo | CI2: Nombre de quién proyectó | CJ2: Cumple o NO | CK2: No. Radicado | CL2: Fecha Radicado | CM2: Fecha de visita técnica | CN2: Fecha Informe técnico | CO2: Nombre del técnico | CP2: No. Acto Administrativo | CQ2: Fecha de notificación | CR2: Fecha de ejecutoria | CS2: Observación | CT2: No. Radicado | CU2: Fecha Radicado | CV2: Fecha de visita técnica | CW2: Fecha Informe técnico | CX2: Nombre del técnico | CY2: No. Acto Administrativo | CZ2: Fecha de notificación | DA2: Fecha de ejecutoria | DB2: Observación | DC2: No. Radicado | DD2: Fecha Radicado | DE2: Fecha de visita técnica | DF2: Fecha Informe técnico | DG2: Nombre del técnico | DH2: No. Acto Administrativo | DI2: Fecha de notificación | DJ2: Fecha de ejecutoria | DK2: Observación | DL2: No. Radicado | DM2: Fecha Radicado | DN2: Fecha de visita técnica | DO2: Fecha Informe técnico | DP2: Nombre del técnico | DQ2: No. Acto Administrativo | DR2: Fecha de notificación | DS2: Fecha de ejecutoria | DT2: Observación | DU2: No. Radicado | DV2: Fecha Radicado | DW2: Fecha de visita técnica | DX2: Fecha Informe técnico | DY2: Nombre del técnico | DZ2: No. Acto Administrativo | EA2: Fecha de notificación | EB2: Fecha de ejecutoria | EC2: Observación | ED2: No. Radicado | EE2: Fecha Radicado | EF2: Fecha de visita técnica | EG2: Fecha Informe técnico | EH2: Nombre del técnico | EI2: No. Acto Administrativo | EJ2: Fecha de notificación | EK2: Fecha de ejecutoria | EL2: Observación | EM2: Fecha Radicado | EN2: Fecha de visita técnica | EO2: Fecha Informe técnico | EP2: Nombre del técnico | EQ2: RECLAMACION TUA | ER2: Fecha de notificación | ES2: Fecha de ejecutoria | ET2: Observación | EU2: Fecha ultimo seguimiento | EV2: Fecha de concepto | EW2: Cadual Aforado (Captado o vertido) | EX2: Volumen metros cubicos aprovechado ( AF) aprovechamiento forestal | EY2: Entrega informes Anuales (L.A) Solo aplica para licencias ambientales | FB2: Acto administrativo
AV3: Solicitamos se agregue la formula | CP3: Modificacion | CY3: Traspaso | DH3: Prorroga | DQ3: Cancelación | DZ3: Perdida de fuerza ejecutoria | EI3: Suspensión | EY3: Llantas Usadas | EZ3: ICA | FA3: Autoliquidación de la vigencia | FB3: N° | FC3: Fecha
EY4: SI /NO
A5: 2006ER1893 | B5: 38824 | C5: CA 073-06 | D5: PENDIENTE | E5: EDILFONSO VARGAS ESGUERRA | F5: 11382368 | G5: NA | H5: 3123629220 | I5: NA | J5: SAN LUIS DE GACENO | K5: NA | L5: SUPERFICIAL | M5: QUEBRADA | N5: EL TORO | O5: NA | P5: 2017EE2861 2022EE16704 2023EE87 2023EE2065 2024EE7331 2024EE8287 2024EE9531 | Q5: 24/05/2017 30/12/2022 10/01/2023 09/03/2023 06/08/2024 08/09/2024 | R5: FREDY P JUAN C JORGE G CAROL C MILENA G KAREN B MILENA G | S5: NA | T5: NA | U5: 2017ER2824 2017ER4111 2023ER563 2024ER6435 2024ER7995 2024ER8984 2024ER13688 | V5: 11/05/2017 30/06/201726/01/2023 18/07/2024 21/08/2024 05/09/2024 23/12/2024 | W5: SIN EVA 180 | X5: 138402 597175 | Y5: 138402 597175 | Z5: 138402 597175 | AA5: 28/06/2017 SIN | AB5: SIN | AC5: 38833 | AD5: YAMILEC | AE5: NA | AF5: 22/01/2007 31/08/2017 | AG5: ALFONSO VARGAS RONAL R | AH5: NA | AI5: NA | AJ5: NA | AK5: NA | AL5: NA | AM5: NA | AN5: 9/02/2007 12/09/2017 | AO5: LOTE | AP5: 010-24-663 011-00-470 ALTURA 445 | AQ5: CENTRO | AR5: INDUSTRIAL | AS5: 0.81 | AT5: 0.81 | AU5: 150 | AV5: NA | AW5: NA | AX5: 1060 | AY5: 43047 | AZ5: JEFER A | BA5: NA | BB5: NA | BC5: 126 | BD5: 39163 | BE5: RIAÑO | BF5: X | BG5: NA | BH5: NA | BI5: 39209 | BJ5: 39214 | BK5: NA | BL5: NA | BM5: NA | BN5: NA | BO5: NA | BP5: NA | BQ5: NA | BR5: NA | BS5: 2008EE4328 | BT5: 39625 | BU5: NA | BV5: NA | BW5: NA | BX5: NA | BY5: NA | BZ5: NA | CA5: NA | CB5: NA | CC5: NA | CD5: NA | CE5: NA | CF5: NA | CG5: NA | CH5: NA | CI5: NA | CJ5: NA | CK5: NA | CL5: NA | CM5: NA | CN5: NA | CO5: NA | CP5: NA | CQ5: NA | CR5: NA | CS5: NA | CT5: 2024ER6435 | CU5: 45491 | CV5: NA | CW5: NA | CX5: NA | CY5: RES 0172(08/04/2025) | CZ5: 45756 | DA5: 45772 | DB5: REQUERIDO MEDIANTE RADICADO 2024ER7331 | DC5: 2022ER12778 | DD5: 44923 | DE5: NA | DF5: NA | DG5: NA | DH5: 1517 (29-DIC-22) AUTO 682 (08/08/2017 RES 1517 | DI5: 11/03/2023 09/08/2017 29/12/2022 | DJ5: NA | DK5: NA | DL5: NA | DM5: NA | DN5: NA | DO5: NA | DP5: NA | DQ5: NA | DR5: NA | DS5: NA | DT5: NA | DU5: NA | DV5: NA | DW5: NA | DX5: NA | DY5: NA | DZ5: NA | EA5: NA | EB5: NA | EC5: NA | ED5: NA | EE5: NA | EF5: NA | EG5: NA | EH5: NA | EI5: NA | EJ5: NA | EK5: NA | EL5: NA | EM5: NA | EN5: NA | EO5: NA | EP5: NA | EQ5: NA | ER5: NA | ES5: NA | ET5: NA | EU5: 28/07/205 01/08/2024 | EV5: 28/07/2015 26/11/2024 | EW5: 0,21 0,00381 | EX5: NA | EY5: NA | EZ5: NA | FA5: NA | FB5: NA | FC5: NA | FD5: SE ENVIO POR MEDIO DE OFICIO 2025EE2298 SE NOTIFICA RES 0172 (08/04/2025 | FE5: MILENA GALINDO | FF5: 45758
C6: CA 089/06 | E6: ADEODATO CRUZ CARO | F6: 6747161 | G6: NA | H6: NA | I6: NA | J6: RAMIRIQUI | K6: EL COMUN | L6: SUPERFICIAL | M6: NA | N6: NA | O6: NA | P6: NA | Q6: NA | R6: NA | S6: NA | T6: NA | U6: NA | V6: NA | W6: NA | X6: NA | Y6: NA | Z6: NA | AA6: NA | AB6: NA | AC6: NA | AD6: NA | AE6: NA | AF6: NA | AG6: NA | AH6: NA | AI6: NA | AJ6: NA | AK6: NA | AL6: NA | AM6: NA | AN6: NA | AO6: NA | AP6: NA | AQ6: NA | AR6: NA | AS6: NA | AT6: NA | AU6: NA | AV6: NA | AW6: NA | AX6: NA | AY6: NA | AZ6: NA | BA6: NA | BB6: NA | BC6: 201 | BD6: 46501 | BE6: NA | BF6: NA | BG6: NA | BH6: NA | BI6: NA | BJ6: NA | BK6: NA | BL6: NA | BM6: NA | BN6: NA | BO6: NA | BP6: NA | BQ6: NA | BR6: NA | BS6: NA | BT6: NA | BU6: NA | BV6: NA | BW6: NA | BX6: NA | BY6: NA | BZ6: NA | CA6: NA | CB6: NA | CC6: NA | CD6: NA | CE6: NA | CF6: NA | CG6: NA | CH6: NA | CI6: NA | CJ6: NA | CK6: NA | CL6: NA | CM6: NA | CN6: NA | CO6: NA | CP6: NA | CQ6: NA | CR6: NA | CS6: NA | CT6: NA | CU6: NA | CV6: NA | CW6: NA | CX6: NA | CY6: NA | CZ6: NA | DA6: NA | DB6: NA | DC6: NA | DD6: NA | DE6: NA | DF6: NA | DG6: NA | DH6: 674 | DI6: 43732 | DJ6: 47250 | DK6: NA | DL6: NA | DM6: NA | DN6: NA | DO6: NA | DP6: NA | DQ6: NA | DR6: NA | DS6: NA | DT6: NA | DU6: NA | DV6: NA | DW6: NA | DX6: NA | DY6: NA | DZ6: NA | EA6: NA | EB6: NA | EC6: NA | ED6: NA | EE6: NA | EF6: NA | EG6: NA | EH6: NA | EI6: NA | EJ6: NA | EK6: NA | EL6: NA | EM6: NA | EN6: NA | EO6: NA | EP6: NA | EQ6: NA | ER6: NA | ES6: NA | ET6: NA | EU6: NA | EV6: NA | EW6: NA | EX6: NA | EY6: NA | EZ6: NA | FA6: NA | FB6: NA | FC6: NA | FD6: Requerido mediante Mediante Auto No. 1000 de fecha 28 de abril de 2023. | FE6: MILENA GALINDO | FF6: 45807
A7: 2016ER3129 | B7: 38889 | C7: CA 092-06 | D7: PENDIENTE | E7: LUZ DEL CARMEN BERMUDEZ | F7: 33675453 | G7: LAVA AUTOS LA QUIGUA | H7: 3133908852 | I7: NA | J7: GARAGOA | K7: REGUARDO MANZANOS ARRIBA | L7: SUPERFICIAL | M7: RIO | N7: RIO GARAGOA | O7: NA | P7: 2009ER5978 2014EE3320 2014EE8418 2022EE11064 2024ER10833 | Q7: 19/08/2009 10/04/2014 12/11/2014 18/09/2022 25/10/2024 19/09/2024 | R7: A RAMIREZ HERCY V LAURA C JEFER A ALEJANDRA G | S7: NA | T7: SOLICITUD AMPLIACION CONCESION. VISITA DE MONITOREO. DAR CUMPLIMIENTO AUTO. AJUSTES MEMORIAS Y PLANOS EVALUADOS MEDIANTE AUTO N 1000 | U7: NA | V7: NA | W7: NA | X7: NA | Y7: NA | Z7: NA | AA7: NA | AB7: 13 | AC7: 44225 | AD7: CRISTIAN FIGUEROA | AE7: NA | AF7: NA | AG7: NA | AH7: NA | AI7: NA | AJ7: NA | AK7: NA | AL7: NA | AM7: NA | AN7: NA | AO7: NA | AP7: NA | AQ7: NA | AR7: NA | AS7: NA | AT7: NA | AU7: NA | AV7: NA | AW7: NA | AX7: 13 1000 708 | AY7: 29/01/2021 15/09/2021 06/05/2022 | AZ7: CRISTIAN F JEFER A CRISTIAN F | BA7: NA | BB7: NA | BC7: 211 | BD7: 39196 | BE7: NA | BF7: X | BG7: NA | BH7: NA | BI7: 39211 | BJ7: 39227 | BK7: NA | BL7: NA | BM7: NA | BN7: NA | BO7: NA | BP7: NA | BQ7: NA | BR7: NA | BS7: 2008ER5608 2021ER4582 | BT7: 23/10/2008 10/06/2021 | BU7: NA | BV7: NA | BW7: NA | BY7: SIN CONSECUTIVO | BZ7: O FORERO | CA7: SI | CB7: 2009ER5307 | CC7: 40109 | CD7: 41506 | CE7: 41550 | CF7: FREDY M | CG7: NA | CH7: NA | CI7: NA | CJ7: NA | CK7: NA | CL7: NA | CM7: NA | CN7: NA | CO7: NA | CP7: NA | CQ7: NA | CR7: NA | CS7: NA | CT7: NA | CU7: NA | CV7: NA | CW7: NA | CX7: NA | CY7: NA | CZ7: NA | DA7: NA | DB7: NA | DC7: 2017ER1756 | DD7: 42817 | DE7: 42873 | DF7: 42901 | DG7: LAURA LOZANO | DH7: 293 | DI7: 42842 | DJ7: 42873 | DK7: NA | DL7: NA | DM7: NA | DN7: NA | DO7: NA | DP7: NA | DQ7: NA | DR7: NA | DS7: NA | DT7: NA | DU7: NA | DV7: NA | DW7: NA | DX7: NA | DY7: NA | DZ7: NA | EA7: NA | EB7: NA | EC7: NA | ED7: NA | EE7: NA | EF7: NA | EG7: NA | EH7: NA | EI7: NA | EJ7: NA | EK7: NA | EL7: NA | EM7: NA | EN7: NA | EO7: NA | EP7: NA | EQ7: NA | ER7: NA | ES7: NA | ET7: NA | EU7: 17/06/2009 11/11/2020 25/11/2021 29/072024 | EV7: 1/08/2009 10/12/2020 23/12/2021 26/09/2024 | EW7: 0,567 0,23 0,171 | EX7: NA | EY7: NA | EZ7: NA | FA7: NA | FB7: NA | FC7: NA | FD7: PENDIENTE RESPUESTA ALLEGAR DOCUMENTOS MEDIANTE RADICADO 2024EE10833 | FE7: ALEJANDRA GUERRERO | FF7: 45601

Sheet CA 2007
A1: DATOS DE LA SOLICITUD | O1: APERTURÓ | P1: REQUERIMIENTO | W1: PAGO SERVICIOS DE EVALUACION | AB1: No. Oficio/ Auto de ADMITE | AE1: CONTROL- DIAS TRANSCURRIDOS HASTA FECHA DE VISITA | AF1: CONCEPTO TECNICO | AV1: CONTROL- DIAS TRANSCURRIDOS DE LA RADICACION AL CONCEPTO CON Vo.Bo. | AW1: FECHA DE ASIGNACION CONCEPTO AL AREA JURIDICO | AX1: REQUERIMIENTO | BC1: ACTO ADMINISTRATIVO | BL1: RECURSO DE REPOSICION | BS1: MEMORIAS DE CALCULO | CB1: RECIBO A SATISFACCION DE OBRAS | CK1: ACTO ADMINISTRATIVO | EU1: SEGUIMIENTO | FD1: Observaciones de lo evidenciado en la visita técnica | FE1: Ultima Actualización | FF1: FECHA ACTUALIZACION
A2: No. Radicado | B2: Fecha Radicado | C2: No. Expediente | D2: RADICADO EN VITAL | E2: Solicitante/Interesado | F2: Cédula de ciudadanía - NIT | G2: Dirección de correspondencia | H2: Telefono | I2: Correo Electrónico | J2: Municipio permiso | K2: Lugar de la captación (Vereda) | L2: Tipo de Fuente | M2: Fuente | N2: Nombre de la Fuente | P2: No. Oficio/ Auto de Requerimiento | Q2: Fecha Oficio/ Auto de Requerimiento | R2: Nombre de quién proyectó | S2: Dias del radicado al requerimiento | T2: Descripcion del requerimiento | U2: Radicado Oficio de entrada | V2: Fecha oficio de entrada | W2: No. de la Factura | X2: Valor tabla única (Factura) | Y2: Valor Facturado | Z2: Valor Cancelado | AA2: Fecha del pago servicio de evaluación | AB2: No. Oficio/ Auto de ADMITE | AC2: Fecha Oficio/ Auto de ADMITE | AD2: Nombre de quién proyectó | AF2: Fecha Visita técnica | AG2: Nombre del técnico | AH2: FECHA LIMITE ENTREGA DE CONCEPTO | AI2: DIAS CALENDARIO TRANSCURRIDOS SEGÚN FECHA LIMITE DE ENTRE DE CONCEPTO Y FECHA DE VISITA TECNICA | AJ2: ALERTAS | AK2: Fecha entrega a Revisión Informe - Lider | AL2: Entrega de Informe al técnico para corrección | AM2: Entrega de concepto corregido | AN2: Fecha Concepto técnico | AO2: Predio a beneficiar | AP2: Georreferenciación del punto de captación | AQ2: Vereda de la localización del punto de captación | AR2: Usos | AS2: Caudal Otordo, dicriminado por cada uso | AT2: Total del caudal otorgado | AU2: Número de Suscriptores | AX2: No. Auto de Requerimiento | AY2: Fecha Auto de Requerimiento | AZ2: Nombre de quién proyectó | BA2: Radicado Oficio de entrada | BB2: Fecha oficio de entrada | BC2: No. Acto Administrativo | BD2: Fecha Acto Administrativo | BE2: Nombre de quién proyectó | BF2: Otorgada | BG2: Negada | BH2: Desistida | BI2: Fecha Notificación | BJ2: Fecha ejecutoria | BK2: Fecha de vencimiento | BL2: No. Radicado | BM2: Fecha Radicado | BN2: No. Acto Administrativo | BO2: Fecha Acto Administrativo | BP2: Nombre de quién proyectó | BQ2: Modifica/ Aclara / Confirma/ Adiciona /Niega | BR2: Fecha Notificación | BS2: No. Radicado | BT2: Fecha Radicado | BU2: Auto Requer. | BV2: Fecha Requer. | BW2: Nombre de quién proyecto | BX2: No. Acto Administrativo | BY2: Fecha Act Administrativo | BZ2: Nombre de quien proyectó | CA2: Cumple o NO | CB2: No. Radicado del usuario | CC2: Fecha Radicado | CD2: Fecha de visita técnica | CE2: Fecha Informe técnico | CF2: Nombre del técnico | CG2: No. Acto Administrativo | CH2: Fecha Acto Administrativo | CI2: Nombre de quién proyectó | CJ2: Cumple o NO | CK2: No. Radicado | CL2: Fecha Radicado | CM2: Fecha de visita técnica | CN2: Fecha Informe técnico | CO2: Nombre del técnico | CP2: No. Acto Administrativo | CQ2: Fecha de notificación | CR2: Fecha de ejecutoria | CS2: Observación | CT2: No. Radicado | CU2: Fecha Radicado | CV2: Fecha de visita técnica | CW2: Fecha Informe técnico | CX2: Nombre del técnico | CY2: No. Acto Administrativo | CZ2: Fecha de notificación | DA2: Fecha de ejecutoria | DB2: Observación | DC2: No. Radicado | DD2: Fecha Radicado | DE2: Fecha de visita técnica | DF2: Fecha Informe técnico | DG2: Nombre del técnico | DH2: No. Acto Administrativo | DI2: Fecha de notificación | DJ2: Fecha de ejecutoria | DK2: Observación | DL2: No. Radicado | DM2: Fecha Radicado | DN2: Fecha de visita técnica | DO2: Fecha Informe técnico | DP2: Nombre del técnico | DQ2: No. Acto Administrativo | DR2: Fecha de notificación | DS2: Fecha de ejecutoria | DT2: Observación | DU2: No. Radicado | DV2: Fecha Radicado | DW2: Fecha de visita técnica | DX2: Fecha Informe técnico | DY2: Nombre del técnico | DZ2: No. Acto Administrativo | EA2: Fecha de notificación | EB2: Fecha de ejecutoria | EC2: Observación | ED2: No. Radicado | EE2: Fecha Radicado | EF2: Fecha de visita técnica | EG2: Fecha Informe técnico | EH2: Nombre del técnico | EI2: No. Acto Administrativo | EJ2: Fecha de notificación | EK2: Fecha de ejecutoria | EL2: Observación | EM2: Fecha Radicado | EN2: Fecha de visita técnica | EO2: Fecha Informe técnico | EP2: Nombre del técnico | EQ2: RECLAMACION TUA | ER2: Fecha de notificación | ES2: Fecha de ejecutoria | ET2: Observación | EU2: Fecha ultimo seguimiento | EV2: Fecha de concepto | EW2: Cadual Aforado (Captado o vertido) | EX2: Volumen metros cubicos aprovechado ( AF) aprovechamiento forestal | EY2: Entrega informes Anuales (L.A) Solo aplica para licencias ambientales | FB2: Acto administrativo
AV3: Solicitamos se agregue la formula | CP3: Modificacion | CY3: Traspaso | DH3: Prorroga | DQ3: Cancelación | DZ3: Perdida de fuerza ejecutoria | EI3: Suspensión | EY3: Llantas Usadas | EZ3: ICA | FA3: Autoliquidación de la vigencia | FB3: N° | FC3: Fecha
EY4: SI /NO
A5: 2007ER070 | B5: 39086 | C5: CA 011-07 | D5: PENDIENTE | E5: PERSONERIA UMBITA | H5: 3202337926 | I5: contactenos@umbita-boyaca.gov.co | J5: UMBITA | FD5: SE MNIEGA POR MEIDIO DE RES 770 DEL 20/08/2025 | FE5: 45897 | FF5: KAREN BARRETO

Sheet CA 2008
C1: CONTROL TRAMITE DE CONCESION DE AGUAS 2024 | FD1: Código | FE1: RE-AA-20 | FF1: FECHA ACTUALIZACION
FD2: Versión | FE2: 7
FD3: Fecha | FE3: 44411
A4: DATOS DE LA SOLICITUD | O4: APERTURÓ | P4: REQUERIMIENTO | W4: PAGO SERVICIOS DE EVALUACION | AB4: No. Oficio/ Auto de Requerimiento | AE4: CONTROL- DIAS TRANSCURRIDOS HASTA FECHA DE VISITA | AF4: CONCEPTO TECNICO | AV4: CONTROL- DIAS TRANSCURRIDOS DE LA RADICACION AL CONCEPTO CON Vo.Bo. | AW4: FECHA DE ASIGNACION CONCEPTO AL AREA JURIDICO | AX4: REQUERIMIENTO | BC4: ACTO ADMINISTRATIVO | BL4: RECURSO DE REPOSICION | BS4: MEMORIAS DE CALCULO | CB4: RECIBO A SATISFACCION DE OBRAS | CK4: ACTO ADMINISTRATIVO | EU4: SEGUIMIENTO | FD4: Observaciones de lo evidenciado en la visita técnica | FE4: Ultima Actualización
A5: No. Radicado | B5: Fecha Radicado | C5: No. Expediente | D5: RADICADO EN VITAL | E5: Solicitante/Interesado | F5: Cédula de ciudadanía - NIT | G5: Dirección de correspondencia | H5: Telefono | I5: Correo Electrónico | J5: Municipio permiso | K5: Lugar de la captación (Vereda) | L5: Tipo de Fuente | M5: Fuente | N5: Nombre de la Fuente | P5: No. Oficio/ Auto de Requerimiento | Q5: Fecha Oficio/ Auto de Requerimiento | R5: Nombre de quién proyectó | S5: Dias del radicado al requerimiento | T5: Descripcion del requerimiento | U5: Radicado Oficio de entrada | V5: Fecha oficio de entrada | W5: No. de la Factura | X5: Valor tabla única (Factura) | Y5: Valor Facturado | Z5: Valor Cancelado | AA5: Fecha del pago servicio de evaluación | AB5: No. Oficio/ Auto de Requerimiento | AC5: Fecha Oficio/ Auto de Requerimiento | AD5: Nombre de quién proyectó | AF5: Fecha Visita técnica | AG5: Nombre del técnico | AH5: FECHA LIMITE ENTREGA DE CONCEPTO | AI5: DIAS CALENDARIO TRANSCURRIDOS SEGÚN FECHA LIMITE DE ENTRE DE CONCEPTO Y FECHA DE VISITA TECNICA | AJ5: ALERTAS | AK5: Fecha entrega a Revisión Informe - Lider | AL5: Entrega de Informe al técnico para corrección | AM5: Entrega de concepto corregido | AN5: Fecha Concepto técnico | AO5: Predio a beneficiar | AP5: Georreferenciación del punto de captación | AQ5: Vereda de la localización del punto de captación | AR5: Usos | AS5: Caudal Otordo, dicriminado por cada uso | AT5: Total del caudal otorgado | AU5: Número de Suscriptores | AX5: No. Auto de Requerimiento | AY5: Fecha Auto de Requerimiento | AZ5: Nombre de quién proyectó | BA5: Radicado Oficio de entrada | BB5: Fecha oficio de entrada | BC5: No. Acto Administrativo | BD5: Fecha Acto Administrativo | BE5: Nombre de quién proyectó | BF5: Otorgada | BG5: Negada | BH5: Desistida | BI5: Fecha Notificación | BJ5: Fecha ejecutoria | BK5: Fecha de vencimiento | BL5: No. Radicado | BM5: Fecha Radicado | BN5: No. Acto Administrativo | BO5: Fecha Acto Administrativo | BP5: Nombre de quién proyectó | BQ5: Modifica/ Aclara / Confirma/ Adiciona /Niega | BR5: Fecha Notificación | BS5: No. Radicado | BT5: Fecha Radicado | BU5: Auto Requer. | BV5: Fecha Requer. | BW5: Nombre de quién proyecto | BX5: No. Acto Administrativo | BY5: Fecha Act Administrativo | BZ5: Nombre de quien proyectó | CA5: Cumple o NO | CB5: No. Radicado del usuario | CC5: Fecha Radicado | CD5: Fecha de visita técnica | CE5: Fecha Informe técnico | CF5: Nombre del técnico | CG5: No. Acto Administrativo | CH5: Fecha Acto Administrativo | CI5: Nombre de quién proyectó | CJ5: Cumple o NO | CK5: No. Radicado | CL5: Fecha Radicado | CM5: Fecha de visita técnica | CN5: Fecha Informe técnico | CO5: Nombre del técnico | CP5: No. Acto Administrativo | CQ5: Fecha de notificación | CR5: Fecha de ejecutoria | CS5: Observación | CT5: No. Radicado | CU5: Fecha Radicado | CV5: Fecha de visita técnica | CW5: Fecha Informe técnico | CX5: Nombre del técnico | CY5: No. Acto Administrativo | CZ5: Fecha de notificación | DA5: Fecha de ejecutoria | DB5: Observación | DC5: No. Radicado | DD5: Fecha Radicado | DE5: Fecha de visita técnica | DF5: Fecha Informe técnico | DG5: Nombre del técnico | DH5: No. Acto Administrativo | DI5: Fecha de notificación | DJ5: Fecha de ejecutoria | DK5: Observación | DL5: No. Radicado | DM5: Fecha Radicado | DN5: Fecha de visita técnica | DO5: Fecha Informe técnico | DP5: Nombre del técnico | DQ5: No. Acto Administrativo | DR5: Fecha de notificación | DS5: Fecha de ejecutoria | DT5: Observación | DU5: No. Radicado | DV5: Fecha Radicado | DW5: Fecha de visita técnica | DX5: Fecha Informe técnico | DY5: Nombre del técnico | DZ5: No. Acto Administrativo | EA5: Fecha de notificación | EB5: Fecha de ejecutoria | EC5: Observación | ED5: No. Radicado | EE5: Fecha Radicado | EF5: Fecha de visita técnica | EG5: Fecha Informe técnico | EH5: Nombre del técnico | EI5: No. Acto Administrativo | EJ5: Fecha de notificación | EK5: Fecha de ejecutoria | EL5: Observación | EM5: Fecha Radicado | EN5: Fecha de visita técnica | EO5: Fecha Informe técnico | EP5: Nombre del técnico | EQ5: RECLAMACION TUA | ER5: Fecha de notificación | ES5: Fecha de ejecutoria | ET5: Observación | EU5: Fecha ultimo seguimiento | EV5: Fecha de concepto | EW5: Cadual Aforado (Captado o vertido) | EX5: Volumen metros cubicos aprovechado ( AF) aprovechamiento forestal | EY5: Entrega informes Anuales (L.A) Solo aplica para licencias ambientales | FB5: Acto administrativo
AV6: Solicitamos se agregue la formula | CP6: Modificacion | CY6: Traspaso | DH6: Prorroga | DQ6: Cancelación | DZ6: Perdida de fuerza ejecutoria | EI6: Suspensión | EY6: Llantas Usadas | EZ6: ICA | FA6: Autoliquidación de la vigencia | FB6: N° | FC6: Fecha
EY7: SI /NO
A8: 2008ER2094 | B8: 39560 | C8: CA 043-2008 | E8: MARIA MERCEDES ALFONSO FULA | F8: 23554447 | G8: VEREDA EL VOLADOR | J8: SAN LUIS DE GACENO | L8: SUPERFICIAL | N8: EL MUCHILERO | BC8: 415 | BD8: 39616 | BE8: SIERRA | BF8: X | BI8: 39640 | BJ8: 39650 | BK8: 43302 | DW8: 39983 | DX8: 40001 | DZ8: 1685 (22 NOV 2021) | EA8: 44552 | EC8: EN EL ULTIMO CONCEPTO SE EVIDENCIA QUE SI EXISTEN OBRAS | FD8: VENCIDO | FE8: 45502
C9: CA 069-08 | E9: ALCALDIA MUNICIPAL DE SOMONDOCO | F9: 80029826-5 | G9: ALCALDIA MUNICIPAL | H9: 3164634439 | I9: alcaldia@somondoco-boyaca.gov.co | J9: SOMONDOCO | K9: VEREDA CANOS | L9: SUPERFICIAL | M9: QUEBRADA0 | N9: LA CUYA | P9: 2020EE9101 2021EE9270 2021EE9143 2024EE12939 2024EE13383 2025EE380 | Q9: 22/12/2020 13/09/2021 08/09/2021 10/12/2024 20/12/2024 03/02/2025 | R9: YEFER AVILA VALENTINA L DIEGO R KAREN B MILENA G ELIANA C | S9: NA | T9: NA | U9: 2020ER696 2020ER7906 2021ER3606 2021ER5812 2021ER6803 2021ER7244 2024ER13038 2024ER13039 2024ER13694 2025ER339 | V9: 4/02/2020 27/11/20 11/05/2021 16/07/2021 18/08/2021 30/08/2021 02/12/2024 02/12/2024 23/12/2024 17/01/2025 | W9: SSEG161 EVA265 | X9: 148485 298288 | Y9: 148485 298288 | Z9: 148485 298288 | AA9: SIN 16/01/2025 | AB9: 828 0090 | AC9: 6/08/2021 11/03/2025 | AD9: JUAN CRUZ MILENA G | AF9: 45751 | AG9: ADRIAN DIAZ | AH9: NA | AI9: NA | AJ9: NA | AK9: NA | AL9: NA | AM9: NA | AN9: 45769 | AO9: MUNICIPIO SOMONDOCO | AP9: 73°26´16,72" 4°55´2,71" ALTURA 2698 | AQ9: SAN SEBASTIAN | AR9: DOMESTICO INDUSTRIAL | AS9: 4,829 0,006 | AT9: 4835 | AU9: 566 USUARIOS | AX9: 3761 957 | AY9: 7/12/2023 19/09/2024 | AZ9: ADRIANA MORA CESAR V | BA9: NA | BB9: NA | BC9: 110 | BD9: 43650 | BE9: DIANA J | BF9: X | BG9: NA | BH9: NA | BI9: 39850 | BJ9: 39867 | BK9: 43519 | CP9: 1695(22/11/21) 402(03/06/2025) | CQ9: 23/11/2021 05/06/2025 | CR9: 44539 | CS9: 45828 | DH9: 417(04/07/2019) | EQ9: NA | ER9: NA | ES9: NA | ET9: NA | EU9: 27/07/2023 24/07/2024 | EV9: 28/11/2023 04/09/2024 | EW9: 4,36 51,18 | EX9: NA | EY9: NA | EZ9: NA | FA9: NA | FB9: NA | FC9: NA | FD9: MODIFICADA | FE9: KAREN BARRETO | FF9: 45819
B10: 45936 | C10: CA 086-08 | D10: PENDIENTE | E10: MARIA PATRICIA DURAN TORRES | F10: 41348702 | G10: JENESANO | H10: 3163963192 | I10: N/A | J10: JENESANO | K10: NARANJOS | L10: SUPERFICIAL | M10: QUEBRADA | N10: LA ROSA | O10: NA | P10: NA | Q10: NA | R10: NA | S10: NA | T10: NA | U10: NA | V10: NA | W10: NA | X10: NA | Y10: NA | Z10: NA | AA10: NA | AB10: NA | AC10: NA | AD10: NA | AE10: NA | AF10: NA | AG10: NA | AH10: NA | AI10: NA | AJ10: NA | AK10: NA | AL10: NA | AM10: NA | AN10: NA | AO10: NA | AP10: NA | AQ10: NA | AR10: NA | AS10: NA | AT10: NA | AU10: NA | AV10: NA | AW10: NA | AX10: NA | AY10: NA | AZ10: NA | BA10: NA | BB10: NA | BC10: 286 | BD10: 17/03/2019 | BE10: CARLOS ANDRES | BF10: X | BG10: NA | BH10: NA | BI10: 39941 | BJ10: 39951 | BK10: 43603 | BL10: NA | BM10: NA | BN10: NA | BO10: NA | BP10: NA | BQ10: NA | BR10: NA | BS10: NA | BT10: NA | BU10: NA | BV10: NA | BW10: NA | BX10: 683 | BY10: 41968 | BZ10: NA | CA10: SI | CB10: NA | CC10: NA | CD10: NA | CE10: NA | CF10: NA | CG10: NA | CH10: NA | CI10: NA | CJ10: NA | CK10: NA | CL10: NA | CM10: NA | CN10: NA | CO10: NA | CP10: NA | CQ10: NA | CR10: NA | CS10: NA | CT10: NA | CU10: NA | CV10: NA | CW10: NA | CX10: NA | CY10: NA | CZ10: NA | DA10: NA | DB10: NA | DC10: NA | DD10: NA | DE10: NA | DF10: NA | DG10: NA | DH10: NA | DI10: NA | DJ10: NA | DK10: AUTO No. 397 de 2019 (admite solicitud de prorroga) | DL10: NA | DM10: NA | DN10: NA | DO10: NA | DP10: NA | DQ10: NA | DR10: NA | DS10: NA | DT10: NA | DU10: NA | DV10: NA | DW10: NA | DX10: NA | DY10: NA | DZ10: 133 | EA10: 44273 | EB10: NA | EC10: EN PROCESO DE NOTIFICACION | ED10: NA | EE10: NA | EF10: NA | EG10: NA | EH10: NA | EI10: NA | EJ10: NA | EK10: NA | EL10: NA | EM10: NA | EN10: NA | EO10: NA | EP10: NA | EQ10: NA | ER10: NA | ES10: NA | ET10: NA | EU10: NA | EV10: NA | EW10: NA | EX10: NA | EY10: NA | EZ10: NA | FA10: NA | FB10: NA | FC10: NA | FD10: PENDIENTE POR NOTIFICAR PERDIDA DE FUERZA EJECUTORIA | FE10: MILENA GALINDO | FF10: 45964
A11: 2008ER6568 | B11: 39792 | C11: CA 105-08 | D11: PENDIENTE | E11: OMAR RENE CORREA VALDERRAMA | F11: 74323037 | G11: TURMEQUE | H11: 3103463300 | I11: rodriguezm@procuraduria.gov.co | J11: TURMEQUE | K11: PASCATA | L11: SUPERFICIAL | M11: RIO | N11: MUINCHA | O11: NA | P11: NA | Q11: NA | R11: NA | S11: NA | T11: NA | U11: NA | V11: NA | W11: NA | X11: NA | Y11: NA | Z11: NA | AA11: NA | AB11: NA | AC11: NA | AD11: NA | AE11: NA | AF11: 39876 | AG11: HENRY LESMES | AI11: NA | AJ11: NA | AK11: NA | AL11: NA | AM11: NA | AN11: 39876 | AO11: ACUEDUCTO | AP11: NA | AQ11: PASCATA | AR11: PECUARIO RIEGO | AS11: NA | AT11: 7.51 | AU11: 35 BOVINO 15 HECTAREAS | AV11: NA | AW11: NA | AX11: NA | AY11: NA | AZ11: NA | BA11: NA | BB11: NA | BC11: 665 | BD11: 39889 | BE11: PLINIO R | BF11: X | BG11: NA | BH11: NA | BI11: 40214 | BJ11: 1502/2010 | BK11: 43876 | BL11: NA | BM11: NA | BN11: NA | BO11: NA | BP11: NA | BQ11: NA | BR11: NA | BS11: NA | BT11: NA | BU11: NA | BV11: NA | BW11: NA | BX11: 683 | BY11: 41968 | BZ11: NA | CA11: SI | CB11: NA | CC11: NA | CD11: NA | CE11: NA | CF11: NA | CG11: NA | CH11: NA | CI11: NA | CJ11: NA | CK11: NA | CL11: NA | CM11: NA | CN11: NA | CO11: NA | CP11: NA | CQ11: NA | CR11: NA | CS11: NA | CT11: NA | CU11: NA | CV11: NA | CW11: NA | CX11: NA | CY11: NA | CZ11: NA | DA11: NA | DB11: NA | DC11: NA | DD11: NA | DE11: NA | DF11: NA | DG11: NA | DH11: NA | DI11: NA | DJ11: NA | DK11: NA | DL11: NA | DM11: NA | DN11: NA | DO11: NA | DP11: NA | DQ11: NA | DR11: NA | DS11: NA | DT11: NA | DU11: NA | DV11: NA | DW11: NA | DX11: NA | DY11: NA | DZ11: 711 | EA11: SIN NOTIFICAR | EB11: NA | EC11: NA | ED11: NA | EE11: NA | EF11: NA | EG11: NA | EH11: NA | EI11: NA | EJ11: NA | EK11: NA | EL11: NA | EM11: NA | EN11: NA | EO11: NA | EP11: NA | EQ11: NA | ER11: NA | ES11: NA | ET11: NA | EU11: NA | EV11: NA | EW11: NA | EX11: NA | EY11: NA | EZ11: NA | FA11: NA | FB11: NA | FC11: NA | FD11: PENDIENTE POR NOTIFICAR PERDIDA DE FUERZA EJECUTORIA | FE11: MILENA GALINDO | FF11: 45566
A12: 2008ER6762 | B12: 39804 | C12: CA 110-08 | D12: PENDIENTE | E12: ASOCIACIÓN DE USUARIOS DEL DISTRITO DE ADECUACIÓN DE TIERRAS DE PEQUEÑA ESCALA (ASOGUATARETA) | G12: VEREDA GUATARETA | H12: 3143728228 | J12: CIÉNEGA | K12: GUATARETA | L12: SUPERFICIAL | M12: QUEBRADA | N12: EL ARENAL | O12: NA | P12: NA | AC12: 39811 | AF12: 39869 | AG12: HENRRY LESMES | AN12: 39876 | AQ12: GUATARETA | AR12: RIEGO | AT12: 32 | AU12: 80 HECTAREAS | BC12: 817 | BD12: 40105 | BF12: X | BI12: 40214 | BJ12: 40224 | BK12: 43876 | FD12: RESOLUCIÓN No. 885 DE FECHA 12/11/2024 POR MEDIO DE LA CUAL SE PRORROGA UN PERMISO DE CONCESIÓN DE AGUAS SUPERFICIALES Y SE ADOPTAN OTRAS DETERMINACIONES | FE12: PAULA MORENO | FF12: 45614

Sheet CA 2009
C1: CONTROL TRAMITE DE CONCESION DE AGUAS 2024 | FD1: Código | FE1: RE-AA-20
FD2: Versión | FE2: 7
FD3: Fecha | FE3: 44411
A4: DATOS DE LA SOLICITUD | O4: APERTURÓ | P4: REQUERIMIENTO | W4: PAGO SERVICIOS DE EVALUACION | AB4: No. Oficio/ Auto de Requerimiento | AE4: CONTROL- DIAS TRANSCURRIDOS HASTA FECHA DE VISITA | AF4: CONCEPTO TECNICO | AV4: CONTROL- DIAS TRANSCURRIDOS DE LA RADICACION AL CONCEPTO CON Vo.Bo. | AW4: FECHA DE ASIGNACION CONCEPTO AL AREA JURIDICO | AX4: REQUERIMIENTO | BC4: ACTO ADMINISTRATIVO | BL4: RECURSO DE REPOSICION | BS4: MEMORIAS DE CALCULO | CB4: RECIBO A SATISFACCION DE OBRAS | CK4: ACTO ADMINISTRATIVO | EU4: SEGUIMIENTO | FD4: Observaciones de lo evidenciado en la visita técnica | FE4: Ultima Actualización
A5: No. Radicado | B5: Fecha Radicado | C5: No. Expediente | D5: RADICADO EN VITAL | E5: Solicitante/Interesado | F5: Cédula de ciudadanía - NIT | G5: Dirección de correspondencia | H5: Telefono | I5: Correo Electrónico | J5: Municipio permiso | K5: Lugar de la captación (Vereda) | L5: Tipo de Fuente | M5: Fuente | N5: Nombre de la Fuente | P5: No. Oficio/ Auto de Requerimiento | Q5: Fecha Oficio/ Auto de Requerimiento | R5: Nombre de quién proyectó | S5: Dias del radicado al requerimiento | T5: Descripcion del requerimiento | U5: Radicado Oficio de entrada | V5: Fecha oficio de entrada | W5: No. de la Factura | X5: Valor tabla única (Factura) | Y5: Valor Facturado | Z5: Valor Cancelado | AA5: Fecha del pago servicio de evaluación | AB5: No. Oficio/ Auto de Requerimiento | AC5: Fecha Oficio/ Auto de Requerimiento | AD5: Nombre de quién proyectó | AF5: Fecha Visita técnica | AG5: Nombre del técnico | AH5: FECHA LIMITE ENTREGA DE CONCEPTO | AI5: DIAS CALENDARIO TRANSCURRIDOS SEGÚN FECHA LIMITE DE ENTRE DE CONCEPTO Y FECHA DE VISITA TECNICA | AJ5: ALERTAS | AK5: Fecha entrega a Revisión Informe - Lider | AL5: Entrega de Informe al técnico para corrección | AM5: Entrega de concepto corregido | AN5: Fecha Concepto técnico | AO5: Predio a beneficiar | AP5: Georreferenciación del punto de captación | AQ5: Vereda de la localización del punto de captación | AR5: Usos | AS5: Caudal Otordo, dicriminado por cada uso | AT5: Total del caudal otorgado | AU5: Número de Suscriptores | AX5: No. Auto de Requerimiento | AY5: Fecha Auto de Requerimiento | AZ5: Nombre de quién proyectó | BA5: Radicado Oficio de entrada | BB5: Fecha oficio de entrada | BC5: No. Acto Administrativo | BD5: Fecha Acto Administrativo | BE5: Nombre de quién proyectó | BF5: Otorgada | BG5: Negada | BH5: Desistida | BI5: Fecha Notificación | BJ5: Fecha ejecutoria | BK5: Fecha de vencimiento | BL5: No. Radicado | BM5: Fecha Radicado | BN5: No. Acto Administrativo | BO5: Fecha Acto Administrativo | BP5: Nombre de quién proyectó | BQ5: Modifica/ Aclara / Confirma/ Adiciona /Niega | BR5: Fecha Notificación | BS5: No. Radicado | BT5: Fecha Radicado | BU5: Auto Requer. | BV5: Fecha Requer. | BW5: Nombre de quién proyecto | BX5: No. Acto Administrativo | BY5: Fecha Act Administrativo | BZ5: Nombre de quien proyectó | CA5: Cumple o NO | CB5: No. Radicado del usuario | CC5: Fecha Radicado | CD5: Fecha de visita técnica | CE5: Fecha Informe técnico | CF5: Nombre del técnico | CG5: No. Acto Administrativo | CH5: Fecha Acto Administrativo | CI5: Nombre de quién proyectó | CJ5: Cumple o NO | CK5: No. Radicado | CL5: Fecha Radicado | CM5: Fecha de visita técnica | CN5: Fecha Informe técnico | CO5: Nombre del técnico | CP5: No. Acto Administrativo | CQ5: Fecha de notificación | CR5: Fecha de ejecutoria | CS5: Observación | CT5: No. Radicado | CU5: Fecha Radicado | CV5: Fecha de visita técnica | CW5: Fecha Informe técnico | CX5: Nombre del técnico | CY5: No. Acto Administrativo | CZ5: Fecha de notificación | DA5: Fecha de ejecutoria | DB5: Observación | DC5: No. Radicado | DD5: Fecha Radicado | DE5: Fecha de visita técnica | DF5: Fecha Informe técnico | DG5: Nombre del técnico | DH5: No. Acto Administrativo | DI5: Fecha de notificación | DJ5: Fecha de ejecutoria | DK5: Observación | DL5: No. Radicado | DM5: Fecha Radicado | DN5: Fecha de visita técnica | DO5: Fecha Informe técnico | DP5: Nombre del técnico | DQ5: No. Acto Administrativo | DR5: Fecha de notificación | DS5: Fecha de ejecutoria | DT5: Observación | DU5: No. Radicado | DV5: Fecha Radicado | DW5: Fecha de visita técnica | DX5: Fecha Informe técnico | DY5: Nombre del técnico | DZ5: No. Acto Administrativo | EA5: Fecha de notificación | EB5: Fecha de ejecutoria | EC5: Observación | ED5: No. Radicado | EE5: Fecha Radicado | EF5: Fecha de visita técnica | EG5: Fecha Informe técnico | EH5: Nombre del técnico | EI5: No. Acto Administrativo | EJ5: Fecha de notificación | EK5: Fecha de ejecutoria | EL5: Observación | EM5: Fecha Radicado | EN5: Fecha de visita técnica | EO5: Fecha Informe técnico | EP5: Nombre del técnico | EQ5: RECLAMACION TUA | ER5: Fecha de notificación | ES5: Fecha de ejecutoria | ET5: Observación | EU5: Fecha ultimo seguimiento | EV5: Fecha de concepto | EW5: Cadual Aforado (Captado o vertido) | EX5: Volumen metros cubicos aprovechado ( AF) aprovechamiento forestal | EY5: Entrega informes Anuales (L.A) Solo aplica para licencias ambientales | FB5: Acto administrativo
AV6: Solicitamos se agregue la formula | CP6: Modificacion | CY6: Traspaso | DH6: Prorroga | DQ6: Cancelación | DZ6: Perdida de fuerza ejecutoria | EI6: Suspensión | EY6: Llantas Usadas | EZ6: ICA | FA6: Autoliquidación de la vigencia | FB6: N° | FC6: Fecha
EY7: SI /NO
C8: C.A. 034/09 | D8: NA | E8: ASOCIACION DE SUSCRIPTORES DEL ACUEDUCTO LOS SAUCES DEL MUNICIPIODE RAMIRIQUI | F8: 900264769-2 | G8: NA | H8: NA | I8: acueductolossauces@gmail.com | J8: NA | K8: RESGUARDO ALTO | L8: SUPERFICIAL | M8: NACIMIENTO | N8: LOS SAUCES | O8: NA | P8: NA | Q8: NA | R8: NA | S8: NA | T8: NA | U8: NA | V8: NA | W8: NA | X8: NA | Y8: NA | Z8: NA | AA8: NA | AB8: NA | AC8: NA | AD8: NA | AE8: NA | AF8: NA | AG8: NA | AH8: NA | AI8: NA | AJ8: NA | AK8: NA | AL8: NA | AM8: NA | AN8: NA | AO8: NA | AP8: NA | AQ8: NA | AR8: NA | AS8: NA | AT8: NA | AU8: NA | AV8: NA | AW8: NA | AX8: NA | AY8: NA | AZ8: NA | BA8: NA | BB8: NA | BC8: 757 | BD8: 40248 | BE8: NA | BF8: NA | BG8: NA | BH8: NA | BJ8: 1/19/2011 | BK8: 01/19/2021 | BL8: NA | BM8: NA | BN8: NA | BO8: NA | BP8: NA | BQ8: NA | BR8: NA | BS8: NA | BT8: NA | BU8: NA | BV8: NA | BW8: NA | BX8: NA | BY8: NA | BZ8: NA | CA8: NA | CB8: NA | CC8: NA | CD8: NA | CE8: NA | CF8: NA | CG8: NA | CH8: NA | CI8: NA | CJ8: NA | CK8: NA | CL8: NA | CM8: NA | CN8: NA | CO8: NA | CP8: NA | CQ8: NA | CR8: NA | CS8: NA | CT8: NA | CU8: NA | CV8: NA | CW8: NA | CX8: NA | CY8: NA | CZ8: NA | DA8: NA | DB8: NA | DC8: NA | DD8: NA | DE8: NA | DF8: NA | DG8: NA | DH8: NA | DI8: NA | DJ8: NA | DK8: NA | DL8: NA | DM8: NA | DN8: NA | DO8: NA | DP8: NA | DQ8: NA | DR8: NA | DS8: NA | DT8: NA | DU8: NA | DV8: NA | DW8: NA | DX8: NA | DY8: NA | DZ8: NA | EA8: NA | EB8: NA | EC8: NA | ED8: NA | EE8: NA | EF8: NA | EG8: NA | EH8: NA | EI8: NA | EJ8: NA | EK8: NA | EL8: NA | EM8: NA | EN8: NA | EO8: NA | EP8: NA | EQ8: NA | ER8: NA | ES8: NA | ET8: NA | EU8: NA | EV8: NA | EW8: NA | EX8: NA | EY8: NA | EZ8: NA | FA8: NA | FB8: NA | FC8: NA | FD8: Tramite Prorroga: En tramite requerido mediante Auto No. 266 de fecha 07 de marzo de 2022, 2022EE3420 y 2022EE5478. Tramite modificación : N/A Seguimiento (Revisión): N/A
A9: 2009ER1681 | B9: 39917 | C9: CA 059-2009 | E9: LUIS ANTONIO MARTIN MACIAS | F9: 4273626 | G9: VEREDA APOSENTOS | H9: 3115807124 | J9: SAN LUIS DE GACENO | K9: APOSENTOS | L9: SUPERCIAL | N9: SIN NOMBRE | BC9: 666 | BD9: 40053 | BE9: LESMES | BF9: X | BI9: 40080 | BJ9: 40087 | BK9: 43739 | DZ9: 938 (09-AGO-21) | EA9: SIN NOTIFICAR | FD9: SIN NOTIFICAR PERDIDA | FE9: 45502
C10: CA 082-2009 | E10: UNIDAD ADMINISTRADORA EPS DE SAN LUIS DE GACENO | F10: 891802151 | J10: SAN LUIS DE GACENO | L10: SUPERCIAL | N10: VARSOVIANA; AGUA NUEVA LA GRANJA | BC10: 82 | BD10: 40214 | BF10: X | BI10: 40381 | DC10: 2019ER9417 | DD10: 43798 | DE10: 44119 | DF10: 44125 | DH10: 1393 (05 OCT 21) | DI10: 44477 | EU10: 44698 | EV10: 44747 | FB10: 1240 | FC10: 45062 | FD10: Requiere PUEAA, TUA, MEMORIAS, PAGO SEGUIMIENTO - ULTIMA RESPUESTA 2023EE10318 | FE10: 45502
A11: 2009ER3449 | B11: 40010 | C11: CA 093-2009 | D11: PENDIENTE | E11: ASOCIAICON DE SUSCRIPTORES ACUEDUCTO QUEBRADITAS | G11: VEREDA CENTRO RURAL | H11: 3142590674 | I11: NA | J11: NUEVO COLON | K11: VEREDA FIOTA | L11: SUPERFICIAL | M11: QUEBRADA | N11: QUEBRADITAS | O11: NA | P11: NA | Q11: NA | R11: NA | S11: NA | T11: NA | U11: NA | V11: NA | W11: NA | X11: NA | Y11: NA | Z11: NA | AA11: NA | AB11: NA | AC11: NA | AD11: NA | AE11: NA | AF11: NA | AG11: NA | AH11: NA | AI11: NA | AJ11: NA | AK11: NA | AL11: NA | AM11: NA | AN11: NA | AO11: NA | AP11: NA | AQ11: NA | AR11: NA | AS11: NA | AT11: NA | AU11: NA | AV11: NA | AW11: NA | AX11: NA | AY11: NA | AZ11: NA | BA11: NA | BB11: NA | BC11: 266 | BD11: 40291 | BE11: PLINIO R | BF11: X | BG11: NA | BH11: NA | BI11: 40312 | BJ11: 40293 | BK11: 43946 | BL11: NA | BM11: NA | BN11: NA | BO11: NA | BP11: NA | BQ11: NA | BR11: NA | BS11: NA | BT11: NA | BU11: NA | BV11: NA | BW11: NA | BX11: NA | BY11: NA | BZ11: NA | CA11: NA | CB11: NA | CC11: NA | CD11: NA | CE11: NA | CF11: NA | CG11: NA | CH11: NA | CI11: NA | CJ11: NA | CK11: NA | CL11: NA | CM11: NA | CN11: NA | CO11: NA | CP11: NA | CQ11: NA | CR11: NA | CS11: NA | CT11: NA | CU11: NA | CV11: NA | CW11: NA | CX11: NA | CY11: NA | CZ11: NA | DA11: NA | DB11: NA | DC11: NA | DD11: NA | DE11: NA | DF11: NA | DG11: NA | DH11: NA | DI11: NA | DJ11: NA | DK11: NA | DL11: NA | DM11: NA | DN11: NA | DO11: NA | DP11: NA | DQ11: NA | DR11: NA | DS11: NA | DT11: NA | DU11: NA | DV11: NA | DW11: NA | DX11: NA | DY11: NA | DZ11: 900 | EA11: NA | EB11: NA | EC11: PENDIENTE NOTIFICADOR POR AVISO 2024EE11398 | ED11: NA | EE11: NA | EF11: NA | EG11: NA | EH11: NA | EI11: NA | EJ11: NA | EK11: NA | EL11: NA | EM11: NA | EN11: NA | EO11: NA | EP11: NA | EQ11: NA | ER11: NA | ES11: NA | ET11: NA | EU11: NA | EV11: NA | EW11: NA | EX11: NA | EY11: NA | EZ11: NA | FA11: NA | FB11: NA | FC11: NA | FD11: PENDIENTE CONSTANCIA DEL NOTIFICADOR | FE11: 19/11/2024 MILENA GALINDO
C12: CA 114-2009 | FD12: RESOLUCION N°54519 DE JULIO 2024 ANULA FACTURA DTUA N°127 | FE12: 27/08/2024 MILENA

Sheet CA 2010
C1: CONTROL TRAMITE DE CONCESION DE AGUAS 2024 | FD1: Código | FE1: RE-AA-20 | FF1: FECHA ACTUALIZACION
FD2: Versión | FE2: 7
FD3: Fecha | FE3: 44411
A4: DATOS DE LA SOLICITUD | O4: APERTURÓ | P4: REQUERIMIENTO | W4: PAGO SERVICIOS DE EVALUACION | AB4: No. Oficio/ Auto de Requerimiento | AE4: CONTROL- DIAS TRANSCURRIDOS HASTA FECHA DE VISITA | AF4: CONCEPTO TECNICO | AV4: CONTROL- DIAS TRANSCURRIDOS DE LA RADICACION AL CONCEPTO CON Vo.Bo. | AW4: FECHA DE ASIGNACION CONCEPTO AL AREA JURIDICO | AX4: REQUERIMIENTO | BC4: ACTO ADMINISTRATIVO | BL4: RECURSO DE REPOSICION | BS4: MEMORIAS DE CALCULO | CB4: RECIBO A SATISFACCION DE OBRAS | CK4: ACTO ADMINISTRATIVO | EU4: SEGUIMIENTO | FD4: Observaciones de lo evidenciado en la visita técnica | FE4: Ultima Actualización
A5: No. Radicado | B5: Fecha Radicado | C5: No. Expediente | D5: RADICADO EN VITAL | E5: Solicitante/Interesado | F5: Cédula de ciudadanía - NIT | G5: Dirección de correspondencia | H5: Telefono | I5: Correo Electrónico | J5: Municipio permiso | K5: Lugar de la captación (Vereda) | L5: Tipo de Fuente | M5: Fuente | N5: Nombre de la Fuente | P5: No. Oficio/ Auto de Requerimiento | Q5: Fecha Oficio/ Auto de Requerimiento | R5: Nombre de quién proyectó | S5: Dias del radicado al requerimiento | T5: Descripcion del requerimiento | U5: Radicado Oficio de entrada | V5: Fecha oficio de entrada | W5: No. de la Factura | X5: Valor tabla única (Factura) | Y5: Valor Facturado | Z5: Valor Cancelado | AA5: Fecha del pago servicio de evaluación | AB5: No. Oficio/ Auto de Requerimiento | AC5: Fecha Oficio/ Auto de Requerimiento | AD5: Nombre de quién proyectó | AF5: Fecha Visita técnica | AG5: Nombre del técnico | AH5: FECHA LIMITE ENTREGA DE CONCEPTO | AI5: DIAS CALENDARIO TRANSCURRIDOS SEGÚN FECHA LIMITE DE ENTRE DE CONCEPTO Y FECHA DE VISITA TECNICA | AJ5: ALERTAS | AK5: Fecha entrega a Revisión Informe - Lider | AL5: Entrega de Informe al técnico para corrección | AM5: Entrega de concepto corregido | AN5: Fecha Concepto técnico | AO5: Predio a beneficiar | AP5: Georreferenciación del punto de captación | AQ5: Vereda de la localización del punto de captación | AR5: Usos | AS5: Caudal Otordo, dicriminado por cada uso | AT5: Total del caudal otorgado | AU5: Número de Suscriptores | AX5: No. Auto de Requerimiento | AY5: Fecha Auto de Requerimiento | AZ5: Nombre de quién proyectó | BA5: Radicado Oficio de entrada | BB5: Fecha oficio de entrada | BC5: No. Acto Administrativo | BD5: Fecha Acto Administrativo | BE5: Nombre de quién proyectó | BF5: Otorgada | BG5: Negada | BH5: Desistida | BI5: Fecha Notificación | BJ5: Fecha ejecutoria | BK5: Fecha de vencimiento | BL5: No. Radicado | BM5: Fecha Radicado | BN5: No. Acto Administrativo | BO5: Fecha Acto Administrativo | BP5: Nombre de quién proyectó | BQ5: Modifica/ Aclara / Confirma/ Adiciona /Niega | BR5: Fecha Notificación | BS5: No. Radicado | BT5: Fecha Radicado | BU5: Auto Requer. | BV5: Fecha Requer. | BW5: Nombre de quién proyecto | BX5: No. Acto Administrativo | BY5: Fecha Act Administrativo | BZ5: Nombre de quien proyectó | CA5: Cumple o NO | CB5: No. Radicado del usuario | CC5: Fecha Radicado | CD5: Fecha de visita técnica | CE5: Fecha Informe técnico | CF5: Nombre del técnico | CG5: No. Acto Administrativo | CH5: Fecha Acto Administrativo | CI5: Nombre de quién proyectó | CJ5: Cumple o NO | CK5: No. Radicado | CL5: Fecha Radicado | CM5: Fecha de visita técnica | CN5: Fecha Informe técnico | CO5: Nombre del técnico | CP5: No. Acto Administrativo | CQ5: Fecha de notificación | CR5: Fecha de ejecutoria | CS5: Observación | CT5: No. Radicado | CU5: Fecha Radicado | CV5: Fecha de visita técnica | CW5: Fecha Informe técnico | CX5: Nombre del técnico | CY5: No. Acto Administrativo | CZ5: Fecha de notificación | DA5: Fecha de ejecutoria | DB5: Observación | DC5: No. Radicado | DD5: Fecha Radicado | DE5: Fecha de visita técnica | DF5: Fecha Informe técnico | DG5: Nombre del técnico | DH5: No. Acto Administrativo | DI5: Fecha de notificación | DJ5: Fecha de ejecutoria | DK5: Observación | DL5: No. Radicado | DM5: Fecha Radicado | DN5: Fecha de visita técnica | DO5: Fecha Informe técnico | DP5: Nombre del técnico | DQ5: No. Acto Administrativo | DR5: Fecha de notificación | DS5: Fecha de ejecutoria | DT5: Observación | DU5: No. Radicado | DV5: Fecha Radicado | DW5: Fecha de visita técnica | DX5: Fecha Informe técnico | DY5: Nombre del técnico | DZ5: No. Acto Administrativo | EA5: Fecha de notificación | EB5: Fecha de ejecutoria | EC5: Observación | ED5: No. Radicado | EE5: Fecha Radicado | EF5: Fecha de visita técnica | EG5: Fecha Informe técnico | EH5: Nombre del técnico | EI5: No. Acto Administrativo | EJ5: Fecha de notificación | EK5: Fecha de ejecutoria | EL5: Observación | EM5: Fecha Radicado | EN5: Fecha de visita técnica | EO5: Fecha Informe técnico | EP5: Nombre del técnico | EQ5: RECLAMACION TUA | ER5: Fecha de notificación | ES5: Fecha de ejecutoria | ET5: Observación | EU5: Fecha ultimo seguimiento | EV5: Fecha de concepto | EW5: Cadual Aforado (Captado o vertido) | EX5: Volumen metros cubicos aprovechado ( AF) aprovechamiento forestal | EY5: Entrega informes Anuales (L.A) Solo aplica para licencias ambientales | FB5: Acto administrativo
AV6: Solicitamos se agregue la formula | CP6: Modificacion | CY6: Traspaso | DH6: Prorroga | DQ6: Cancelación | DZ6: Perdida de fuerza ejecutoria | EI6: Suspensión | EY6: Llantas Usadas | EZ6: ICA | FA6: Autoliquidación de la vigencia | FB6: N° | FC6: Fecha
EY7: SI /NO
A8: 2010ER1508 | B8: 40256 | C8: CA 073-10 | E8: ASOCIACION DE SUSCRIPTORES DEL ACUEDUCTO DE SANTA RITA | F8: 900121140-7 | G8: VEREDA NAGUATA | H8: 3043982465 | I8: acueductossantarita49@gmail.com | J8: RAMIRIQUI | K8: VEREDA NAGUATA | L8: SUPERFICIAL | M8: NACIMIENTO | N8: SANTA RITA | BC8: 853 | BD8: 40515 | BE8: CARLOS SIERRA | BF8: X | BG8: NA | BH8: NA | BI8: 40539 | BJ8: 40547 | BK8: 44200 | DW8: 42508 | DX8: 42541 | DY8: DIEGO F | DZ8: 995 | EA8: 44981 | FD8: 2025IE1441 - Se remite a seguimiento para declarar la perdida | FE8: MILENA GALINDO | FF8: 45850
A9: 2010ER1622 | B9: 40263 | C9: CA 086-10 | D9: NA | E9: OMAR HERNANDO PEÑA RUBIANO Y OTROS | F9: 733791 | G9: VEREDA SICHA ABAJO | H9: 3212099232 | I9: acueductoveredalpuravida@gmail.com | J9: CHINAVITA | K9: ZANJA ARRIBA | L9: SUPERFICIAL | M9: QUEBRADA | N9: LA ESMERALDA | O9: NA | P9: 2011EE3707 2011EE5227 | Q9: 1/04/2011 23/05/2011 | R9: P PERILLA | S9: NA | T9: NA | U9: NA | V9: NA | W9: 1510 | X9: 112194 | Y9: 112194 | Z9: 112194 | AA9: SIN | AB9: NA | AC9: NA | AD9: NA | AE9: NA | AF9: NA | AG9: NA | AH9: NA | AI9: NA | AJ9: NA | AK9: NA | AL9: NA | AM9: NA | AN9: NA | AO9: NA | AP9: NA | AQ9: NA | AR9: NA | AS9: NA | AT9: NA | AU9: NA | AV9: NA | AW9: NA | AX9: 1114 | AY9: 2311/2020 | AZ9: LAURA M | BA9: NA | BB9: NA | BC9: 522 | BD9: 41903 | BE9: J SUAREZ | BF9: X | BG9: NA | BH9: NA | BI9: 41897 | BJ9: 41912 | BK9: 45565 | BL9: NA | BM9: NA | BN9: NA | BO9: NA | BP9: NA | BQ9: NA | BR9: NA | BS9: NA | BT9: NA | BU9: NA | BV9: NA | BW9: NA | BX9: NA | BY9: NA | BZ9: NA | CA9: NA | CB9: NA | CC9: NA | CD9: NA | CE9: NA | CF9: NA | CG9: NA | CH9: NA | CI9: NA | CJ9: NA | CK9: NA | CL9: NA | CM9: NA | CN9: NA | CO9: NA | CP9: NA | CQ9: NA | CR9: NA | CS9: NA | CT9: NA | CU9: NA | CV9: NA | CW9: NA | CX9: NA | CY9: NA | CZ9: NA | DA9: NA | DB9: NA | DC9: 2024ER8729 | DD9: 45538 | DE9: 45697 | DF9: NA | DG9: NA | DH9: NA | DI9: NA | DJ9: NA | DK9: NA | DL9: NA | DM9: NA | DN9: NA | DO9: NA | DP9: NA | DQ9: NA | DR9: NA | DS9: NA | DT9: NA | DU9: NA | DV9: NA | DW9: NA | DX9: NA | DY9: NA | DZ9: NA | EA9: NA | EB9: NA | EC9: NA | ED9: NA | EE9: NA | EF9: NA | EG9: NA | EH9: NA | EI9: NA | EJ9: NA | EK9: NA | EL9: NA | EM9: NA | EN9: NA | EO9: NA | EP9: NA | EQ9: NA | ER9: NA | ES9: NA | ET9: NA | EU9: 21/09/2016 16/10/2020 20/08/2024 | EV9: 25/10/2016 05/11/2020 25/09/24 | EW9: 0,98 0,85 | EX9: NA | EY9: NA | EZ9: NA | FA9: NA | FB9: NA | FC9: NA | FD9: PENDIENTE CONCEPTO TECNICO EN EL MARCO DE PRORROGA | FE9: MILENA GALINDO | FF9: 45689
A10: 2010ER1719 | B10: 40273 | C10: CA 091/10 | E10: WILSON JACINTO BUITRAGO MELOI | F10: 74329330 | G10: VEREDA NUEVE PILAS | H10: 3124362065 | I10: wilsonbuitrago312@gmail.com | J10: UMBITA | K10: NUEVE PILAS | L10: SUPERFICIAL | M10: QUEBRADA | N10: EL BERJENAL | P10: 2020EE683 2021EE6319 2022EE4938 | Q10: 17/02/2020 09/07/2021 09/05/2022 | R10: IVONNE G DIEGO R ADRIANA B | U10: 2020ER675 2021ER4754 | V10: 3/02/2020 16/06/2021 | W10: 1889 2707 | X10: 114001 120408 | Y10: 114001 120408 | Z10: 114001 120408 | AA10: 14/11/2023 SIN | AF10: 40287 | AG10: LUIS ORTIZ | AH10: NA | AI10: NA | AJ10: NA | AK10: NA | AL10: NA | AM10: NA | AN10: 31/06/2011 | AO10: EL TESORO | AP10: 010 69 328 010 63 418 ALTURA 3154 | AQ10: NUEVE PILAS | AR10: DOMESTICO PECUARIO | AS10: 0,014 0,007 | AT10: 0.17 | AU10: NA | AV10: NA | AW10: NA | AX10: 695 | AY10: 45497 | AZ10: LEONARDO G | BA10: NA | BB10: NA | BC10: 537 | BD10: 40799 | BE10: CARLOS SIERRA | BF10: X | BG10: NA | BH10: NA | BI10: 40837 | BJ10: 40847 | BK10: 44500 | BL10: NA | BM10: NA | BN10: NA | BO10: NA | BP10: NA | BQ10: NA | BR10: NA | BS10: NA | BT10: NA | BU10: NA | BV10: NA | BW10: NA | BX10: NA | BY10: NA | BZ10: NA | CA10: NA | CB10: NA | CC10: NA | CD10: NA | CE10: NA | CF10: NA | CG10: NA | CH10: NA | CI10: NA | CJ10: NA | CK10: NA | CL10: NA | CM10: NA | CN10: NA | CO10: NA | CP10: NA | CQ10: NA | CR10: NA | CS10: NA | CT10: NA | CU10: NA | CV10: NA | CW10: NA | CX10: NA | CY10: NA | CZ10: NA | DA10: NA | DB10: NA | DC10: 2020ER675 | DD10: 43864 | DE10: NA | DF10: NA | DG10: NA | DH10: 909 | DI10: NA | DJ10: NA | DK10: OFICIO 2020EE683 SE SOLICITA ALLEGAR DOCUMENTACION FALTANTE PARA EL TRAMITE | DL10: NA | DM10: NA | DN10: NA | DO10: NA | DP10: NA | DQ10: NA | DR10: NA | DS10: NA | DT10: NA | DU10: NA | DV10: NA | DW10: NA | DX10: NA | DY10: NA | DZ10: NA | EA10: NA | EB10: NA | EC10: NA | ED10: NA | EE10: NA | EF10: NA | EG10: NA | EH10: NA | EI10: NA | EJ10: NA | EK10: NA | EL10: NA | EM10: NA | EN10: NA | EO10: NA | EP10: NA | EQ10: NA | ER10: NA | ES10: NA | ET10: NA | EU10: 45240 | EV10: 45280 | EW10: 0.141 | EX10: NA | EY10: NA | EZ10: NA | FA10: NA | FB10: NA | FC10: NA | FD10: POR MEDIO DE AUTO 096 DEL 12 MAR 2025 SE REALIZA UN REQUERIMIENTO | FE10: MILENA GALINDO | FF10: 45733
A11: 2010ER2135 | B11: 40290 | C11: CA 101-10 | E11: MARIA AURORA DE JESUS ALFONSO VARGAS | F11: 41749700 | G11: REGUARDO MACIEGAL | H11: 3115775169 | I11: auroravargas1954@hotmail.com | J11: GARAGOA | K11: MACIEGAL | L11: SUPERFICIAL | M11: NACIMIENTO | N11: SIN NOMBRE | BC11: 640 | BD11: 45533 | BE11: MILENA GALINDO | BF11: NA | BG11: NA | BH11: X | FD11: PENDIENTE POR NOTIFICAR | FE11: MILENA GALINDO | FF11: 45537
A12: 2010ER3538 | B12: 40375 | C12: CA 129-10 | D12: PENDIENTE | E12: AVICOLA LOS CAMBULOS | F12: 860058831-4 | G12: CARRERA 70 N 108-59 BOGOTA | H12: 6017470401 | I12: inco@avicambulos.com.co | J12: TENZA | K12: CORA GRANDE | L12: SUPERFICIAL | M12: QUEBRADA | N12: LA QUIÑA | O12: NA | P12: NA | Q12: NA | R12: NA | S12: NA | T12: NA | U12: NA | V12: NA | W12: NA | X12: NA | Y12: NA | Z12: NA | AA12: NA | AB12: NA | AC12: 40385 | AD12: PLINIO RONALDO DUEÑAS | AE12: NA | AF12: 40934 | AG12: ALEXANDER A | AN12: 40948 | AO12: EL LAGO | AR12: INDUSTRIAL | AS12: 1.8 | AT12: 1.8 | AU12: 1 | BC12: 222 | BD12: 40994 | BE12: JOSE A. | BF12: X | BG12: NA | BH12: NA | BI12: 41039 | BJ12: 41057 | BK12: 44709 | BS12: 2023ER11736 | BT12: 45259 | BX12: 43 | BY12: 45330 | BZ12: MILENA GALINDO | CA12: SI | CK12: 2024ER10980 | CL12: 45582 | CS12: ACTUALMENTE REQURIDO PAGO POR SERVICIOS DE EVALUACION | CT12: NA | CU12: NA | CV12: NA | CW12: NA | CX12: NA | CY12: NA | CZ12: NA | DA12: NA | DB12: NA | DC12: NA | DD12: NA | DE12: NA | DF12: NA | DG12: NA | DH12: 124 | DI12: 44993 | DJ12: NA | DK12: NA | DL12: NA | DM12: NA | DN12: NA | DO12: NA | DP12: NA | DQ12: NA | DR12: NA | DS12: NA | DT12: NA | DU12: NA | DV12: NA | DW12: NA | DX12: NA | DY12: NA | DZ12: NA | EA12: NA | EB12: NA | EC12: NA | ED12: NA | EE12: NA | EF12: NA | EG12: NA | EH12: NA | EI12: NA | EJ12: NA | EK12: NA | EL12: NA | EM12: NA | EN12: NA | EO12: NA | EP12: NA | EQ12: NA | ER12: NA | ES12: NA | ET12: NA | EU12: NA | EV12: NA | EW12: NA | EX12: NA | EY12: NA | EZ12: NA | FA12: NA | FB12: NA | FC12: NA | FD12: Requerido para ajustar las obras de captación 1430 de 2026 | FE12: MILENA GALINDO | FF12: 46194
A13: 2010er3721 | B13: 40387 | C13: ca 135-10 | E13: EMELINA HUERTAS DE MORALES | F13: 24211349 | G13: VEREDA TAMBOR GRANDE | H13: 3134680137/3004941915 | I13: NA | J13: UMBITA | K13: TAMBOR GRNANDE | L13: SUPERFICIAL | M13: NACIEMIENTO | N13: LOS ENCENILLOS | P13: 2011EE5831 | Q13: 40709 | R13: PPERILLA | S13: NA | T13: NA | U13: 2021ER5220 2021ER8263 | V13: 29/06/2021 29/09/2021 | W13: 2055 2998 | X13: 114001 120408 | Y13: 114001 120408 | Z13: 114001 120408 | AA13: 20/10/2021 22/10/2022 | AF13: 44511 | AG13: LICETH HOLGUIN | AH13: NA | AI13: NA | AJ13: NA | AK13: NA | AL13: NSA | AM13: NA | AN13: 44559 | AO13: LOS ENCENILLOS | AX13: 1902 1597 2303 | AY13: 21/09/2022 14/06/2023 18/12/2025 | AZ13: MARTHA SOSCAR R PAULA B | BC13: 260 | BD13: 40704 | BE13: PPERILLA | BF13: X | BG13: NA | BH13: NA | BI13: 40709 | BJ13: 40724 | BK13: 44377 | BU13: 287 | BV13: 46106 | BW13: KAREN BARRETO | DC13: ER5220 Y ER8263 | DD13: 29/06/2021 29/09/2021 | DE13: 44511 | DF13: 44559 | DG13: LICETH HOLGUIN | DH13: 1971 | DI13: 44560 | EN13: NA | EO13: NA | EP13: NA | EQ13: NA | ER13: NA | ES13: NA | ET13: NA | EU13: NA | EV13: NA | EW13: NA | EX13: NA | EY13: NA | EZ13: NA | FA13: NA | FB13: NA | FC13: NA | FD13: MEDIANTE OFICIO N 2026EE3244 DE FECHA 26/03/2026 SE NOTIFICO RESOLUCION N 0287- 25/03/2026 | FE13: KAREN BARETO | FF13: 46108
A14: 2010ER4748 | B14: 40445 | C14: CA 149-10 | E14: LUZ MIRYAM BOHORQUEZ CUESTA | F14: 23423552 | G14: CRA 3 No. 3-48 | H14: 3202359390 | J14: SAN LUIS DE GACENO | K14: CENTRO | L14: SUPERFICIAL | M14: QUEBRADA | N14: EL TORO | AC14: 40448 | AD14: PLINIO RONALDO | AF14: 40620 | AN14: 40624 | AO14: EL VAUPECITO | AR14: PISCICOLA | AX14: N/A | AY14: N/A | AZ14: N/A | BA14: N/A | BB14: N/A | BC14: 123 | BD14: 40634 | BE14: PERILLA | BF14: X | BI14: 40644 | BJ14: 40652 | DC14: 2021ER1930 | DD14: 44271 | DE14: 44523 | DF14: 44559 | DH14: 521 (08-JUN-22) | DI14: 44721 | FD14: Requerida mediante 2023EE17236 | FF14: 45502
A15: 2010ER4749 | B15: 40445 | C15: CA 150-10 | E15: ELVER MAURICIO PERILLA MORA | F15: 74352377 | G15: CALLE 3 No. 6-82 | H15: 3187533330 | I15: shijab07@hotmail.com | J15: SAN LUIS DE GACENO | K15: CENTRO | L15: SUPERFICIAL | M15: QUEBRADA | N15: EL TORO | AC15: 40448 | AD15: PLINIO RONALDO | AF15: 40620 | AN15: 40624 | AO15: SAN ANTONIO | AR15: PISCICOLA | AX15: N/A | AY15: N/A | AZ15: N/A | BA15: N/A | BB15: N/A | BC15: 121 | BD15: 40634 | BE15: PERILLA | BF15: X | BI15: 40644 | BJ15: 40652 | DC15: 2021ER2298 | DD15: 44282 | DE15: 44558 | DF15: 44560 | DH15: 313 (02-MAT-22) | DI15: 44685 | FD15: Mediante Auto 1148 de fecha 06 julio de 2022 se concede prorroga de 2 meses para dar cumplimiento a rsolucion 313 - Que mediante Auto 2275 de fecha 16 de agosto de 2023 se realiza requerimiento para ajustar PUEAA | FF15: 45502
A16: 2010ER4707 | B16: 40444 | C16: CA 151-10 | E16: MARIA CONSUELO PEÑA ROJAS | F16: 23422906 | G16: VEREDA EL CAIRO | H16: 3125495147 | J16: SAN LUIS DE GACENO | L16: SUPERFICIAL | M16: QUEBRADA | N16: AGUA FRIA | AC16: 40448 | AD16: PLINIO RONALDO | AF16: 40620 | AN16: 40621 | AO16: LA ESPERANZA | AR16: PECUARIO | AX16: N/A | AY16: N/A | AZ16: N/A | BA16: N/A | BB16: N/A | BC16: 342 | BD16: 40710 | BE16: PERILLA | BF16: X | BI16: 40723 | BJ16: 40732 | BK16: 44385 | EU16: 43570 | EV16: 43585 | FB16: 247 | FC16: 44281 | FD16: Se requiere pv, pago tua, y adecuaciones - VENCIDA | FF16: 45502
A17: 2010ER4786 | B17: 40449 | C17: CA 154/10 | E17: ISIDORO BERNAL | F17: 19076794 | G17: INVITA | J17: NUEVO COLON | L17: SUPERFICIAL | M17: QUEBRADA | N17: SORCA | BC17: 269 | BD17: 40704 | BE17: CARLOS SIERRA | BF17: X | BI17: 40729 | BJ17: 40735 | BK17: 44753 | FD17: VENCIDA POR TIEMPO MEDIANTE LA RESOLUCION No. 0685 de 2025 | FF17: 45902
C18: CA 160/10 | D18: PENDIENTE | E18: MARTHA UVALDINA CASTRO RODRIGUEZ | F18: 23824081 | H18: 3133570180 | I18: uvita.castro81@gmail.com | J18: NUEVO COLON | L18: SUPERFICIAL | M18: NACIMIENTO | N18: LA FUENTE | BC18: 575 680 | BD18: 23/09/2011 08/07/2022 | BF18: X | CY18: 084 (01/03/2025) | FD18: SOLCITUD DE INFORMACION 2025EE11632 | FF18: 45939
C19: CA 164/10 | E19: EFRAIN MARTINEZ FONSECA | F19: 74329100 | J19: UMBITA | BC19: 581 | BD19: 40809 | BF19: X | BI19: 40821 | BJ19: 40829 | BX19: 936 | BY19: 46245 | BZ19: MILENA GALINDO | CA19: SI | DH19: 472 | DI19: 44714 | DJ19: 44734
A20: 2010ER5893 | B20: 40518 | C20: CA 179-10 | E20: PAULO ENRIQUE APONTE SORA | F20: 72326546 | G20: EL HERVIEROS Y FRAGUA | H20: 3202779153 | I20: pabliaponte302019@gmail.com | J20: RAMIRIQUI | K20: VEREDA HERVIDEROS | L20: NA | M20: NA | N20: EL ENCANTO | O20: NA | P20: NA | Q20: NA | R20: NA | S20: NA | T20: NA | U20: NA | V20: NA | W20: NA | X20: NA | Y20: NA | Z20: NA | AA20: NA | AB20: NA | AC20: NA | AD20: NA | AE20: NA | AF20: NA | AG20: NA | AH20: NA | AI20: NA | AJ20: NA | AK20: NA | AL20: NA | AM20: NA | AN20: NA | AO20: NA | AP20: NA | AQ20: NA | AR20: NA | AS20: NA | AT20: NA | AU20: NA | AV20: NA | AW20: NA | AX20: NA | AY20: NA | AZ20: NA | BA20: NA | BB20: NA | BC20: 265 | BD20: 40704 | BE20: CARLOS SIERRA | BF20: X | BG20: NA | BH20: NA | BI20: 40718 | BJ20: 40730 | BK20: 44383 | BL20: NA | BM20: NA | BN20: NA | BO20: NA | BP20: NA | BQ20: NA | BR20: NA | BS20: NA | BT20: NA | BU20: NA | BV20: NA | BW20: NA | BX20: 491 | BY20: 45475 | BZ20: PAULA MORENO | CA20: SI | CB20: NA | CC20: NA | CD20: NA | CE20: NA | CF20: NA | CG20: 201 | CH20: 40984 | CI20: JOSE AMAYA | CJ20: SI | CK20: NA | CL20: NA | CM20: NA | CN20: NA | CO20: NA | CP20: NA | CQ20: NA | CR20: NA | CS20: NA | CT20: NA | CU20: NA | CV20: NA | CW20: NA | CX20: NA | CY20: NA | CZ20: NA | DA20: NA | DB20: NA | DC20: NA | DD20: NA | DE20: NA | DF20: NA | DG20: NA | DH20: 90 | DI20: 44981 | DJ20: NA | DK20: 07/18/2033 | DL20: NA | DM20: NA | DN20: NA | DO20: NA | DP20: NA | DQ20: NA | DR20: NA | DS20: NA | DT20: NA | DU20: NA | DV20: NA | DW20: NA | DX20: NA | DY20: NA | DZ20: NA | EA20: NA | EB20: NA | EC20: NA | ED20: NA | EE20: NA | EF20: NA | EG20: NA | EH20: NA | EI20: NA | EJ20: NA | EK20: NA | EL20: NA | EM20: NA | EN20: NA | EO20: NA | EP20: NA | EQ20: NA | ER20: NA | ES20: NA | ET20: NA | EU20: NA | EV20: NA | EW20: NA | EX20: NA | EY20: NA | EZ20: NA | FA20: NA | FB20: NA | FC20: NA | FD20: Tramite prorroga: N/A Tramite modificación : N/A Seguimiento (Revisión): Requerido mediante Auto No. 0251 de fecha 24 de febrero de 2026. | FE20: MILENA GALINDO | FF20: 46167

Sheet CA 2011
C1: CONTROL TRAMITE DE CONCESION DE AGUAS 2024 | FD1: Código | FE1: RE-AA-20
FD2: Versión | FE2: 7
FD3: Fecha | FE3: 44411
A4: DATOS DE LA SOLICITUD | O4: APERTURÓ | P4: REQUERIMIENTO | W4: PAGO SERVICIOS DE EVALUACION | AB4: No. Oficio/ Auto de Requerimiento | AE4: CONTROL- DIAS TRANSCURRIDOS HASTA FECHA DE VISITA | AF4: CONCEPTO TECNICO | AV4: CONTROL- DIAS TRANSCURRIDOS DE LA RADICACION AL CONCEPTO CON Vo.Bo. | AW4: FECHA DE ASIGNACION CONCEPTO AL AREA JURIDICO | AX4: REQUERIMIENTO | BC4: ACTO ADMINISTRATIVO | BL4: RECURSO DE REPOSICION | BS4: MEMORIAS DE CALCULO | CB4: RECIBO A SATISFACCION DE OBRAS | CK4: ACTO ADMINISTRATIVO | EU4: SEGUIMIENTO | FD4: Observaciones de lo evidenciado en la visita técnica | FE4: Ultima Actualización
A5: No. Radicado | B5: Fecha Radicado | C5: No. Expediente | D5: RADICADO EN VITAL | E5: Solicitante/Interesado | F5: Cédula de ciudadanía - NIT | G5: Dirección de correspondencia | H5: Telefono | I5: Correo Electrónico | J5: Municipio permiso | K5: Lugar de la captación (Vereda) | L5: Tipo de Fuente | M5: Fuente | N5: Nombre de la Fuente | P5: No. Oficio/ Auto de Requerimiento | Q5: Fecha Oficio/ Auto de Requerimiento | R5: Nombre de quién proyectó | S5: Dias del radicado al requerimiento | T5: Descripcion del requerimiento | U5: Radicado Oficio de entrada | V5: Fecha oficio de entrada | W5: No. de la Factura | X5: Valor tabla única (Factura) | Y5: Valor Facturado | Z5: Valor Cancelado | AA5: Fecha del pago servicio de evaluación | AB5: No. Oficio/ Auto de Requerimiento | AC5: Fecha Oficio/ Auto de Requerimiento | AD5: Nombre de quién proyectó | AF5: Fecha Visita técnica | AG5: Nombre del técnico | AH5: FECHA LIMITE ENTREGA DE CONCEPTO | AI5: DIAS CALENDARIO TRANSCURRIDOS SEGÚN FECHA LIMITE DE ENTRE DE CONCEPTO Y FECHA DE VISITA TECNICA | AJ5: ALERTAS | AK5: Fecha entrega a Revisión Informe - Lider | AL5: Entrega de Informe al técnico para corrección | AM5: Entrega de concepto corregido | AN5: Fecha Concepto técnico | AO5: Predio a beneficiar | AP5: Georreferenciación del punto de captación | AQ5: Vereda de la localización del punto de captación | AR5: Usos | AS5: Caudal Otordo, dicriminado por cada uso | AT5: Total del caudal otorgado | AU5: Número de Suscriptores | AX5: No. Auto de Requerimiento | AY5: Fecha Auto de Requerimiento | AZ5: Nombre de quién proyectó | BA5: Radicado Oficio de entrada | BB5: Fecha oficio de entrada | BC5: No. Acto Administrativo | BD5: Fecha Acto Administrativo | BE5: Nombre de quién proyectó | BF5: Otorgada | BG5: Negada | BH5: Desistida | BI5: Fecha Notificación | BJ5: Fecha ejecutoria | BK5: Fecha de vencimiento | BL5: No. Radicado | BM5: Fecha Radicado | BN5: No. Acto Administrativo | BO5: Fecha Acto Administrativo | BP5: Nombre de quién proyectó | BQ5: Modifica/ Aclara / Confirma/ Adiciona /Niega | BR5: Fecha Notificación | BS5: No. Radicado | BT5: Fecha Radicado | BU5: Auto Requer. | BV5: Fecha Requer. | BW5: Nombre de quién proyecto | BX5: No. Acto Administrativo | BY5: Fecha Act Administrativo | BZ5: Nombre de quien proyectó | CA5: Cumple o NO | CB5: No. Radicado del usuario | CC5: Fecha Radicado | CD5: Fecha de visita técnica | CE5: Fecha Informe técnico | CF5: Nombre del técnico | CG5: No. Acto Administrativo | CH5: Fecha Acto Administrativo | CI5: Nombre de quién proyectó | CJ5: Cumple o NO | CK5: No. Radicado | CL5: Fecha Radicado | CM5: Fecha de visita técnica | CN5: Fecha Informe técnico | CO5: Nombre del técnico | CP5: No. Acto Administrativo | CQ5: Fecha de notificación | CR5: Fecha de ejecutoria | CS5: Observación | CT5: No. Radicado | CU5: Fecha Radicado | CV5: Fecha de visita técnica | CW5: Fecha Informe técnico | CX5: Nombre del técnico | CY5: No. Acto Administrativo | CZ5: Fecha de notificación | DA5: Fecha de ejecutoria | DB5: Observación | DC5: No. Radicado | DD5: Fecha Radicado | DE5: Fecha de visita técnica | DF5: Fecha Informe técnico | DG5: Nombre del técnico | DH5: No. Acto Administrativo | DI5: Fecha de notificación | DJ5: Fecha de ejecutoria | DK5: Observación | DL5: No. Radicado | DM5: Fecha Radicado | DN5: Fecha de visita técnica | DO5: Fecha Informe técnico | DP5: Nombre del técnico | DQ5: No. Acto Administrativo | DR5: Fecha de notificación | DS5: Fecha de ejecutoria | DT5: Observación | DU5: No. Radicado | DV5: Fecha Radicado | DW5: Fecha de visita técnica | DX5: Fecha Informe técnico | DY5: Nombre del técnico | DZ5: No. Acto Administrativo | EA5: Fecha de notificación | EB5: Fecha de ejecutoria | EC5: Observación | ED5: No. Radicado | EE5: Fecha Radicado | EF5: Fecha de visita técnica | EG5: Fecha Informe técnico | EH5: Nombre del técnico | EI5: No. Acto Administrativo | EJ5: Fecha de notificación | EK5: Fecha de ejecutoria | EL5: Observación | EM5: Fecha Radicado | EN5: Fecha de visita técnica | EO5: Fecha Informe técnico | EP5: Nombre del técnico | EQ5: RECLAMACION TUA | ER5: Fecha de notificación | ES5: Fecha de ejecutoria | ET5: Observación | EU5: Fecha ultimo seguimiento | EV5: Fecha de concepto | EW5: Cadual Aforado (Captado o vertido) | EX5: Volumen metros cubicos aprovechado ( AF) aprovechamiento forestal | EY5: Entrega informes Anuales (L.A) Solo aplica para licencias ambientales | FB5: Acto administrativo
AV6: Solicitamos se agregue la formula | CP6: Modificacion | CY6: Traspaso | DH6: Prorroga | DQ6: Cancelación | DZ6: Perdida de fuerza ejecutoria | EI6: Suspensión | EY6: Llantas Usadas | EZ6: ICA | FA6: Autoliquidación de la vigencia | FB6: N° | FC6: Fecha
EY7: SI /NO
A8: 2011ER706 | B8: 44241 | C8: CA 024-2011 | D8: PENDIENTE | E8: LUIS GERARDO ROA MARTINEZ | F8: 4048819 | G8: CARRERA 7 #10-46 | H8: 3112083225 | J8: SAN LUIS DE GACENO | K8: LOS ARRAYANES | L8: SUPERFICIAL | M8: NACIMIENTO | N8: CAÑO SEGURA | AF8: 40682 | AG8: LUIS CARLOS ORTIZ | AN8: 40702 | AO8: VILLA PAOLA | BC8: 538 | BD8: 40799 | BE8: CARLOS AUGUSTO CIERRA RIOS | BF8: X | BI8: 40815 | DC8: 2021ER1693 | DD8: 44263 | DE8: 44384 | DF8: 44445 | DG8: KARLA HERNANDEZ | DH8: 1237 (14 SEPTIEMBRE DE 2021) | DI8: 44494 | EQ8: Resolución No. 208 (13-06-2017) RESOLUCIÓN 545 (29 JUNIO DE 2023) | ER8: 19-09-17 (AVISO) | ET8: PENDIENTE NOTIFICACIÓN DE LA RESOLUCIÓN 545 DE FECHA 29 DE JUNIO DE 2023 | EW8: NA | EX8: NA | EY8: NA | EZ8: NA | FA8: NA | FB8: NA | FC8: NA
C9: CA 074/11 | D9: NA | E9: CLAUDIA ESTELLA ALFONSO | F9: 23694685 | G9: Carrera 2 # 1A 19 | H9: 320 831 5839 | I9: claualfo@hotmail.com | J9: SANTA MARIA | K9: CENTRO | L9: SUPERFICIAL | M9: QUEBRADA | N9: EL CHULO | O9: NA | P9: NA | Q9: NA | R9: NA | S9: NA | T9: NA | U9: NA | V9: NA | W9: NA | X9: NA | Y9: NA | Z9: NA | AA9: NA | AB9: NA | AC9: NA | AD9: NA | AE9: NA | AF9: NA | AG9: NA | AH9: NA | AI9: NA | AJ9: NA | AK9: NA | AL9: NA | AM9: NA | AN9: NA | AO9: NA | AP9: NA | AQ9: NA | AR9: NA | AS9: NA | AT9: NA | AU9: NA | AV9: NA | AW9: NA | AX9: NA | AY9: NA | AZ9: NA | BA9: NA | BB9: NA | BC9: 540 | BD9: 40799 | BE9: NA | BF9: X | BG9: NA | BH9: NA | BI9: 40829 | BJ9: 40840 | BK9: 44493 | BL9: NA | BM9: NA | BN9: NA | BO9: NA | BP9: NA | BQ9: NA | BR9: NA | BS9: NA | BT9: NA | BU9: NA | BV9: NA | BW9: NA | BX9: NA | BY9: NA | BZ9: NA | CA9: NA | CB9: NA | CC9: NA | CD9: NA | CE9: NA | CF9: NA | CG9: NA | CH9: NA | CI9: NA | CJ9: NA | CK9: NA | CL9: NA | CM9: NA | CN9: NA | CO9: NA | CP9: NA | CQ9: NA | CR9: NA | CS9: NA | CT9: NA | CU9: NA | CV9: NA | CW9: NA | CX9: NA | CY9: NA | CZ9: NA | DA9: NA | DB9: NA | DC9: NA | DD9: NA | DE9: NA | DF9: NA | DG9: NA | DH9: 479 | DI9: 44714 | DJ9: 44729 | DK9: VIGENTEHASTA 17-6-22 | DL9: 2025ER13295 | DM9: 45967 | DN9: NA | DO9: NA | DP9: NA | DQ9: NA | DR9: NA | DS9: NA | DT9: NA | DU9: NA | DV9: NA | DW9: NA | DX9: NA | DY9: NA | DZ9: NA | EA9: NA | EB9: NA | EC9: NA | ED9: NA | EE9: NA | EF9: NA | EG9: NA | EH9: NA | EI9: NA | EJ9: NA | EK9: NA | EL9: NA | EM9: NA | EN9: NA | EO9: NA | EP9: NA | EQ9: NA | ER9: NA | ES9: NA | ET9: NA | EU9: NA | EV9: NA | EW9: NA | EX9: NA | EY9: NA | EZ9: NA | FA9: NA | FB9: NA | FC9: NA | FD9: PENDIENTE CONCEPTO TECNICO EN EL MARCO DE CANCELACIÓN | FE9: MILENA GALINDO | FF9: 45689
A10: 2011ER2847 | B10: 40696 | C10: CA 078-11 | D10: PENDIENTE | E10: ANA DELIA BERMUDEZ DE FANDIÑO | F10: 23421395 | G10: CALLE 6 N 3-08 | H10: 31024791220 | I10: fandinosbemardino@gmail.com | J10: SAN LUIS DE GACENO | P10: 2025EE8729 | Q10: 45875 | R10: KAREN BARRETO | U10: 2025ER7395 | V10: 45846 | BC10: 686 | BD10: 40847 | BE10: CARLOS SIERRA | BF10: X | BG10: NA | BH10: NA | BI10: 40869 | EW10: NA | EX10: NA | EY10: NA | EZ10: NA | FA10: NA | FB10: NA | FC10: NA | FD10: PENDIENTE PAGO FACTURA PARA CONTINUAR CON EL PERMISO | FE10: KAREN BARRETO | FF10: 45897

Sheet CA 2012
C1: CONTROL TRAMITE DE CONCESION DE AGUAS 2024 | FD1: Código | FE1: RE-AA-20 | FF1: FECHA ACTUALIZACION
FD2: Versión | FE2: 7
FD3: Fecha | FE3: 44411
A4: DATOS DE LA SOLICITUD | O4: APERTURÓ | P4: REQUERIMIENTO | W4: PAGO SERVICIOS DE EVALUACION | AB4: No. Oficio/ Auto de Admite | AE4: CONTROL- DIAS TRANSCURRIDOS HASTA FECHA DE VISITA | AF4: CONCEPTO TECNICO | AV4: CONTROL- DIAS TRANSCURRIDOS DE LA RADICACION AL CONCEPTO CON Vo.Bo. | AW4: FECHA DE ASIGNACION CONCEPTO AL AREA JURIDICO | AX4: REQUERIMIENTO | BC4: ACTO ADMINISTRATIVO | BL4: RECURSO DE REPOSICION | BS4: MEMORIAS DE CALCULO | CB4: RECIBO A SATISFACCION DE OBRAS | CK4: ACTO ADMINISTRATIVO | EU4: SEGUIMIENTO | FD4: Observaciones de lo evidenciado en la visita técnica | FE4: Ultima Actualización
A5: No. Radicado | B5: Fecha Radicado | C5: No. Expediente | D5: RADICADO EN VITAL | E5: Solicitante/Interesado | F5: Cédula de ciudadanía - NIT | G5: Dirección de correspondencia | H5: Telefono | I5: Correo Electrónico | J5: Municipio permiso | K5: Lugar de la captación (Vereda) | L5: Tipo de Fuente | M5: Fuente | N5: Nombre de la Fuente | P5: No. Oficio/ Auto de Requerimiento | Q5: Fecha Oficio/ Auto de Requerimiento | R5: Nombre de quién proyectó | S5: Dias del radicado al requerimiento | T5: Descripcion del requerimiento | U5: Radicado Oficio de entrada | V5: Fecha oficio de entrada | W5: No. de la Factura | X5: Valor tabla única (Factura) | Y5: Valor Facturado | Z5: Valor Cancelado | AA5: Fecha del pago servicio de evaluación | AB5: No. Oficio/ Auto de Admite | AC5: Fecha Oficio/ Auto de Admite | AD5: Nombre de quién proyectó | AF5: Fecha Visita técnica | AG5: Nombre del técnico | AH5: FECHA LIMITE ENTREGA DE CONCEPTO | AI5: DIAS CALENDARIO TRANSCURRIDOS SEGÚN FECHA LIMITE DE ENTRE DE CONCEPTO Y FECHA DE VISITA TECNICA | AJ5: ALERTAS | AK5: Fecha entrega a Revisión Informe - Lider | AL5: Entrega de Informe al técnico para corrección | AM5: Entrega de concepto corregido | AN5: Fecha Concepto técnico | AO5: Predio a beneficiar | AP5: Georreferenciación del punto de captación | AQ5: Vereda de la localización del punto de captación | AR5: Usos | AS5: Caudal Otordo, dicriminado por cada uso | AT5: Total del caudal otorgado | AU5: Número de Suscriptores | AX5: No. Auto de Requerimiento | AY5: Fecha Auto de Requerimiento | AZ5: Nombre de quién proyectó | BA5: Radicado Oficio de entrada | BB5: Fecha oficio de entrada | BC5: No. Acto Administrativo | BD5: Fecha Acto Administrativo | BE5: Nombre de quién proyectó | BF5: Otorgada | BG5: Negada | BH5: Desistida | BI5: Fecha Notificación | BJ5: Fecha ejecutoria | BK5: Fecha de vencimiento | BL5: No. Radicado | BM5: Fecha Radicado | BN5: No. Acto Administrativo | BO5: Fecha Acto Administrativo | BP5: Nombre de quién proyectó | BQ5: Modifica/ Aclara / Confirma/ Adiciona /Niega | BR5: Fecha Notificación | BS5: No. Radicado | BT5: Fecha Radicado | BU5: Auto Requer. | BV5: Fecha Requer. | BW5: Nombre de quién proyecto | BX5: No. Acto Administrativo | BY5: Fecha Act Administrativo | BZ5: Nombre de quien proyectó | CA5: Cumple o NO | CB5: No. Radicado del usuario | CC5: Fecha Radicado | CD5: Fecha de visita técnica | CE5: Fecha Informe técnico | CF5: Nombre del técnico | CG5: No. Acto Administrativo | CH5: Fecha Acto Administrativo | CI5: Nombre de quién proyectó | CJ5: Cumple o NO | CK5: No. Radicado | CL5: Fecha Radicado | CM5: Fecha de visita técnica | CN5: Fecha Informe técnico | CO5: Nombre del técnico | CP5: No. Acto Administrativo | CQ5: Fecha de notificación | CR5: Fecha de ejecutoria | CS5: Observación | CT5: No. Radicado | CU5: Fecha Radicado | CV5: Fecha de visita técnica | CW5: Fecha Informe técnico | CX5: Nombre del técnico | CY5: No. Acto Administrativo | CZ5: Fecha de notificación | DA5: Fecha de ejecutoria | DB5: Observación | DC5: No. Radicado | DD5: Fecha Radicado | DE5: Fecha de visita técnica | DF5: Fecha Informe técnico | DG5: Nombre del técnico | DH5: No. Acto Administrativo | DI5: Fecha de notificación | DJ5: Fecha de ejecutoria | DK5: Observación | DL5: No. Radicado | DM5: Fecha Radicado | DN5: Fecha de visita técnica | DO5: Fecha Informe técnico | DP5: Nombre del técnico | DQ5: No. Acto Administrativo | DR5: Fecha de notificación | DS5: Fecha de ejecutoria | DT5: Observación | DU5: No. Radicado | DV5: Fecha Radicado | DW5: Fecha de visita técnica | DX5: Fecha Informe técnico | DY5: Nombre del técnico | DZ5: No. Acto Administrativo | EA5: Fecha de notificación | EB5: Fecha de ejecutoria | EC5: Observación | ED5: No. Radicado | EE5: Fecha Radicado | EF5: Fecha de visita técnica | EG5: Fecha Informe técnico | EH5: Nombre del técnico | EI5: No. Acto Administrativo | EJ5: Fecha de notificación | EK5: Fecha de ejecutoria | EL5: Observación | EM5: Fecha Radicado | EN5: Fecha de visita técnica | EO5: Fecha Informe técnico | EP5: Nombre del técnico | EQ5: RECLAMACION TUA | ER5: Fecha de notificación | ES5: Fecha de ejecutoria | ET5: Observación | EU5: Fecha ultimo seguimiento | EV5: Fecha de concepto | EW5: Cadual Aforado (Captado o vertido) | EX5: Volumen metros cubicos aprovechado ( AF) aprovechamiento forestal | EY5: Entrega informes Anuales (L.A) Solo aplica para licencias ambientales | FB5: Acto administrativo
AV6: Solicitamos se agregue la formula | CP6: Modificacion | CY6: Traspaso | DH6: Prorroga | DQ6: Cancelación | DZ6: Perdida de fuerza ejecutoria | EI6: Suspensión | EY6: Llantas Usadas | EZ6: ICA | FA6: Autoliquidación de la vigencia | FB6: N° | FC6: Fecha
EY7: SI /NO
A9: 2011ER4732 | B9: 40798 | C9: CA 040-12 | D9: PENDIENTE | E9: JOSE ARISTIDES SARMIENTO | F9: 4276990 | G9: CARRERA 56 N 78-38 BOGOTA | H9: 3105735167 3144148517 | I9: AGROPECUARIA_JAS@HOTMAIL.COM | J9: TIBANA | K9: VEREDA CHIGUATA | L9: SUPERFICIAL | M9: NACIMIENTO | N9: EL RECUERDO | AC9: 357(15/03/2022) | AD9: ANGELA MARTINEZ | AX9: 26 | AY9: 43864 | AZ9: GINA MONROY | BC9: 181 | BD9: 40982 | BE9: JOSE AMAYA | BF9: X | BG9: NA | BH9: NA | BI9: 40995 | BS9: 2025ER3758 2025ER5071 | BT9: 24/04/2025 19/05/2025 | BU9: 568 | BV9: 45846 | BW9: KAREN BARRETO | CA9: SI | CG9: 828 | CH9: 44393 | CI9: IVONN GUTIERREZ | CJ9: SI | DC9: 2022ER10 | DD9: 44564 | DE9: 44656 | DF9: 44741 | DG9: KARLA H | DH9: 678(08/07/2022) | DK9: SI SE PRORROGA | ET9: NA | EU9: NA | EV9: NA | EW9: NA | EX9: NA | EY9: NA | EZ9: NA | FA9: NA | FB9: NA | FC9: NA | FD9: SE APRUEBAN MEMORIAS | FE9: KAREN BARRETO | FF9: 45854
A10: 2012ER922 | B10: 41272 | C10: 085-12 | E10: ARISITIDES SARMIENTO ROMERO | F10: 4275195 | G10: Autopista Sur No. 66 - 78 Local B12 -B13 | H10: 601 713 4803 | I10: lospinosambiental@gmail.com | J10: TIBANA | BC10: 332 848 | BD10: 09-05-2012 08-09-2023 | BF10: x | BI10: 45118 | BJ10: 45183 | BK10: 12311 | BS10: 2025ER6115 | BT10: 45817 | BX10: 746 | BY10: 45882 | BZ10: MILENA GALINDO | CA10: SI | FD10: PENDIENTE RECIBO DE OBRAS | FF10: 45891
A11: 2012ER826 | B11: 40963 | C11: CA 088-12 | E11: BERTHA INES MARQUEZ DE SALOMÓN | F11: 20295836 | H11: 3123518865 | I11: asesoriaytramitesamb@gmail.com | J11: JENESANO | L11: SUPERFICIAL | N11: CHORRO PALENQUE | AB11: SIN | AC11: 40973 | AF11: 45739 | AN11: 41040 | AX11: 5540 | AY11: 41075 | BC11: 308 | BD11: 41453 | BF11: X | BI11: 41550 | FD11: RES 216 11/04/2025 POR MEDIO DEL CUAL SE DECLARA EL DESISTIMIENTO TÁCITO DE LA SOLICITUD DE PRÓRROGA
A12: 2012ER1316 | B12: 40991 | C12: CA 098/12 | E12: JAIME ANDRADE APONTE LOPEZ Representante Legal DISTRITO DE RIEGO EL TRIUNFO | F12: NA | G12: Vereda Potreros | H12: 313 462 5184 | J12: Nuevo Colón | L12: SUPERFICIAL | M12: NA | N12: NA | O12: NA | P12: NA | Q12: NA | R12: NA | S12: NA | T12: NA | U12: NA | V12: NA | W12: NA | X12: NA | Y12: NA | Z12: NA | AA12: NA | AB12: NA | AC12: NA | AD12: NA | AE12: NA | AF12: NA | AG12: NA | AH12: NA | AI12: NA | AJ12: NA | AK12: NA | AL12: NA | AM12: NA | AN12: NA | AO12: NA | AP12: NA | AQ12: NA | AR12: NA | AS12: NA | AT12: NA | AU12: NA | AV12: NA | AW12: NA | AX12: NA | AY12: NA | AZ12: NA | BA12: NA | BB12: NA | BC12: 468 094 | BD12: 26/06/2012 27/02/2023 | BE12: NA | BF12: X | BG12: NA | BH12: NA | BI12: 5/07/2012 17/04/2023 | BJ12: 13/07/2012 03/05/2023 | BK12: 48702 | BL12: NA | BM12: NA | BN12: NA | BO12: NA | BP12: NA | BQ12: NA | BR12: NA | BS12: NA | BT12: NA | BU12: NA | BV12: NA | BW12: NA | BX12: NA | BY12: NA | BZ12: NA | CA12: NA | CB12: NA | CC12: NA | CD12: NA | CE12: NA | CF12: NA | CG12: NA | CH12: NA | CI12: NA | CJ12: NA | CK12: NA | CL12: NA | CM12: NA | CN12: NA | CO12: NA | CP12: 1145 | CQ12: 45751 | CR12: NA | CS12: NA | CT12: NA | CU12: NA | CV12: NA | CW12: NA | CX12: NA | CY12: NA | CZ12: NA | DA12: NA | DB12: NA | DC12: NA | DD12: NA | DE12: NA | DF12: NA | DG12: NA | DH12: NA | DI12: NA | DJ12: NA | DK12: NA | DL12: NA | DM12: NA | DN12: NA | DO12: NA | DP12: NA | DQ12: NA | DR12: NA | DS12: NA | DT12: NA | DU12: NA | DV12: NA | DW12: NA | DX12: NA | DY12: NA | DZ12: NA | EA12: NA | EB12: NA | EC12: NA | ED12: NA | EE12: NA | EF12: NA | EG12: NA | EH12: NA | EI12: NA | EJ12: NA | EK12: NA | EL12: NA | EM12: NA | EN12: NA | EO12: NA | EP12: NA | EQ12: NA | ER12: NA | ES12: NA | ET12: NA | EU12: NA | EV12: NA | EW12: NA | EX12: NA | EY12: NA | EZ12: NA | FA12: NA | FB12: NA | FC12: NA | FD12: REQUERIDO PARA QUE ALLEGUE SOPORTE DE CAMBIO DE REPRESENTANTE LEGAL 2026EE2727 | FE12: 46095
A13: 2012ER3423 | B13: 41124 | C13: CA 137-12 | D13: PENDIENTE | E13: GLORIA ANGELICA SANCHEZ BUENO | F13: 23423812 | G13: NA | H13: 3103419975 | I13: gcontable.surtiagrosanñuis@gmail.com | J13: SAN LUIS DE GACENO | L13: SUPERFICIAL | M13: QUEBRADA | N13: BUENA AVENTURA | O13: NA | AB13: SIN | AC13: 41282 | AD13: FNIÑO | AF13: 41282 | AG13: JHON ARIAS | AH13: NA | AI13: NA | AJ13: NA | AK13: NA | AL13: NA | AM13: NA | AN13: 41339 | AO13: EL PALMAR | AQ13: GAZAJARRO | AR13: INDUSTRIAL | AT13: 9.24 | AU13: NA | AX13: 175 | AY13: 44267 | AZ13: ANGY CARO | BA13: NA | BB13: NA | BC13: 336 | BD13: 41466 | BE13: ANA SALINAS | BF13: X | BG13: NA | BH13: NA | BI13: 41477 | BJ13: 41492 | BK13: 45144 | BL13: NA | BM13: NA | BN13: NA | BO13: NA | BP13: NA | BQ13: NA | BR13: NA | BS13: 2023ER8608 | BT13: 45166 | BU13: 3696 | BV13: 45264 | BW13: NA | BX13: NA | BY13: NA | BZ13: NA | CA13: NA | CB13: NA | CC13: NA | CD13: NA | CE13: NA | CF13: NA | CG13: NA | CH13: NA | CI13: NA | CJ13: NA | CK13: NA | CL13: NA | CM13: NA | CN13: NA | CO13: NA | CP13: NA | CQ13: NA | CR13: NA | CS13: NA | CT13: NA | CU13: NA | CV13: NA | CW13: NA | CX13: NA | CY13: NA | CZ13: NA | DA13: NA | DB13: NA | DC13: NA | DD13: NA | DE13: NA | DF13: NA | DG13: NA | DH13: NA | DI13: NA | DJ13: NA | DK13: NA | DL13: NA | DM13: NA | DN13: NA | DO13: NA | DP13: NA | DQ13: NA | DR13: NA | DS13: NA | DT13: NA | DU13: NA | DV13: NA | DW13: NA | DX13: NA | DY13: NA | DZ13: NA | EA13: NA | EB13: NA | EC13: NA | ED13: NA | EE13: NA | EF13: NA | EG13: NA | EH13: NA | EI13: NA | EJ13: NA | EK13: NA | EL13: NA | EM13: 2025ER15039 | EN13: 0-12-25 | EO13: 46021 | EP13: CAROL C | EQ13: RESOLUCION 0091 | ER13: 46359 | ES13: 46377 | ET13: NA | EU13: 43570 | EV13: 43581 | EW13: NA | EX13: NA | EY13: NA | EZ13: NA | FA13: NA | FB13: 175 | FC13: 44267 | FD13: VENCIDA | FE13: MILENA G | FF13: 46095
A14: 2012ER3715 | B14: 41143 | C14: CA 140-12 | D14: PENDIENTE | E14: ACUEDUCTOS SUTAMANGA | F14: 900012936-5 | G14: VEREDA SUTA ABAJO | H14: 3125385830 | I14: sutamanga@gmail.com | J14: TIBANA | K14: NA | L14: NA | M14: NA | N14: NA | O14: NA | P14: NA | Q14: NA | R14: NA | S14: NA | T14: NA | U14: NA | V14: NA | W14: NA | X14: NA | Y14: NA | Z14: NA | AA14: NA | AB14: SIN 979 (MODIFICACION) | AC14: 2/01/2013 24/10/2017 | AD14: ANA SALINAS DAMARIS BUSTOS | AE14: NA | AF14: NA | AG14: NA | AH14: NA | AI14: NA | AJ14: NA | AK14: NA | AL14: NA | AM14: NA | AN14: NA | AO14: NA | AP14: NA | AQ14: NA | AR14: NA | AS14: NA | AT14: NA | AU14: NA | AV14: NA | AW14: NA | AX14: NA | AY14: NA | AZ14: NA | BA14: NA | BB14: NA | BC14: 230 273 (MODIFICA) | BD14: 28/05/2013 29/05/2018 | BE14: ANA SALINAS LAURA M | BF14: X | BG14: NA | BH14: NA | BI14: 13/06/2013 31/05/2018 | BJ14: NA | BK14: NA | BL14: NA | BM14: NA | BN14: NA | BO14: NA | BP14: NA | BQ14: NA | BR14: NA | BS14: NA | BT14: NA | BU14: NA | BV14: NA | BW14: NA | BX14: NA | BY14: NA | BZ14: NA | CA14: NA | CB14: NA | CC14: NA | CD14: NA | CE14: NA | CF14: NA | CG14: NA | CH14: NA | CI14: NA | CJ14: NA | CK14: NA | CL14: NA | CM14: NA | CN14: NA | CO14: NA | CP14: NA | CQ14: NA | CR14: NA | CS14: NA | CT14: NA | CU14: NA | CV14: NA | CW14: NA | CX14: NA | CY14: NA | CZ14: NA | DA14: NA | DB14: NA | DC14: NA | DD14: NA | DE14: NA | DF14: NA | DG14: NA | DH14: NA | DI14: NA | DJ14: NA | DK14: NA | DL14: NA | DM14: NA | DN14: NA | DO14: NA | DP14: NA | DQ14: NA | DR14: NA | DS14: NA | DT14: NA | DU14: NA | DV14: NA | DW14: NA | DX14: NA | DY14: NA | DZ14: NA | EA14: NA | EB14: NA | EC14: NA | ED14: NA | EE14: NA | EF14: NA | EG14: NA | EH14: NA | EI14: NA | EJ14: NA | EK14: NA | EL14: NA | EM14: NA | EN14: NA | EO14: NA | EP14: NA | EQ14: NA | ER14: NA | ES14: NA | ET14: NA | EU14: NA | EV14: NA | EW14: NA | EX14: NA | EY14: NA | EZ14: NA | FA14: NA | FB14: NA | FC14: NA | FD14: RECLAMACION TUA RES 766 DEL 20/08/2025 | FE14: KAREN BARRETO | FF14: 45897
A15: 2012ER4500 | B15: 41180 | C15: CA 153-2012 | D15: PENDIENTE | E15: CERVELEON ALFONSO LOPEZ | F15: 19145149 | G15: CALLE 3#6 35 | H15: 3212322188 | J15: SAN LUIS DE GACENO | L15: SUPERFICIAL | M15: QUEBRADA | N15: BARSOVIA | BC15: 629 | BD15: 41940 | BF15: X | BI15: 41949 | BJ15: 41967 | EU15: 42549 | EV15: 42583 | FB15: 104 | FC15: 42802 | FD15: REQUIERE FLOTADORES, OBRAS, PAGO SEGUIMIENTO
A16: 2012ER4529 | B16: 41183 | C16: CA 156-12 | D16: PENDIENTE | E16: ANDRES RICARDO CUBIDES LOPEZ | F16: 1056688186 | G16: VEREDA BARRO BLANCO ARRIBA | H16: 3188784226 | I16: NA | J16: LA CAPILLA | AB16: SIN | AC16: 41276 | AD16: JUANK | BC16: 232 | BD16: 41422 | BE16: JUANK | BF16: X | BG16: NA | BH16: NA | EN16: NA | EO16: NA | EP16: NA | EQ16: NA | ER16: NA | ES16: NA | ET16: NA | EU16: NA | EV16: NA | EW16: NA | EX16: NA | EY16: NA | EZ16: NA | FA16: NA | FB16: NA | FC16: NA | FD16: MEDIANTE RES 0236 DEL 14/04/2025 POR MEDIO DE LA CUAL SE DECLARA EL DESISTIMIENTO TACITO Y SE ORDENA EL ARCHIVO DEL EXPEDIENTE | FE16: ADRIANA B | FF16: 45775
A17: 2012ER4625 | B17: 41187 | C17: CA 158-12 | D17: PENDIENTE | E17: JUSTO GERMAN PULIDO SANCHEZ | F17: 4290248 | G17: CARRERA 3 N 6-03 | H17: 3125212436 | J17: VEREDA SACANECA PACHAVITA | K17: VEREDA SACANECA PACHAVITA | L17: SUPERFICIAL | M17: QUEBRADA | N17: EL BEJUCO | BC17: 524 | BD17: 41564 | BE17: ANA SALINAS | BF17: X | BI17: 41598 | BJ17: 41613 | BK17: 45265 | CB17: 2014ER2207 | CC17: 41773 | CD17: 41810 | CE17: 41845 | CF17: WUALTER CRUZ | CG17: 526 | CH17: 41886 | CI17: ANA SALINAS | CJ17: SI | DZ17: 641 | EA17: 45533 | EB17: PENDIENTE FECHA | FE17: KAREN BARRERO | FF17: 45544
C18: CA 172-12 | E18: OMAR ANTONIO MEDINA BUITRAGO | F18: 4128829 | G18: Predio El Pabellón Vereda Pie de Peña Pachavita - Boyacá | H18: 310 887 5749 | N18: LA JUCUA | O18: NA | P18: NA | Q18: NA | R18: NA | S18: NA | T18: NA | U18: NA | V18: NA | W18: NA | X18: NA | Y18: NA | Z18: NA | AA18: NA | AB18: NA | AC18: NA | AD18: NA | AE18: NA | AF18: NA | AG18: NA | AH18: NA | AI18: NA | AJ18: NA | AK18: NA | AL18: NA | AM18: NA | AN18: NA | AO18: NA | AP18: NA | AQ18: NA | AR18: NA | AS18: NA | AT18: NA | AU18: NA | AV18: NA | AW18: NA | AX18: NA | AY18: NA | AZ18: NA | BA18: NA | BB18: NA | BC18: 517 | BD18: 41564 | BE18: ANA SALINAS | BF18: x | BG18: NA | BH18: NA | BI18: 41570 | BJ18: 41586 | BK18: 41586 | BL18: NA | BM18: NA | BN18: NA | BO18: NA | BP18: NA | BQ18: NA | BR18: NA | BS18: NA | BT18: NA | BU18: NA | BV18: NA | BW18: NA | BX18: NA | BY18: NA | BZ18: NA | CA18: NA | CB18: NA | CC18: NA | CD18: NA | CE18: NA | CF18: NA | CG18: NA | CH18: NA | CI18: NA | CJ18: NA | CK18: NA | CL18: NA | CM18: NA | CN18: NA | CO18: NA | CP18: NA | CQ18: NA | CR18: NA | CS18: NA | CT18: NA | CU18: NA | CV18: NA | CW18: NA | CX18: NA | CY18: NA | CZ18: NA | DA18: NA | DB18: NA | DC18: NA | DD18: NA | DE18: NA | DF18: NA | DG18: NA | DH18: NA | DI18: NA | DJ18: NA | DK18: NA | DL18: NA | DM18: NA | DN18: NA | DO18: NA | DP18: NA | DQ18: NA | DR18: NA | DS18: NA | DT18: NA | DU18: NA | DV18: NA | DW18: NA | DX18: NA | DY18: NA | DZ18: NA | EA18: NA | EB18: NA | EC18: NA | ED18: NA | EE18: NA | EF18: NA | EG18: NA | EH18: NA | EI18: NA | EJ18: NA | EK18: NA | EL18: NA | EM18: NA | EN18: NA | EO18: NA | EP18: NA | EQ18: NA | ER18: NA | ES18: NA | ET18: NA | EU18: NA | EV18: NA | EW18: NA | EX18: NA | EY18: NA | EZ18: NA | FA18: NA | FB18: NA | FC18: NA | FD18: PRORROGADO | FE18: MILENA G | FF18: 46199
A19: 2012ER5068 | B19: 41215 | C19: CA 166-12 | D19: PENDIENTE | E19: LILIAN ALICIA LEGUIZAMON MARTINAZ | F19: 33675862 | G19: CARRERA 10 N 12-06 | H19: 3103451888 | I19: NA | J19: GARAGOA | P19: 2022EE12853 | Q19: 44860 | R19: MARTHA SANCHEZ | S19: NA | BC19: 343 | BD19: 41466 | BE19: ANA SALINAS | BF19: X | BG19: NA | BH19: NA | DZ19: 250 | EA19: 45253 | EC19: SE RESUELVE UNA RECLAMACION DE LAS FACTURAS DE TUA 646 PERIODO 20 | EY19: NA | EZ19: NA | FA19: NA | FB19: NA | FC19: NA | FD19: DESISTIDA Y SE ANULA FACTURA DE TUA 646 PERIODO 20 | FE19: KAREN BARRETO | FF19: 45849
A20: 2012ER5616 | B20: 41253 | C20: CA 186-12 | D20: PENDIENTE | E20: ROSALBA SARMIENTO RODRIGUEZ | F20: 24162509 | G20: VEREDA MOMBITA | H20: 3197758259 | I20: WILLIAM.MORENO9714@GMAIL.COM | J20: TIBANA | K20: MOMNITA | L20: SUPERFICIAL | M20: RIO | N20: TURMEQUE | O20: NA | P20: NA | Q20: NA | R20: NA | S20: NA | T20: NA | U20: NA | V20: NA | W20: NA | X20: NA | Y20: NA | Z20: NA | AA20: NA | AB20: NA | AC20: NA | AD20: NA | AE20: NA | AF20: NA | AG20: NA | AH20: NA | AI20: NA | AJ20: NA | AK20: NA | AL20: NA | AM20: NA | AN20: NA | AO20: NA | AP20: NA | AQ20: NA | AR20: NA | AS20: NA | AT20: NA | AU20: NA | AV20: NA | AW20: NA | AX20: NA | AY20: NA | AZ20: NA | BA20: NA | BB20: NA | BC20: 339 | BD20: 41466 | BE20: ANA SALINAS | BF20: X | BG20: NA | BH20: NA | BI20: 41481 | BJ20: 41499 | BK20: 45151 | BL20: NA | BM20: NA | BN20: NA | BO20: NA | BP20: NA | BQ20: NA | BR20: NA | BS20: 2025ER7805 | BT20: 45855 | BV20: 0 | BX20: 1485 1307 | BY20: 8/09/2025 28-11-25 | BZ20: KAREN BARRETO MILENA GALINDO | CA20: NO | CB20: NA | CC20: NA | CD20: NA | CE20: NA | CF20: NA | CG20: NA | CH20: NA | CI20: NA | CJ20: NA | CK20: NA | CL20: NA | CM20: NA | CN20: NA | CO20: NA | CP20: NA | CQ20: NA | CR20: NA | CS20: NA | CT20: NA | CU20: NA | CV20: NA | CW20: NA | CX20: NA | CY20: NA | CZ20: NA | DA20: NA | DB20: NA | DC20: 2022ER9715 | DD20: 44831 | DE20: 44897 | DF20: 44924 | DG20: CARLA H | DH20: 72 | DI20: 44972 | DJ20: 45027 | DK20: VENCE 11/04/2033 | DL20: NA | DM20: NA | DN20: NA | DO20: NA | DP20: NA | DQ20: NA | DR20: NA | DS20: NA | DT20: NA | DU20: NA | DV20: NA | DW20: NA | DX20: NA | DY20: NA | DZ20: NA | EA20: NA | EB20: NA | EC20: NA | ED20: NA | EE20: NA | EF20: NA | EG20: NA | EH20: NA | EI20: NA | EJ20: NA | EK20: NA | EL20: NA | EM20: NA | EN20: NA | EO20: NA | EP20: NA | EQ20: NA | ER20: NA | ES20: NA | ET20: NA | EU20: 45588 | EV20: 45652 | EW20: 5.416 | EX20: NA | EY20: NA | EZ20: NA | FA20: NA | FB20: NA | FC20: NA | FD20: SE REQUIERE PARA MEMORIAS | FE20: MILENA G | FF20: 45997
A21: 2012ER5406 | B21: 41240 | C21: CA 188-12 | D21: PENDIENTE | E21: JAIRO LOPÉZ COLMENARES | F21: 4290906 | G21: jairo.lopezcolmenares@gmail.com | H21: 3204188673 | I21: jairo.lopezcolmenares@gmail.com | J21: ÚMBITA | K21: VEREDA LOS PUENTES | L21: SUPERFICIAL | M21: QUEBRADA | N21: LAS QUINCHAS | O21: NA | P21: 2024EE9768 2024EE11734 2024EE12872 | Q21: 23/09/2024 14/11/2024 | R21: PAULA MORENO MILENA GALINDO KAREN BARRETO | S21: NA | T21: RESPUESTA RESPUESTA | U21: 2024ER8255 2024ER9910 2024ER12931 | V21: 28/008/224 25/19/2024 28/11/2024 | W21: EVA 235 | X21: 148485 | Y21: 148485 | Z21: 148485 | AA21: SIN | AB21: SIN | AC21: 41347 | AD21: ELKYN | AE21: NA | AF21: 41373 | AG21: MARCO DURAN | AH21: NA | AI21: NA | AJ21: NA | AK21: NA | AL21: NA | AM21: NA | AN21: NA | AO21: NA | AP21: NA | AQ21: NA | AR21: NA | AS21: NA | AT21: NA | AU21: NA | AV21: NA | AW21: NA | AX21: NA | AY21: NA | AZ21: NA | BA21: NA | BB21: NA | BC21: 707 | BD21: 41631 | BE21: NA | BF21: X | BG21: NA | BH21: NA | BI21: 41652 | BJ21: 41667 | BK21: 45319 | BL21: NA | BM21: NA | BN21: NA | BO21: NA | BP21: NA | BQ21: NA | BR21: NA | BS21: NA | BT21: NA | BU21: NA | BV21: NA | BW21: NA | BX21: NA | BY21: NA | BZ21: NA | CA21: NA | CB21: NA | CC21: NA | CD21: NA | CE21: NA | CF21: NA | CG21: NA | CH21: NA | CI21: NA | CJ21: NA | CK21: NA | CL21: NA | CM21: NA | CN21: NA | CO21: NA | CP21: NA | CQ21: NA | CR21: NA | CS21: NA | CT21: NA | CU21: NA | CV21: NA | CW21: NA | CX21: NA | CY21: NA | CZ21: NA | DA21: NA | DB21: NA | DC21: 2023ER10220 | DD21: 45209 | DE21: NA | DF21: NA | DG21: NA | DH21: 1319 | DI21: NA | DJ21: NA | DK21: NA | DL21: NA | DM21: NA | DN21: NA | DO21: NA | DP21: NA | DQ21: NA | DR21: NA | DS21: NA | DT21: NA | DU21: NA | DV21: NA | DW21: NA | DX21: NA | DY21: NA | DZ21: NA | EA21: NA | EB21: NA | EC21: NA | ED21: NA | EE21: NA | EF21: NA | EG21: NA | EH21: NA | EI21: NA | EJ21: NA | EK21: NA | EL21: NA | EM21: NA | EN21: NA | EO21: NA | EP21: NA | EQ21: NA | ER21: NA | ES21: NA | ET21: NA | EU21: 42804 | EV21: 29/011/2016 | EW21: NA | EX21: NA | EY21: NA | EZ21: NA | FA21: NA | FB21: 117 | FC21: 41708 | FD21: POR MEIDO DE LA RES 628 18/06/2025 SE MODIFICA Y RPORROGA LA CONCESION DE AGUAS | FE21: KAREN BARRETO | FF21: 45897
A22: 2012ER2036 | B22: 41038 | C22: CA 192-12 | D22: PENDIENTE | E22: ACUEDUCTO REGIONAL ASO BOSQUE | F22: 820002617-8 | G22: VEREDA JURCA | H22: 3133014586 | I22: asobosque@yahoo.com | J22: VENTAQUEMADA | K22: BOQUERON | L22: NA | M22: NA | N22: QUEBRADA COLORADA | O22: DILMA GUTIERREZ | P22: 204 | Q22: 44272 | R22: ANGIE CARO GALINDO | S22: NA | T22: NA | U22: 2024ER5468 | V22: 44383 | W22: NA | X22: NA | Y22: NA | Z22: NA | AA22: NA | AB22: AUTO | AC22: 41282 | AD22: ANA SALINAS | AE22: NA | AF22: 41303 | AG22: NA | AH22: NA | AI22: NA | AJ22: NA | AK22: NA | AL22: NA | AM22: NA | AN22: 42077 | AO22: LOTE 2 RESERVA FORESTAL SAN FRANCISCO | AP22: NA | AQ22: NA | AR22: NA | AS22: NA | AT22: 8,29LPS | AU22: NA | AV22: NA | AW22: NA | AX22: NA | AY22: NA | AZ22: NA | BA22: NA | BB22: NA | BC22: RES 453 | BD22: 41528 | BE22: ANA SALINAS | BF22: X | BG22: NA | BH22: CONSUMO DOMESTICO | BI22: 41540 | BJ22: 41555 | BK22: 45207 | BL22: NA | BM22: NA | BN22: NA | BO22: NA | BP22: NA | BQ22: NA | BR22: NA | BS22: 2013ER4977 | BT22: 41599 | BU22: NA | BV22: NA | BW22: NA | BX22: 716 | BY22: 45874 | BZ22: KAREN BARRETO | CA22: SI | CB22: NA | CC22: NA | CD22: NA | CE22: NA | CF22: NA | CG22: NA | CH22: NA | CI22: NA | CJ22: NA | CK22: NA | CL22: NA | CM22: NA | CN22: NA | CO22: NA | CP22: NA | CQ22: NA | CR22: NA | CS22: NA | CT22: NA | CU22: NA | CV22: NA | CW22: NA | CX22: NA | CY22: NA | CZ22: NA | DA22: NA | DB22: NA | DC22: 2023ER9222 | DD22: 45182 | DE22: 45548 | DF22: NA | DG22: ADRIAN DIAZ | DH22: 914 | DI22: 45611 | DJ22: 45628 | DK22: AUTO 879 2024 | DL22: NA | DM22: NA | DN22: NA | DO22: NA | DP22: NA | DQ22: NA | DR22: NA | DS22: NA | DT22: NA | DU22: NA | DV22: NA | DW22: NA | DX22: NA | DY22: NA | DZ22: NA | EA22: NA | EB22: NA | EC22: NA | ED22: NA | EE22: NA | EF22: NA | EG22: NA | EH22: NA | EI22: NA | EJ22: NA | EK22: NA | EL22: NA | EM22: NA | EN22: NA | EO22: NA | EP22: NA | EQ22: NA | ER22: NA | ES22: NA | ET22: NA | EU22: NA | EV22: NA | EW22: NA | EX22: NA | EY22: NA | EZ22: NA | FA22: NA | FB22: NA | FC22: NA | FD22: SE APRUEBAN MEMORIAS | FE22: KEREN BARRETO | FF22: 45897

Sheet CA 2013
C1: CONTROL TRAMITE DE CONCESION DE AGUAS 2024 | FD1: Código | FE1: RE-AA-20 | FF1: FECHA ACTUALIZACION
FD2: Versión | FE2: 7
FD3: Fecha | FE3: 44411
A4: DATOS DE LA SOLICITUD | O4: APERTURÓ | P4: REQUERIMIENTO | W4: PAGO SERVICIOS DE EVALUACION | AB4: No. Oficio/ Auto de ADMITE | AE4: CONTROL- DIAS TRANSCURRIDOS HASTA FECHA DE VISITA | AF4: CONCEPTO TECNICO | AV4: CONTROL- DIAS TRANSCURRIDOS DE LA RADICACION AL CONCEPTO CON Vo.Bo. | AW4: FECHA DE ASIGNACION CONCEPTO AL AREA JURIDICO | AX4: REQUERIMIENTO | BC4: ACTO ADMINISTRATIVO | BL4: RECURSO DE REPOSICION | BS4: MEMORIAS DE CALCULO | CB4: RECIBO A SATISFACCION DE OBRAS | CK4: ACTO ADMINISTRATIVO | EU4: SEGUIMIENTO | FD4: Observaciones de lo evidenciado en la visita técnica | FE4: Ultima Actualización
A5: No. Radicado | B5: Fecha Radicado | C5: No. Expediente | D5: RADICADO EN VITAL | E5: Solicitante/Interesado | F5: Cédula de ciudadanía - NIT | G5: Dirección de correspondencia | H5: Telefono | I5: Correo Electrónico | J5: Municipio permiso | K5: Lugar de la captación (Vereda) | L5: Tipo de Fuente | M5: Fuente | N5: Nombre de la Fuente | P5: No. Oficio/ Auto de Requerimiento | Q5: Fecha Oficio/ Auto de Requerimiento | R5: Nombre de quién proyectó | S5: Dias del radicado al requerimiento | T5: Descripcion del requerimiento | U5: Radicado Oficio de entrada | V5: Fecha oficio de entrada | W5: No. de la Factura | X5: Valor tabla única (Factura) | Y5: Valor Facturado | Z5: Valor Cancelado | AA5: Fecha del pago servicio de evaluación | AB5: No. Oficio/ Auto de ADMITE | AC5: Fecha Oficio/ Auto de ADMITE | AD5: Nombre de quién proyectó | AF5: Fecha Visita técnica | AG5: Nombre del técnico | AH5: FECHA LIMITE ENTREGA DE CONCEPTO | AI5: DIAS CALENDARIO TRANSCURRIDOS SEGÚN FECHA LIMITE DE ENTRE DE CONCEPTO Y FECHA DE VISITA TECNICA | AJ5: ALERTAS | AK5: Fecha entrega a Revisión Informe - Lider | AL5: Entrega de Informe al técnico para corrección | AM5: Entrega de concepto corregido | AN5: Fecha Concepto técnico | AO5: Predio a beneficiar | AP5: Georreferenciación del punto de captación | AQ5: Vereda de la localización del punto de captación | AR5: Usos | AS5: Caudal Otordo, dicriminado por cada uso | AT5: Total del caudal otorgado | AU5: Número de Suscriptores | AX5: No. Auto de Requerimiento | AY5: Fecha Auto de Requerimiento | AZ5: Nombre de quién proyectó | BA5: Radicado Oficio de entrada | BB5: Fecha oficio de entrada | BC5: No. Acto Administrativo | BD5: Fecha Acto Administrativo | BE5: Nombre de quién proyectó | BF5: Otorgada | BG5: Negada | BH5: Desistida | BI5: Fecha Notificación | BJ5: Fecha ejecutoria | BK5: Fecha de vencimiento | BL5: No. Radicado | BM5: Fecha Radicado | BN5: No. Acto Administrativo | BO5: Fecha Acto Administrativo | BP5: Nombre de quién proyectó | BQ5: Modifica/ Aclara / Confirma/ Adiciona /Niega | BR5: Fecha Notificación | BS5: No. Radicado | BT5: Fecha Radicado | BU5: Auto Requer. | BV5: Fecha Requer. | BW5: Nombre de quién proyecto | BX5: No. Acto Administrativo | BY5: Fecha Act Administrativo | BZ5: Nombre de quien proyectó | CA5: Cumple o NO SI | CB5: No. Radicado del usuario | CC5: Fecha Radicado | CD5: Fecha de visita técnica | CE5: Fecha Informe técnico | CF5: Nombre del técnico | CG5: No. Acto Administrativo | CH5: Fecha Acto Administrativo | CI5: Nombre de quién proyectó | CJ5: Cumple o NO | CK5: No. Radicado | CL5: Fecha Radicado | CM5: Fecha de visita técnica | CN5: Fecha Informe técnico | CO5: Nombre del técnico | CP5: No. Acto Administrativo | CQ5: Fecha de notificación | CR5: Fecha de ejecutoria | CS5: Observación | CT5: No. Radicado | CU5: Fecha Radicado | CV5: Fecha de visita técnica | CW5: Fecha Informe técnico | CX5: Nombre del técnico | CY5: No. Acto Administrativo | CZ5: Fecha de notificación | DA5: Fecha de ejecutoria | DB5: Observación | DC5: No. Radicado | DD5: Fecha Radicado | DE5: Fecha de visita técnica | DF5: Fecha Informe técnico | DG5: Nombre del técnico | DH5: No. Acto Administrativo | DI5: Fecha de notificación | DJ5: Fecha de ejecutoria | DK5: Observación | DL5: No. Radicado | DM5: Fecha Radicado | DN5: Fecha de visita técnica | DO5: Fecha Informe técnico | DP5: Nombre del técnico | DQ5: No. Acto Administrativo | DR5: Fecha de notificación | DS5: Fecha de ejecutoria | DT5: Observación | DU5: No. Radicado | DV5: Fecha Radicado | DW5: Fecha de visita técnica | DX5: Fecha Informe técnico | DY5: Nombre del técnico | DZ5: No. Acto Administrativo | EA5: Fecha de notificación | EB5: Fecha de ejecutoria | EC5: Observación | ED5: No. Radicado | EE5: Fecha Radicado | EF5: Fecha de visita técnica | EG5: Fecha Informe técnico | EH5: Nombre del técnico | EI5: No. Acto Administrativo | EJ5: Fecha de notificación | EK5: Fecha de ejecutoria | EL5: Observación | EM5: Fecha Radicado | EN5: Fecha de visita técnica | EO5: Fecha Informe técnico | EP5: Nombre del técnico | EQ5: RECLAMACION TUA | ER5: Fecha de notificación | ES5: Fecha de ejecutoria | ET5: Observación | EU5: Fecha ultimo seguimiento | EV5: Fecha de concepto | EW5: Cadual Aforado (Captado o vertido) | EX5: Volumen metros cubicos aprovechado ( AF) aprovechamiento forestal | EY5: Entrega informes Anuales (L.A) Solo aplica para licencias ambientales | FB5: Acto administrativo
AV6: Solicitamos se agregue la formula | BS6: 2024ER824 | BT6: 31/01/20124 | CP6: Modificacion | CY6: Traspaso | DH6: Prorroga | DQ6: Cancelación | DZ6: Perdida de fuerza ejecutoria | EI6: Suspensión | EY6: Llantas Usadas | EZ6: ICA | FA6: Autoliquidación de la vigencia | FB6: N° | FC6: Fecha
EY7: SI /NO
C8: C.A. 004/13 | E8: LUIS ERNESTO PULIDO RINCON | F8: 4221909 | H8: 3144843383 | J8: RAMIRIQUI | K8: VEREDA ESCOBAL | L8: SUPERFICIAL | BC8: 394 | BD8: 45118 | BF8: X | DH8: 1207 | DI8: 45246 | DJ8: 12-28-23 | FD8: Seguimiento (Revisión): Requerido Mediante Auto No.1147 de fecha 11 de mayo de 2023. | FE8: MILENA GALINDO | FF8: 46172
A9: 2013ER498 | B9: 41312 | C9: C.A 12-13 | D9: PENDIENTE | E9: ANA YOLANDA GARZON DE ORTEGA | F9: 23620627 | G9: Calle 12No.10-04 | H9: 3112768230 | I9: felipeortega43@gmail.com | J9: Guateque | K9: Sibata | L9: SUPERFICIAL | M9: NACIMIENTO | N9: Aljibe Sin Nombre | O9: Vanesa Roa | AB9: AUTO | AC9: 17 DE JUNIO DEL 2013 | AD9: FREDY P | AF9: 41660 | AG9: MARCO DURAN | AN9: 41691 | AO9: La Quintica | AP9: N.A | AQ9: Sibata | AR9: industrial | AS9: 0.017 | AT9: 0.017 | AX9: N.A | AY9: N.A | AZ9: N.A | BA9: N.A | BB9: N.A | BC9: Res 967 | BD9: 43830 | BE9: Vanesa Roa | BF9: x | BG9: N.A | BH9: N.A | BI9: N.A | BJ9: N.A | BK9: N.A | BL9: N.A | BM9: N.A | BN9: N.A | BO9: N.A | BP9: N.A | BQ9: N.A | BR9: N.A | BS9: N.A | BT9: N.A | BU9: N.A | BV9: N.A | BW9: N.A | BX9: N.A | BY9: N.A | BZ9: N.A | CA9: N.A | CB9: N.A | CC9: N.A | CD9: N.A | CE9: N.A | CF9: N.A | CG9: N.A | CH9: N.A | CI9: N.A | CJ9: N.A | CK9: N.A | CL9: N.A | CM9: N.A | CN9: N.A | CO9: N.A | CP9: N.A | CQ9: N.A | CR9: N.A | CS9: N.A | CT9: N.A | CU9: N.A | CV9: N.A | CW9: N.A | CX9: N.A | CY9: N.A | CZ9: N.A | DA9: N.A | DB9: N.A | DC9: N.A | DD9: N.A | DE9: N.A | DF9: N.A | DG9: N.A | DH9: N.A | DI9: N.A | DJ9: N.A | DK9: Requerido para allegar comprobante de pago mediante Resolución No. 0399 de fecha 23 de abril de 2026 | DL9: N.A | DM9: N.A | DN9: N.A | DO9: N.A | DP9: N.A | DQ9: N.A | DR9: N.A | DS9: N.A | DT9: N.A | DU9: N.A | DV9: N.A | DW9: N.A | DX9: N.A | DY9: N.A | DZ9: N.A | EA9: N.A | EB9: N.A | EC9: N.A | ED9: N.A | EE9: N.A | EF9: N.A | EG9: N.A | EH9: N.A | EI9: N.A | EJ9: N.A | EK9: N.A | EL9: N.A | EM9: N.A | EN9: N.A | EO9: N.A | EP9: N.A | EQ9: N.A | ER9: N.A | ES9: N.A | ET9: N.A | EU9: 45051 | EV9: 45141 | EW9: 0.078 | FB9: 773 | FC9: 45509 | FD9: EN PROCESO DE PRORROGA | FE9: MILENA GALINDO | FF9: 46134
A10: 2013ER151 | B10: 41657 | C10: CA 013-13 | D10: PENDIENTE | E10: CARLOS RAFAEL VARGAS ALBARRACIN | F10: 7171899 | G10: VEREDA PANCUPA | H10: 3209314347 | I10: j7955009@gmail.com Cperilla7080@gmail.com | J10: TURMEQUE | K10: CENTRO | L10: SUPERFICIAL | M10: RIO | N10: ALBARRACIN | O10: NA | P10: NA | Q10: NA | R10: NA | S10: NA | T10: NA | U10: NA | V10: NA | W10: NA | X10: NA | Y10: NA | Z10: NA | AA10: NA | AB10: NA | AC10: NA | AD10: NA | AE10: NA | AF10: NA | AG10: NA | AH10: NA | AI10: NA | AJ10: NA | AK10: NA | AL10: NA | AM10: NA | AN10: NA | AO10: NA | AP10: NA | AQ10: NA | AR10: NA | AS10: NA | AT10: NA | AU10: NA | AV10: NA | AW10: NA | AX10: NA | AY10: NA | AZ10: NA | BA10: NA | BB10: NA | BC10: 157 | BD10: 41716 | BE10: ANA CELIA SALINAS | BF10: X | BG10: NA | BH10: NA | BI10: 41834 | BJ10: 41849 | BK10: 45502 | BL10: NA | BM10: NA | BN10: NA | BO10: NA | BP10: NA | BQ10: NA | BR10: NA | BS10: NA | BT10: NA | BU10: NA | BV10: NA | BW10: NA | BX10: NA | BY10: NA | BZ10: NA | CA10: NA | CB10: NA | CC10: NA | CD10: NA | CE10: NA | CF10: NA | CG10: NA | CH10: NA | CI10: NA | CJ10: NA | CK10: NA | CL10: NA | CM10: NA | CN10: NA | CO10: NA | CP10: NA | CQ10: NA | CR10: NA | CS10: NA | CT10: NA | CU10: NA | CV10: NA | CW10: NA | CX10: NA | CY10: NA | CZ10: NA | DA10: NA | DB10: NA | DC10: NA | DD10: NA | DE10: NA | DF10: NA | DG10: NA | DH10: NA | DI10: NA | DJ10: NA | DK10: NA | DL10: NA | DM10: NA | DN10: NA | DO10: NA | DP10: NA | DQ10: NA | DR10: NA | DS10: NA | DT10: NA | DU10: NA | DV10: NA | DW10: NA | DX10: NA | DY10: NA | DZ10: NA | EA10: NA | EB10: NA | EC10: NA | ED10: NA | EE10: NA | EF10: NA | EG10: NA | EH10: NA | EI10: NA | EJ10: NA | EK10: NA | EL10: NA | EM10: NA | EN10: NA | EO10: NA | EP10: NA | EQ10: NA | ER10: NA | ES10: NA | ET10: NA | EU10: 30/09/2020 17/10/2023 | EV10: 9/11/2020 28/12/2023 | EW10: 0,062 1,30 | EX10: NA | EY10: NA | EZ10: NA | FA10: NA | FB10: NA | FC10: NA | FD10: Por medio de oficio No. 2025EE4616 se comunico que la concesion se encuentra vencida | FE10: MILENA GALINDO | FF10: 45813
A11: 2013ER2013ER44 | B11: 41282 | C11: CA 018-13 | D11: PENDIENTE | E11: GUSTAVO GIL PINZON | F11: 4276077 | G11: VEREDA BAYETA | H11: 3144037939 | I11: NA | J11: TIBANA | EY11: NA | EZ11: NA | FA11: NA | FB11: NA | FC11: NA | FD11: DESISTIDA MEDIANTE RES 1203 DEL 09/11/2022 NOTIFICAICON POR AVISO OFICIO 2025EE6762 | FE11: KAREN BARRETO | FF11: 45853
A12: 2013ER180 | B12: 41296 | C12: CA 022-13 | D12: PENDIENTE | E12: AURA LUZ ROJAS QUIMBAYA | F12: 26477625 | G12: VEREDA PANCUPA | H12: 3209314347 | I12: j7955009@gmail.com Cperilla7080@gmail.com | J12: somondoco | K12: SANTA LUCIA | L12: SUPERFICIAL | M12: QUEBRADA | N12: ANIMAS O QUEBRADA PANCUPA | O12: NA | P12: 2024EE10870 2025EE445 | Q12: 25/10/2024 06/02/2025 | R12: PAULA MARANTA KAREN BARRETO | S12: NA | T12: NA | U12: 2020ER8493 2024ER9933 2025ER76 | V12: 21/12/2020 25/09/2024 09/01/2025 | W12: 1486 SSEG21 EV16 | X12: 112194 148485 156585 | Y12: 112194 148485 156585 | Z12: 112194 148485 156585 | AA12: SIN SIN SIN | AB12: SIN | AC12: 41442 | AD12: FREDY P | AF12: 41662 | AG12: MARCO DURAN | AH12: NA | AI12: NA | AJ12: NA | AK12: NA | AL12: NA | AM12: NA | AN12: 41691 | AO12: SANTA LUCIA | AP12: 05°´0,4" 73°24´56,4" ALTURA3507-03 | AQ12: PANCUPA | AR12: DOMESTICO PECUARIO | AT12: 1,5 LPS | AU12: 3 PERSONAS 20 BOVINOS 20 PORCINOS 3000 PECES | AV12: NA | AW12: NA | AX12: 1112 260 | AY12: 23/11/2020 09/04/2024 | AZ12: IVONNE G DIANA B | BA12: NA | BB12: NA | BC12: 274 | BD12: 41767 | BE12: HERSY V | BF12: X | BG12: N | BH12: NA | BI12: 41843 | BJ12: 41859 | BK12: 45512 | BL12: NA | BM12: NA | BN12: NA | BO12: NA | BP12: NA | BQ12: NA | BR12: NA | BS12: NA | BT12: NA | BU12: NA | BV12: NA | BW12: NA | BX12: NA | BY12: NA | BZ12: NA | CA12: NA | CB12: NA | CC12: NA | CD12: NA | CE12: NA | CF12: NA | CG12: NA | CH12: NA | CI12: NA | CJ12: NA | CK12: NA | CL12: NA | CM12: NA | CN12: NA | CO12: NA | CP12: NA | CQ12: NA | CR12: NA | CS12: NA | CT12: NA | CU12: NA | CV12: NA | CW12: NA | CX12: NA | CY12: NA | CZ12: NA | DA12: NA | DB12: NA | DC12: NA | DD12: NA | DE12: NA | DF12: NA | DG12: NA | DH12: NA | DI12: NA | DJ12: NA | DK12: NA | DL12: NA | DM12: NA | DN12: NA | DO12: NA | DP12: NA | DQ12: NA | DR12: NA | DS12: NA | DT12: NA | DU12: NA | DV12: NA | DW12: NA | DX12: NA | DY12: NA | DZ12: NA | EA12: NA | EB12: NA | EC12: NA | ED12: NA | EE12: NA | EF12: NA | EG12: NA | EH12: NA | EI12: NA | EJ12: NA | EK12: NA | EL12: NA | EM12: NA | EN12: NA | EO12: NA | EP12: NA | EQ12: NA | ER12: NA | ES12: NA | ET12: NA | EU12: 30/09/2020 17/10/2023 | EV12: 9/11/2020 28/12/2023 | EW12: 0,062 1,30 | EX12: NA | EY12: NA | EZ12: NA | FA12: NA | FB12: NA | FC12: NA | FD12: PENDIENTE COMPROVANTE DE PAGO FAVCTURA | FE12: KAREN BARRETO | FF12: 45756
A13: 2013ER1545 | B13: 41380 | C13: C.A 068-13 | D13: PENDIENTE | E13: JOSE PRESENTACIÓN JIMENEZ RAMIREZ | F13: 17021910 | G13: Fragua | H13: 3133278136 | I13: NA | J13: Ramiriqui | L13: SUPERFICIAL | M13: NACIMIENTO | N13: En Encanto | O13: ANA CELIA | AB13: SIN | AC13: 41436 | AD13: FREDY P | AF13: 41681 | AG13: MARCO DURAN | AN13: 41769 | AO13: Buenos Aires Santarder | AT13: 0.52 | AU13: Domestico 9 personas 20 Bovinos 5 hectareas de cultivo | BC13: Res 459 | BD13: 41851 | BE13: Elkyn | BF13: x | BG13: NA | BH13: NA | BI13: 41862 | BJ13: 41878 | BK13: 45531 | BL13: NA | BM13: NA | BN13: NA | BO13: NA | BP13: NA | BQ13: NA | BR13: NA | BS13: AN | BT13: NA | BU13: NA | BV13: NA | BW13: NA | BX13: NA | BY13: NA | BZ13: NA | CA13: NA | CB13: NA | CC13: NA | CD13: NA | CE13: NA | CF13: NA | CG13: NA | CH13: NA | CI13: NA | CJ13: NA | CK13: NA | CL13: NA | CM13: NA | CN13: NA | CO13: NA | CP13: NA | CQ13: NA | CR13: NA | CS13: NA | CT13: NA | CU13: NA | CV13: NA | CW13: NA | CX13: NA | CY13: NA | CZ13: NA | DA13: NA | DB13: NA | DC13: 2025ER2456 | DD13: 45369 | DE13: NA | DF13: NA | DG13: NA | DH13: NA | DI13: NA | DJ13: NA | DK13: NA | DL13: NA | DM13: NA | DN13: NA | DO13: NA | DP13: NA | DQ13: NA | DR13: NA | DS13: NA | DT13: NA | DU13: NA | DV13: NA | DW13: NA | DX13: NA | DY13: NA | DZ13: NA | EA13: NA | EB13: NA | EC13: NA | ED13: NA | EE13: NA | EF13: NA | EG13: NA | EH13: NA | EI13: NA | EJ13: NA | EK13: NA | EL13: NA | EM13: NA | EN13: NA | EO13: NA | EP13: NA | EQ13: NA | ER13: NA | ES13: NA | ET13: NA | FD13: Res. 1354 de fecha 03-12-2024, se desiste solicitud radicado 2024ER2456 Esta para realizar perdida de fuerza | FE13: KAREN BARRETO | FF13: 46010
A14: 2013ER517 | B14: 41313 | C14: CA 027-13 | D14: PENDIENTE | E14: MARIA OLGA PORRAS DE SUAREZ | F14: 41405934 | G14: CARRERA 80B N 6-25 RINCON DE TECHO 3 TORRE 10 APAT 338 | H14: 3142200698 | I14: NA | J14: TIBANA | K14: VEREDA LAJA | L14: SUPERFICIAL | M14: NACIMIENTO | N14: SIN NOMBRE | P14: 2024EE1238 2024EE2622 2024EE4555 2024EE6200 2024EE1238 2024EE2622 2024EE4555 | Q14: 4/03/2024 05/04/2024 17/05/2024 09/07/2024 04/03/2024 05/04/2024 17/05/2024 | R14: MILENA GALINDO KAREN BARRETO KAREN BUITRAGO PAULA MPRENO MILENA GALINDO KAREN BARRETO KAREN BUITRAGO | S14: NA | T14: NA | U14: 2024ER3449 2024ER7347 2024ER11702 2024ER821 2024ER2378 2024ER3449 2024ER11702 | V14: 19/04/2024 01/08/2024 01/11/2024 31/01/2024 15/03/2024 19/04/2024 01/11/2024 | AB14: 1011 | AC14: 45582 | AD14: PAULA MARANTA | AF14: 45636 | AG14: ANGIE ALVAREZ | AH14: NA | AI14: NA | AJ14: NA | AK14: NA | AL14: NA | AM14: NA | AN14: 45650 | AO14: LOS RECUERDOS | AP14: MANANTIAL 1 5°20´8,136" 73°23´53,690" AL 2179 MANANTIAL 2 5°20´8,467" 73°23´53,418" ALT 2182 MANANTIAL 3 5°20´8,620" 73°23´52,650" AL 2173 | AQ14: LAJAS | AR14: DOMESTICO | AS14: 0,01 0,01 0,01 | AT14: 0.03 | AU14: NA | AX14: 1443 | AY14: 45079 | AZ14: MAURICIO QUIROGA | BA14: 2024ER821 | BB14: 45322 | BC14: 193 | BD14: 41731 | BE14: ANA SALINAS | BF14: X | BG14: NA | BH14: NA | BI14: 41750 | BJ14: 41767 | BK14: 45420 | DC14: 2024ER4598 | DD14: 20/052024 | DH14: 1011 1219 420 (04/05/2025 | DI14: 22/10/2024 25/11/2024 09/06/2025 | DJ14: 23/10/2024 26/11/2024 25/06/2025 | FD14: SE PRORROCO , MODIFICO Y TRASPASO | FE14: KAREN BARRETO | FF14: 45819
A15: 2013ER488 | B15: 41312 | C15: CA 028-13 | E15: NUMAEL ZAMBRANO SALAMANCA | F15: 4132284 | G15: VEREDA SOCHAQUIRA | H15: 3142242599 | I15: mariasalinas@outlook.com | J15: GUAYATA | K15: SOCHAQUIRA ARRIBA Y ABAJO | L15: SUPERFICIAL | M15: QUEBRADA | N15: LA PLAYA | BC15: 456 | BD15: 41528 | BE15: ANA SALINAS | BF15: X | BI15: 41568 | BJ15: 41584 | BK15: 45236 | DC15: 2023ER9023 | DD15: 0/09/23 | DK15: SE ADMITE EL TRAMITE A TRAVES DE AUTO 468 | FD15: OFICIO REQUERIMIENTO DE DOCUMENTACIÓN < | FE15: MILENA GALINDO
A16: 2013ER183 | B16: 41296 | C16: CA 029-13 | D16: PENDIENTE | E16: LUIS ALBERTO MORA ROA | F16: 74364765 | G16: VEREDA SICHA | H16: 3132227859 | I16: luisalbertomora81@gmail.com | J16: CHINAVITA | K16: SICHA ARRIBA | L16: SUPERFICIAL | M16: NACIMIENTO | N16: SAN JUAN 1 SAN JUAN 2 | BC16: 239 | BD16: 41751 | BF16: X | CY16: 133 (04/03/2022) | CZ16: 45169 | DA16: 45184 | DB16: SE REALIZA TRASPASO DE LA SRA GLORIA MERCEDES DUARTE ALBA AL SEÑOR LUIS ALBERTO MORA ROA | DC16: 2024ER2645 | DD16: 45377 | DE16: 45551 | DG16: ROCIO LESMES | DK16: AUTO ADMITE 878-24 - AUTO 1308 DE FECHA 05/12/2024 | FD16: MEDIANTE RES 774 DEL 20/08/2025 SE NIEGA SOLICITUD DE PRORROGA | FE16: KAREN BARRETO | FF16: 45897
A17: 2013ER194 | B17: 41297 | C17: CA 037-13 | D17: PENDIENTE | E17: TERESA SANABRIA DE SALOMO | F17: 23651631 | G17: VEREDA HERBIDEROS | H17: 3144156621 3125397380 | I17: leiderrodriguez9@gmail.com | J17: JENESANO | K17: NA | L17: SUPERFICIAL | M17: NACIMIENTO | N17: LA ENTRADA | O17: NA | P17: NA | Q17: NA | R17: NA | S17: NA | T17: NA | U17: NA | V17: NA | W17: 2339 | X17: 114001 | Y17: 114001 | Z17: 114001 | AA17: 44658 | AX17: 1793 262 | AY17: 14/12/2021 09/04/2024 | AZ17: YENNY G DIANA B | BA17: NA | BB17: NA | BC17: 218 | BD17: 41739 | BE17: ERCYB | BF17: X | BG17: NA | BH17: NA | BI17: 41833 | BJ17: 41849 | BK17: 45502 | BL17: NA | BM17: NA | BN17: NA | BO17: NA | BP17: NA | BQ17: NA | BR17: NA | BS17: NA | BT17: NA | BU17: NA | BV17: NA | BW17: NA | BX17: NA | BY17: NA | BZ17: NA | CA17: NA | CB17: NA | CC17: NA | CD17: NA | CE17: NA | CF17: NA | CG17: NA | CH17: NA | CI17: NA | CJ17: NA | CK17: NA | CL17: NA | CM17: NA | CN17: NA | CO17: NA | CP17: NA | CQ17: NA | CR17: NA | CS17: NA | CT17: NA | CU17: NA | CV17: NA | CW17: NA | CX17: NA | CY17: NA | CZ17: NA | DA17: NA | DB17: NA | DC17: NA | DD17: NA | DE17: NA | DF17: NA | DG17: NA | DH17: NA | DI17: NA | DJ17: NA | DK17: NA | DL17: NA | DM17: NA | DN17: NA | DO17: NA | DP17: NA | DQ17: NA | DR17: NA | DS17: NA | DT17: NA | DU17: 2024ER8480 | DV17: 45532 | DW17: 45556 | DX17: 45593 | DY17: NA | DZ17: 884 | EA17: 45604 | EB17: NA | EC17: 45622 | ED17: NA | EE17: NA | EF17: NA | EG17: NA | EH17: NA | EI17: NA | EJ17: NA | EK17: NA | EL17: NA | EM17: NA | EN17: NA | EO17: NA | EP17: NA | EQ17: NA | ER17: NA | ES17: NA | ET17: NA | EU17: 17/09/2021021/11/2023 | EV17: 4/11/2021 27/12/2023 | EW17: NA | EX17: NA | EY17: NA | EZ17: NA | FA17: NA | FB17: NA | FC17: NA | FD17: SE DIO RESPUESTA A RADICADO 2024ER8480 | FE17: ALEJANDRA GUERRERO | FF17: 45611
A18: 2013ER546 | B18: 41316 | C18: CA 038-13 | D18: PENDIENTE | E18: RAFAEL ANTONIO REYES PORRAS | F18: 79381902 | G18: VEREDA LAJA | H18: 3112637923 | I18: NA | J18: TIBANA | L18: SUPERFICIAL | AB18: SIN | AC18: 41436 | AD18: ANA SALINAS | FD18: SE DECLARA DESISTIMIENTO MEDIANTE RES 1217 DEL 10/11/2022 Y NOTIFICADA POR AVISO OFICIO N 2025EE6768 | FE18: KAREN BARRETO | FF18: 45853
A19: 2013ER1130 | B19: 41347 | C19: CA 052-13 | E19: JUNTA DE ACCION COMUNAL DE CASERIO DE LA FRONTERA DEL MUNICIPIO DE SAN LUIS DE GACENO | G19: CRA 4 #6-09 | H19: 6248458 | J19: SAN LUIS DE GACENO | L19: SUPERFICIAL | M19: QUEBRADA | N19: LA ANGURRIA | BC19: 1688 | BD19: 44522 | BF19: X | BI19: 41634 | BJ19: 41653 | BK19: 45305 | DW19: 44369 | DX19: 44496 | DZ19: 1688 (2021) | EA19: 44559 | EC19: POR NO DERIVACION
A20: 2013ER986 | B20: 41339 | C20: CA 056-13 | E20: MARIA AMPARO BORDA DE PARRA | F20: 23963801 | I20: amparoborda0@gmail.com | J20: RAMIRIQUI | K20: CAICEDOS | L20: SUPERFICIAL | M20: Fuente | N20: LA ISLA | BC20: 154 | BD20: 41716 | BF20: x | BI20: 41730 | BJ20: 41745 | BK20: 45398 | FD20: ACTUALMENTE SE ENCUENTRA VENCIDA - PERO SIN DECLARAR PERDIDA | FE20: MILENA GALINDO | FF20: 45880
A21: 2013ER1170 | B21: 41351 | C21: CA 059-13 | D21: PENDIENTE | E21: VICTOR MANUEL RIVERA Y OTROS | F21: 72326659 | G21: VEREDA CAICEDOS | H21: 3227909494 | I21: NA | J21: RAMIRIQUI | K21: CAICEDOS | L21: SUPERFICIAL | M21: NACIMIENTO | N21: LA RESERVA | O21: NA | P21: 2024EE8627 2024EE11644 2024EE11645 2024EE12610 | Q21: 25/11/2014 13/11/2024 13/11/2024 02/12/2024 | R21: NA | S21: NA | T21: NA | U21: 2014ER5294 2021ER7604 2023ER8918 2023ER9473 2023ER10946 2024ER8921 | V21: 11/11/2014 09/09/2021 05/09/2023 19/09/2023 02/11/2023 05/09/2024 | W21: 377 | X21: 136205 | Y21: 136205 | Z21: 136205 | AA21: 45232 | AB21: NA | AC21: NA | AD21: NA | AE21: NA | AF21: 42087 | AG21: ANDRES O | AH21: NA | AI21: NA | AJ21: NA | AK21: NA | AL21: NA | AM21: NA | AN21: 42305 | AO21: SAN ROQUE | AP21: 05°22´53,08" 73°19´21,54" 2650 | AQ21: VEREDA CAICEDOS | AR21: DOMESTICO PECUARIO | AS21: NA | AT21: 0.02 | AU21: 6 | AV21: NA | AW21: NA | AX21: 210 820 798 | AY21: 18/03/2021 18/04/2023 14/08/2024 | AZ21: IVONNE G MAURICIO Q LEONARDO G | BA21: NA | BB21: NA | BC21: 174 | BD21: 41722 | BE21: ANA SALINAS | BF21: X | BG21: NA | BH21: NA | BI21: 41732 | BJ21: 41751 | BK21: 45404 | BL21: NA | BM21: NA | BN21: NA | BO21: NA | BP21: NA | BQ21: NA | BR21: NA | BS21: NA | BT21: NA | BU21: NA | BV21: NA | BW21: NA | BX21: NA | BY21: NA | BZ21: NA | CA21: NA | CB21: NA | CC21: NA | CD21: NA | CE21: NA | CF21: NA | CG21: NA | CH21: NA | CI21: NA | CJ21: NA | CK21: NA | CL21: NA | CM21: NA | CN21: NA | CO21: NA | CP21: 10 | CQ21: 42570 | CR21: 42586 | CS21: NA | CT21: NA | CU21: NA | CV21: NA | CW21: NA | CX21: NA | CY21: NA | CZ21: NA | DA21: NA | DB21: NA | DC21: NA | DD21: NA | DE21: NA | DF21: NA | DG21: NA | DH21: NA | DI21: NA | DJ21: NA | DK21: NA | DL21: NA | DM21: NA | DN21: NA | DO21: NA | DP21: NA | DQ21: NA | DR21: NA | DS21: NA | DT21: NA | DU21: 2024ER8921 | DV21: 45540 | DW21: NA | DX21: NA | DY21: NA | DZ21: 886 | EA21: 45608 | EB21: NA | EC21: NA | ED21: NA | EE21: NA | EF21: NA | EG21: NA | EH21: NA | EI21: NA | EJ21: NA | EK21: NA | EL21: NA | EM21: NA | EN21: NA | EO21: NA | EP21: NA | EQ21: NA | ER21: NA | ES21: NA | ET21: NA | EU21: 9/05/2017 03/12/2022 13/10/2023 | EV21: 22/08/2017 03/12/2022 01/11/2023 | EW21: 0,057 0,079 | EX21: NA | EY21: NA | EZ21: NA | FA21: NA | FB21: NA | FC21: NA | FD21: PENDIENTE NOTIFICACION POR AVISO MEDIANTE OFICIO 2024ER12610 DEL 02 DICIEMBRE 2024 | FE21: MILENA GALINDO | FF21: 45630
A22: 2013ER1545 | B22: 45398 | C22: CA 068-13 | E22: JOSÉ PRESENTACIÓN JIMÉNEZ RAMÍREZ | F22: 17021910 | G22: VEREDA FRAGUA | H22: 3203207147 | I22: cepgbioingenieria@gmail.com | J22: RAMIRIQUÍ | K22: VEREDA FRAGUA | L22: SUPERFICIAL | M22: NACIMIENTO | N22: EL ENACANTO | BC22: 459 | BD22: 45504 | BF22: X | CT22: 2024ER2456 - 2024ER7430 | CU22: 18/03/2024 - 05/08/2024 | FD22: EN PROCESO DE PRORROGA Y TRASPASO | FE22: PAULA MORENO | FF22: 45539
A23: 2013ER1581 | B23: 45033 | C23: CA 070-13 | D23: PENDIENTE | E23: LUIS ALFONSO ESPINOSA SANABRIA | F23: 4079569 | G23: VEREDA REQUITA | H23: 3133135388 | I23: ariasdavid736@gmail.com | J23: TIBANA | K23: VEREDA EL PLAN | L23: SUPERFICIAL | M23: QUEBRADA | N23: LAS DELICIAS | O23: NA | P23: NA | Q23: NA | R23: NA | S23: NA | T23: NA | U23: NA | V23: NA | W23: NA | X23: NA | Y23: NA | Z23: NA | AA23: NA | AB23: NA | AC23: 45306 | AD23: FREDY P | AE23: NA | AF23: 41683 | AG23: MARCO DURAN | AH23: NA | AI23: NA | AJ23: NA | AK23: NA | AL23: NA | AM23: NA | AN23: 41778 | AO23: el recuerdo, el roble , la frontera, la florida, los laureles y santa rosa | AP23: N1081106,957 E 1085932473 A 2932 | AQ23: VEREDA REAVITA Y EL PLAN | AR23: PECUARIO DOMESTICO | AS23: 0.04 | AT23: 0.08 | AU23: 9 | AV23: NA | AW23: NA | AX23: NA | AY23: NA | AZ23: NA | BA23: NA | BB23: NA | BC23: 391 | BD23: 41817 | BE23: HENRY | BF23: X | BG23: NA | BH23: NA | BI23: 41831 | BJ23: 41848 | BK23: 45501 | BL23: NA | BM23: NA | BN23: NA | BO23: NA | BP23: NA | BQ23: NA | BR23: NA | BS23: NA | BT23: NA | BU23: NA | BV23: NA | BW23: NA | BX23: NA | BY23: NA | BZ23: NA | CA23: NA | CB23: NA | CC23: NA | CD23: NA | CE23: NA | CF23: NA | CG23: NA | CH23: NA | CI23: NA | CJ23: NA | CK23: NA | CL23: NA | CM23: NA | CN23: NA | CO23: NA | CP23: NA | CQ23: NA | CR23: NA | CS23: NA | CT23: NA | CU23: NA | CV23: NA | CW23: NA | CX23: NA | CY23: NA | CZ23: NA | DA23: NA | DB23: NA | DC23: NA | DD23: NA | DE23: NA | DF23: NA | DG23: NA | DH23: NA | DI23: NA | DJ23: NA | DK23: NA | DL23: NA | DM23: NA | DN23: NA | DO23: NA | DP23: NA | DQ23: NA | DR23: NA | DS23: NA | DT23: NA | DU23: NA | DV23: NA | DW23: NA | DX23: NA | DY23: NA | DZ23: 265 (25/04/2025) | EA23: PENDIENTE | EB23: NA | EC23: NA | ED23: NA | EE23: NA | EF23: NA | EG23: NA | EH23: NA | EI23: NA | EJ23: NA | EK23: NA | EL23: NA | EM23: NA | EN23: NA | EO23: NA | EP23: NA | EQ23: NA | ER23: NA | ES23: NA | ET23: NA | EU23: 10/06/20230 | EV23: 45273 | EW23: NA | EX23: NA | EY23: NA | EZ23: NA | FA23: NA | FC23: NA | FD23: SE DA RESPUESTA 2025ER6314 POR EL OFICIO 2025EE6241 | FE23: KAREN BARERTO | FF23: 45849
A24: 2013ER2135 | B24: 21/005/2024 | C24: CA 077-13 | D24: PENDIENTE | E24: AVICOLA VALLE DE TENZA AVITENZA LIMITADA | F24: 830118457-1 | G24: PIEDRA LARGA | H24: 3164663931 | I24: dadmon.avitenza@gmail.com - avitenza@hotmail.com - sapelo0209@gmail.com | J24: SUTATENZA | K24: NA | L24: SUPERFICIAL | M24: NACIMIENTO | N24: LOS CUROS | O24: NA | P24: NA | Q24: NA | R24: NA | S24: NA | T24: NA | U24: NA | V24: NA | W24: NA | X24: NA | Y24: NA | Z24: NA | AA24: NA | AB24: SIN | AC24: 41442 | AD24: ANA SALINAS | AE24: NA | AF24: 41691 | AG24: WALTER CRUZ | AH24: NA | AI24: NA | AJ24: NA | AK24: NA | AL24: NA | AM24: NA | AN24: 41736 | AO24: SAN ANTONIO | AP24: NA | AQ24: VEREDA PIERDA LARGA | AR24: PECUARIO | AS24: 0.03 | AT24: 0.018 | AU24: 0 | AV24: NA | AW24: NA | AX24: NA | AY24: NA | AZ24: NA | BA24: NA | BB24: NA | BC24: 501 | BD24: 45532 | BE24: NA | BF24: X | BG24: NA | BH24: NA | BI24: 41898 | BJ24: NA | BK24: NA | BL24: NA | BM24: NA | BN24: NA | BO24: NA | BP24: NA | BQ24: NA | BR24: NA | BS24: NA | BT24: NA | BU24: NA | BV24: NA | BW24: NA | BX24: NA | BY24: NA | BZ24: NA | CA24: NA | CB24: NA | CC24: NA | CD24: NA | CE24: NA | CF24: NA | CG24: NA | CH24: NA | CI24: NA | CJ24: NA | CK24: NA | CL24: NA | CM24: NA | CN24: NA | CO24: NA | CP24: NA | CQ24: NA | CR24: NA | CS24: NA | CT24: NA | CU24: NA | CV24: NA | CW24: NA | CX24: NA | CY24: NA | CZ24: NA | DA24: NA | DB24: NA | DC24: 2023ER5774 | DD24: 45091 | DE24: 45610 | DF24: 45642 | DG24: EVELIN LESMES | DH24: RES 154 | DI24: 45751 | DJ24: 45770 | DK24: NA | DL24: NA | DM24: NA | DN24: NA | DO24: NA | DP24: NA | DQ24: NA | DR24: NA | DS24: NA | DT24: NA | DU24: NA | DV24: NA | DW24: NA | DX24: NA | DY24: NA | DZ24: NA | EA24: NA | EB24: NA | EC24: NA | ED24: NA | EE24: NA | EF24: NA | EG24: NA | EH24: NA | EI24: NA | EJ24: NA | EK24: NA | EL24: NA | EM24: NA | EN24: NA | EO24: NA | EP24: NA | EQ24: NA | ER24: NA | ES24: NA | ET24: NA | EU24: NA | EV24: NA | EW24: NA | EX24: NA | EY24: NA | EZ24: NA | FA24: NA | FB24: NA | FC24: NA | FD24: PRORROGADA MEDIANTE LA RES 154 DEL 02/04/2024 | FE24: MILENA GALINDO | FF24: 45754
A25: 2013ER2221 | B25: 41418 | C25: CA 080-13 | E25: AVICOLA LOS CAMBULOS SA | F25: 860058831-4 | G25: CARRERA 5 N 10-125 | H25: 3124486384 | I25: ambiental@avicambulos.com.co | J25: GARAGOA | K25: VEREDA APOSENTOS | L25: SUPERFICIAL | M25: QUEBRADA | N25: LA BATEA | O25: N/A | P25: N/A | Q25: N/A | R25: N/A | S25: N/A | T25: N/A | U25: N/A | V25: N/A | W25: N/A | X25: N/A | Y25: N/A | Z25: N/A | AA25: N/A | AB25: N/A | AC25: N/A | AD25: N/A | AE25: N/A | AF25: N/A | AG25: N/A | AH25: N/A | AI25: N/A | AJ25: N/A | AK25: N/A | AL25: N/A | AM25: N/A | AN25: N/A | AO25: N/A | AP25: N/A | AQ25: N/A | AR25: N/A | AS25: N/A | AT25: N/A | AU25: N/A | AV25: N/A | AW25: N/A | AX25: N/A | AY25: N/A | AZ25: N/A | BA25: N/A | BB25: N/A | BC25: 654 | BD25: 41955 | BF25: X | BI25: 41970 | BJ25: 41988 | BK25: 45641 | BL25: N/A | BM25: N/A | BN25: N/A | BO25: N/A | BP25: N/A | BQ25: N/A | BR25: N/A | BS25: 2025ER1702 | BT25: 45714 | BU25: N/A | BV25: N/A | BW25: N/A | BX25: 293 | BY25: 45776 | BZ25: MILENA GALINDO | CA25: SI | CB25: 2015ER4780 | CC25: 42278 | CD25: 42290 | CE25: 42326 | CF25: MARCO DURAN | CG25: 750 | CH25: 42348 | CI25: JULIAN S | CJ25: SI | CK25: N/A | CL25: N/A | CM25: N/A | CN25: N/A | CO25: N/A | CP25: N/A | CQ25: N/A | CR25: N/A | CS25: N/A | CT25: N/A | CU25: N/A | CV25: N/A | CW25: N/A | CX25: N/A | CY25: N/A | CZ25: N/A | DA25: N/A | DB25: N/A | DC25: N/A | DD25: N/A | DE25: N/A | DF25: N/A | DG25: N/A | DH25: N/A | DI25: N/A | DJ25: N/A | DK25: N/A | DL25: N/A | DM25: N/A | DN25: N/A | DO25: N/A | DP25: N/A | DQ25: N/A | DR25: N/A | DS25: N/A | DT25: N/A | DU25: N/A | DV25: N/A | DW25: N/A | DX25: N/A | DY25: N/A | DZ25: N/A | EA25: N/A | EB25: N/A | EC25: N/A | ED25: N/A | EE25: N/A | EF25: N/A | EG25: N/A | EH25: N/A | EI25: N/A | EJ25: N/A | EK25: N/A | EL25: N/A | EM25: N/A | EN25: N/A | EO25: N/A | EP25: N/A | EQ25: N/A | ER25: N/A | ES25: N/A | ET25: N/A | EU25: N/A | EV25: N/A | EW25: N/A | EX25: N/A | EY25: N/A | EZ25: N/A | FA25: N/A | FB25: N/A | FC25: N/A | FD25: PENDIENTE RECIBO DE OBRAS | FE25: MILENA GALINDO | FF25: 45785
A26: 2013ER2738 | B26: 43276 | C26: CA 083-13 | D26: PENDIENTE | E26: ELVIRA RATIVA DE PARADA | F26: 40011396 | G26: VEREDA BANEGA | H26: 3118773663 | J26: BOYACA | DS26: NA | DT26: NA | DU26: NA | DV26: NA | DW26: NA | DX26: NA | DY26: NA | DZ26: NA | EA26: NA | EB26: NA | EC26: NA | ED26: NA | EE26: NA | EF26: NA | EG26: NA | EH26: NA | EI26: NA | EJ26: NA | EK26: NA | EL26: NA | EM26: NA | EN26: NA | EO26: NA | EP26: NA | EQ26: NA | ER26: NA | ES26: NA | ET26: NA | EU26: NA | EV26: NA | EW26: NA | EX26: NA | EY26: NA | EZ26: NA | FA26: NA | FB26: NA | FC26: NA | FD26: DESITIMIENTO RESOLUION N 532 DE 01/07/2025 | FE26: KAREN BARRETO | FF26: 45849
